Workbook

Sheet MATRIZ CARTA
B2: MATRIZ DE COSTOS
E3: CARTA | K3: SUGERIDO COSTOS | N3: PRECIO FINAL
B4: ENTRADAS | C4: DESCRIPCION | D4: COSTO | E4: VENTA | F4: ICO 8% | G4: BASE | H4: % | I4: RENTABILIDAD | J4: ROTACION | K4: PRECIO SUGERIDO | L4: ICO2 | M4: CARTA | N4: PRECIO N | O4: ICO 8%2 | P4: CARTA | Q4: % | R4: RATION | S4: Incremento 13% | T4: Costo2
A5: 1 | B5: =+ENTRADAS!B88 -> PATACONES MAREA | C5: Patacones de camarones y mango sobre suero costeño. | D5: =+ENTRADAS!K93 -> 7899.1315 | E5: =+ENTRADAS!K94 -> 35000 | F5: =+E5/1.08*0.08 -> 2592.5926 | G5: =+Tabla55[[#This Row],[VENTA]]-Tabla55[[#This Row],[ICO 8%]] -> 32407.407 | H5: =+Tabla55[[#This Row],[COSTO]]/Tabla55[[#This Row],[BASE]] -> 0.24374463 | I5: =+Tabla55[[#This Row],[BASE]]/Tabla55[[#This Row],[COSTO]] -> 4.1026545 | J5: =+VLOOKUP(Tabla55[[#This Row],[ENTRADAS]],#REF!,2,0) -> #REF! | K5: =+D5/(100-65)*100 -> 22568.947 | L5: =+K5/1.08*0.08 -> 1671.7739 | M5: =+Tabla55[[#This Row],[PRECIO SUGERIDO]]+Tabla55[[#This Row],[ICO2]] -> 24240.721 | N5: 35000 | O5: =+N5/1.08*0.08 -> 2592.5926 | P5: =+N5-O5 -> 32407.407 | Q5: =+D5/P5 -> 0.24374463 | R5: =+P5/D5 -> 4.1026545 | S5: 37000 | T5: =+Tabla55[[#This Row],[COSTO]]/Tabla55[[#This Row],[Incremento 13%]] -> 0.21349004
A6: 2 | B6: =+ENTRADAS!B147 -> TACO DE POSTA | D6: =+ENTRADAS!K150 -> 6949.769 | E6: =+ENTRADAS!K151 -> 0 | F6: =+E6/1.08*0.08 -> 0 | G6: =+Tabla55[[#This Row],[VENTA]]-Tabla55[[#This Row],[ICO 8%]] -> 0 | I6: =+Tabla55[[#This Row],[BASE]]/Tabla55[[#This Row],[COSTO]] -> 0 | J6: =+VLOOKUP(Tabla55[[#This Row],[ENTRADAS]],#REF!,2,0) -> #REF! | K6: =+D6/(100-65)*100 -> 19856.483 | L6: =+K6/1.08*0.08 -> 1470.8506 | M6: =+Tabla55[[#This Row],[PRECIO SUGERIDO]]+Tabla55[[#This Row],[ICO2]] -> 21327.333 | N6: =+Tabla55[[#This Row],[VENTA]] -> 0 | O6: =+N6/1.08*0.08 -> 0 | P6: =+N6-O6 -> 0 | Q6: =+D6/P6 -> #DIV/0! | R6: =+P6/D6 -> 0 | S6: =+Tabla55[[#This Row],[VENTA]]*13%+Tabla55[[#This Row],[VENTA]] -> 0 | T6: =+Tabla55[[#This Row],[COSTO]]/Tabla55[[#This Row],[Incremento 13%]] -> #DIV/0!
A7: 3 | B7: =+ENTRADAS!B159 -> TACO DE CHICHARRON | D7: =+ENTRADAS!K162 -> 4248.9094 | E7: =+ENTRADAS!K163 -> 0 | F7: =+E7/1.08*0.08 -> 0 | G7: =+Tabla55[[#This Row],[VENTA]]-Tabla55[[#This Row],[ICO 8%]] -> 0 | I7: =+Tabla55[[#This Row],[BASE]]/Tabla55[[#This Row],[COSTO]] -> 0 | J7: =+VLOOKUP(Tabla55[[#This Row],[ENTRADAS]],#REF!,2,0) -> #REF! | K7: =+D7/(100-65)*100 -> 12139.741 | L7: =+K7/1.08*0.08 -> 899.24008 | M7: =+Tabla55[[#This Row],[PRECIO SUGERIDO]]+Tabla55[[#This Row],[ICO2]] -> 13038.981 | N7: =+Tabla55[[#This Row],[VENTA]] -> 0 | O7: =+N7/1.08*0.08 -> 0 | P7: =+N7-O7 -> 0 | Q7: =+D7/P7 -> #DIV/0! | R7: =+P7/D7 -> 0 | S7: =+Tabla55[[#This Row],[VENTA]]*13%+Tabla55[[#This Row],[VENTA]] -> 0 | T7: =+Tabla55[[#This Row],[COSTO]]/Tabla55[[#This Row],[Incremento 13%]] -> #DIV/0!
A8: 4 | B8: =+ENTRADAS!B131 -> TACO DE CAMARONES | D8: =+ENTRADAS!K134 -> 3630.8447 | E8: =+ENTRADAS!K135 -> 0 | F8: =+E8/1.08*0.08 -> 0 | G8: =+Tabla55[[#This Row],[VENTA]]-Tabla55[[#This Row],[ICO 8%]] -> 0 | I8: =+Tabla55[[#This Row],[BASE]]/Tabla55[[#This Row],[COSTO]] -> 0 | J8: =+VLOOKUP(Tabla55[[#This Row],[ENTRADAS]],#REF!,2,0) -> #REF! | K8: =+D8/(100-65)*100 -> 10373.842 | L8: =+K8/1.08*0.08 -> 768.43274 | M8: =+Tabla55[[#This Row],[PRECIO SUGERIDO]]+Tabla55[[#This Row],[ICO2]] -> 11142.275 | N8: =+Tabla55[[#This Row],[VENTA]] -> 0 | O8: =+N8/1.08*0.08 -> 0 | P8: =+N8-O8 -> 0 | Q8: =+D8/P8 -> #DIV/0! | R8: =+P8/D8 -> 0 | S8: =+Tabla55[[#This Row],[VENTA]]*13%+Tabla55[[#This Row],[VENTA]] -> 0 | T8: =+Tabla55[[#This Row],[COSTO]]/Tabla55[[#This Row],[Incremento 13%]] -> #DIV/0!
A9: 5 | B9: =+ENTRADAS!B115 -> TACO DE PESCADO | D9: =+ENTRADAS!K118 -> 3420.6682 | E9: =+ENTRADAS!K119 -> 0 | F9: =+E9/1.08*0.08 -> 0 | G9: =+Tabla55[[#This Row],[VENTA]]-Tabla55[[#This Row],[ICO 8%]] -> 0 | I9: =+Tabla55[[#This Row],[BASE]]/Tabla55[[#This Row],[COSTO]] -> 0 | J9: =+VLOOKUP(Tabla55[[#This Row],[ENTRADAS]],#REF!,2,0) -> #REF! | K9: =+D9/(100-65)*100 -> 9773.3378 | L9: =+K9/1.08*0.08 -> 723.95095 | M9: =+Tabla55[[#This Row],[PRECIO SUGERIDO]]+Tabla55[[#This Row],[ICO2]] -> 10497.289 | N9: =+Tabla55[[#This Row],[VENTA]] -> 0 | O9: =+N9/1.08*0.08 -> 0 | P9: =+N9-O9 -> 0 | Q9: =+D9/P9 -> #DIV/0! | R9: =+P9/D9 -> 0 | S9: =+Tabla55[[#This Row],[VENTA]]*13%+Tabla55[[#This Row],[VENTA]] -> 0 | T9: =+Tabla55[[#This Row],[COSTO]]/Tabla55[[#This Row],[Incremento 13%]] -> #DIV/0!
A10: 6 | B10: =+ENTRADAS!B251 -> NACHOS MARINEROS | D10: =+ENTRADAS!K254 -> 15446.887 | E10: =+ENTRADAS!K255 -> 49000 | F10: =+E10/1.08*0.08 -> 3629.6296 | G10: =+Tabla55[[#This Row],[VENTA]]-Tabla55[[#This Row],[ICO 8%]] -> 45370.37 | H10: =+Tabla55[[#This Row],[COSTO]]/Tabla55[[#This Row],[BASE]] -> 0.34046199 | I10: =+Tabla55[[#This Row],[BASE]]/Tabla55[[#This Row],[COSTO]] -> 2.9371854 | J10: =+VLOOKUP(Tabla55[[#This Row],[ENTRADAS]],#REF!,2,0) -> #REF! | K10: =+D10/(100-65)*100 -> 44133.962 | L10: =+K10/1.08*0.08 -> 3269.1823 | M10: =+Tabla55[[#This Row],[PRECIO SUGERIDO]]+Tabla55[[#This Row],[ICO2]] -> 47403.144 | N10: 49000 | O10: =+N10/1.08*0.08 -> 3629.6296 | P10: =+N10-O10 -> 45370.37 | Q10: =+D10/P10 -> 0.34046199 | R10: =+P10/D10 -> 2.9371854 | S10: 55000 | T10: =+Tabla55[[#This Row],[COSTO]]/Tabla55[[#This Row],[Incremento 13%]] -> 0.28085248
A11: 7 | B11: =+ENTRADAS!B170 -> CHICHARRONES CARIBEÃ‘OS | C11: Cubos crocantes de chicharrón acompañados con ensalada a la criolla y papas nativas en chimichurri acevichadas al cilantro. | D11: =+ENTRADAS!K173 -> 13198.324 | E11: =+ENTRADAS!K174 -> 39000 | F11: =+E11/1.08*0.08 -> 2888.8889 | G11: =+Tabla55[[#This Row],[VENTA]]-Tabla55[[#This Row],[ICO 8%]] -> 36111.111 | H11: =+Tabla55[[#This Row],[COSTO]]/Tabla55[[#This Row],[BASE]] -> 0.36549205 | I11: =+Tabla55[[#This Row],[BASE]]/Tabla55[[#This Row],[COSTO]] -> 2.7360376 | J11: =+VLOOKUP(Tabla55[[#This Row],[ENTRADAS]],#REF!,2,0) -> #REF! | K11: =+D11/(100-65)*100 -> 37709.497 | L11: =+K11/1.08*0.08 -> 2793.2961 | M11: =+Tabla55[[#This Row],[PRECIO SUGERIDO]]+Tabla55[[#This Row],[ICO2]] -> 40502.793 | N11: 42000 | O11: =+N11/1.08*0.08 -> 3111.1111 | P11: =+N11-O11 -> 38888.889 | Q11: =+D11/P11 -> 0.33938547 | R11: =+P11/D11 -> 2.9465021 | S11: 44000 | T11: =+Tabla55[[#This Row],[COSTO]]/Tabla55[[#This Row],[Incremento 13%]] -> 0.29996191
A12: 8 | B12: =+ENTRADAS!B67 -> PICADA DE MAR | C12: Crocantes anillos de calamar, camarones, palmito y pescado blanco en panko con chips de plátano con topping de cebolla acevichada y salsa de la casa, perfecto para compartir | D12: =+ENTRADAS!K70 -> 14827.464 | E12: =+ENTRADAS!K71 -> 49000 | F12: =+E12/1.08*0.08 -> 3629.6296 | G12: =+Tabla55[[#This Row],[VENTA]]-Tabla55[[#This Row],[ICO 8%]] -> 45370.37 | H12: =+Tabla55[[#This Row],[COSTO]]/Tabla55[[#This Row],[BASE]] -> 0.32680942 | I12: =+Tabla55[[#This Row],[BASE]]/Tabla55[[#This Row],[COSTO]] -> 3.0598873 | J12: =+VLOOKUP(Tabla55[[#This Row],[ENTRADAS]],#REF!,2,0) -> #REF! | K12: =+D12/(100-65)*100 -> 42364.184 | L12: =+K12/1.08*0.08 -> 3138.0877 | M12: =+Tabla55[[#This Row],[PRECIO SUGERIDO]]+Tabla55[[#This Row],[ICO2]] -> 45502.272 | N12: 49000 | O12: =+N12/1.08*0.08 -> 3629.6296 | P12: =+N12-O12 -> 45370.37 | Q12: =+D12/P12 -> 0.32680942 | R12: =+P12/D12 -> 3.0598873 | S12: 55000 | T12: =+Tabla55[[#This Row],[COSTO]]/Tabla55[[#This Row],[Incremento 13%]] -> 0.26959026
A13: 9 | B13: =+ENTRADAS!B219 -> TACO TIERRA | C13: Tortilla de maíz, base de guacamole, posta cartagenera con toping de piñas caramelizadas con ron de coco y chicharrón crocante con pico de gallo. | D13: =+ENTRADAS!K222 -> 9012.4208 | E13: =+ENTRADAS!K223 -> 35000 | F13: =+E13/1.08*0.08 -> 2592.5926 | G13: =+Tabla55[[#This Row],[VENTA]]-Tabla55[[#This Row],[ICO 8%]] -> 32407.407 | H13: =+Tabla55[[#This Row],[COSTO]]/Tabla55[[#This Row],[BASE]] -> 0.27809756 | I13: =+Tabla55[[#This Row],[BASE]]/Tabla55[[#This Row],[COSTO]] -> 3.5958604 | J13: =+VLOOKUP(Tabla55[[#This Row],[ENTRADAS]],#REF!,2,0) -> #REF! | K13: =+D13/(100-65)*100 -> 25749.774 | L13: =+K13/1.08*0.08 -> 1907.3906 | M13: =+Tabla55[[#This Row],[PRECIO SUGERIDO]]+Tabla55[[#This Row],[ICO2]] -> 27657.164 | N13: 35000 | O13: =+N13/1.08*0.08 -> 2592.5926 | P13: =+N13-O13 -> 32407.407 | Q13: =+D13/P13 -> 0.27809756 | R13: =+P13/D13 -> 3.5958604 | S13: 38000 | T13: =+Tabla55[[#This Row],[COSTO]]/Tabla55[[#This Row],[Incremento 13%]] -> 0.23716897
A14: 10 | B14: =+ENTRADAS!B49 -> GRATINADO DE SETAS | C14: Champiñones portobello, orellanas y paris en salsa de queso fundido al vino blanco, acompañado de pan baguette. | D14: =+ENTRADAS!K52 -> 9691.7024 | E14: =+ENTRADAS!K53 -> 39000 | F14: =+E14/1.08*0.08 -> 2888.8889 | G14: =+Tabla55[[#This Row],[VENTA]]-Tabla55[[#This Row],[ICO 8%]] -> 36111.111 | H14: =+Tabla55[[#This Row],[COSTO]]/Tabla55[[#This Row],[BASE]] -> 0.2683856 | I14: =+Tabla55[[#This Row],[BASE]]/Tabla55[[#This Row],[COSTO]] -> 3.7259823 | J14: =+VLOOKUP(Tabla55[[#This Row],[ENTRADAS]],#REF!,2,0) -> #REF! | K14: =+D14/(100-65)*100 -> 27690.578 | L14: =+K14/1.08*0.08 -> 2051.1539 | M14: =+Tabla55[[#This Row],[PRECIO SUGERIDO]]+Tabla55[[#This Row],[ICO2]] -> 29741.732 | N14: 39000 | O14: =+N14/1.08*0.08 -> 2888.8889 | P14: =+N14-O14 -> 36111.111 | Q14: =+D14/P14 -> 0.2683856 | R14: =+P14/D14 -> 3.7259823 | S14: 44000 | T14: =+Tabla55[[#This Row],[COSTO]]/Tabla55[[#This Row],[Incremento 13%]] -> 0.22026596
A15: 11 | B15: =+ENTRADAS!B188 -> PULPO PARRILLADO | C15: Pulpo salteado con vegetales, papas criollas crocantes y suero costeño. | D15: =+ENTRADAS!K191 -> 20520.493 | E15: =+ENTRADAS!K192 -> 85000 | F15: =+E15/1.08*0.08 -> 6296.2963 | G15: =+Tabla55[[#This Row],[VENTA]]-Tabla55[[#This Row],[ICO 8%]] -> 78703.704 | H15: =+Tabla55[[#This Row],[COSTO]]/Tabla55[[#This Row],[BASE]] -> 0.26073097 | I15: =+Tabla55[[#This Row],[BASE]]/Tabla55[[#This Row],[COSTO]] -> 3.835371 | J15: =+VLOOKUP(Tabla55[[#This Row],[ENTRADAS]],#REF!,2,0) -> #REF! | K15: =+D15/(100-65)*100 -> 58629.979 | L15: =+K15/1.08*0.08 -> 4342.9614 | M15: =+Tabla55[[#This Row],[PRECIO SUGERIDO]]+Tabla55[[#This Row],[ICO2]] -> 62972.941 | N15: 85000 | O15: =+N15/1.08*0.08 -> 6296.2963 | P15: =+N15-O15 -> 78703.704 | Q15: =+D15/P15 -> 0.26073097 | R15: =+P15/D15 -> 3.835371 | S15: 92000 | T15: =+Tabla55[[#This Row],[COSTO]]/Tabla55[[#This Row],[Incremento 13%]] -> 0.22304883
A16: 12 | B16: =+ENTRADAS!B233 -> TACO MIXTO | C16: Taco de mar y taco de tierra a elección. | D16: =+ENTRADAS!K236 -> 8362.9656 | E16: =+ENTRADAS!K237 -> 35000 | F16: =+E16/1.08*0.08 -> 2592.5926 | G16: =+Tabla55[[#This Row],[VENTA]]-Tabla55[[#This Row],[ICO 8%]] -> 32407.407 | H16: =+Tabla55[[#This Row],[COSTO]]/Tabla55[[#This Row],[BASE]] -> 0.25805722 | I16: =+Tabla55[[#This Row],[BASE]]/Tabla55[[#This Row],[COSTO]] -> 3.8751095 | J16: =+VLOOKUP(Tabla55[[#This Row],[ENTRADAS]],#REF!,2,0) -> #REF! | K16: =+D16/(100-65)*100 -> 23894.187 | L16: =+K16/1.08*0.08 -> 1769.9398 | M16: =+Tabla55[[#This Row],[PRECIO SUGERIDO]]+Tabla55[[#This Row],[ICO2]] -> 25664.127 | N16: 35000 | O16: =+N16/1.08*0.08 -> 2592.5926 | P16: =+N16-O16 -> 32407.407 | Q16: =+D16/P16 -> 0.25805722 | R16: =+P16/D16 -> 3.8751095 | S16: 38000 | T16: =+Tabla55[[#This Row],[COSTO]]/Tabla55[[#This Row],[Incremento 13%]] -> 0.22007804
A17: 13 | B17: =+ENTRADAS!B6 -> BOCADOS DEL ORIENTE | C17: Palmitos crocantes rellenos de salsa dinamita, acompañados de salsa melcocha. | D17: =+ENTRADAS!K9 -> 6412.5787 | E17: =+ENTRADAS!K10 -> 31000 | F17: =+E17/1.08*0.08 -> 2296.2963 | G17: =+Tabla55[[#This Row],[VENTA]]-Tabla55[[#This Row],[ICO 8%]] -> 28703.704 | H17: =+Tabla55[[#This Row],[COSTO]]/Tabla55[[#This Row],[BASE]] -> 0.22340597 | I17: =+Tabla55[[#This Row],[BASE]]/Tabla55[[#This Row],[COSTO]] -> 4.4761562 | J17: =+VLOOKUP(Tabla55[[#This Row],[ENTRADAS]],#REF!,2,0) -> #REF! | K17: =+D17/(100-65)*100 -> 18321.653 | L17: =+K17/1.08*0.08 -> 1357.1595 | M17: =+Tabla55[[#This Row],[PRECIO SUGERIDO]]+Tabla55[[#This Row],[ICO2]] -> 19678.813 | N17: 31000 | O17: =+N17/1.08*0.08 -> 2296.2963 | P17: =+N17-O17 -> 28703.704 | Q17: =+D17/P17 -> 0.22340597 | R17: =+P17/D17 -> 4.4761562 | S17: 35000 | T17: =+Tabla55[[#This Row],[COSTO]]/Tabla55[[#This Row],[Incremento 13%]] -> 0.18321653
A18: 14 | B18: =+ENTRADAS!B17 -> DEDOS DE QUESO COSTEÃ‘O | C18: Queso costeño frito acompañado de mermelada de ají. | D18: =+ENTRADAS!K20 -> 5327.9285 | E18: =+ENTRADAS!K21 -> 26000 | F18: =+E18/1.08*0.08 -> 1925.9259 | G18: =+Tabla55[[#This Row],[VENTA]]-Tabla55[[#This Row],[ICO 8%]] -> 24074.074 | H18: =+Tabla55[[#This Row],[COSTO]]/Tabla55[[#This Row],[BASE]] -> 0.22131395 | I18: =+Tabla55[[#This Row],[BASE]]/Tabla55[[#This Row],[COSTO]] -> 4.5184679 | J18: =+VLOOKUP(Tabla55[[#This Row],[ENTRADAS]],#REF!,2,0) -> #REF! | K18: =+D18/(100-65)*100 -> 15222.653 | L18: =+K18/1.08*0.08 -> 1127.6039 | M18: =+Tabla55[[#This Row],[PRECIO SUGERIDO]]+Tabla55[[#This Row],[ICO2]] -> 16350.257 | N18: 26000 | O18: =+N18/1.08*0.08 -> 1925.9259 | P18: =+N18-O18 -> 24074.074 | Q18: =+D18/P18 -> 0.22131395 | R18: =+P18/D18 -> 4.5184679 | S18: 29000 | T18: =+Tabla55[[#This Row],[COSTO]]/Tabla55[[#This Row],[Incremento 13%]] -> 0.18372167
A19: 15 | B19: =+ENTRADAS!B205 -> TACO DE MAR | C19: Tortilla de maíz, mézclum con aceite de trufa, camarones apanados y pescado tempurizado con vinagreta mediterránea y salsa tártara. | D19: =+ENTRADAS!K208 -> 6981.1971 | E19: =+ENTRADAS!K209 -> 35000 | F19: =+E19/1.08*0.08 -> 2592.5926 | G19: =+Tabla55[[#This Row],[VENTA]]-Tabla55[[#This Row],[ICO 8%]] -> 32407.407 | H19: =+Tabla55[[#This Row],[COSTO]]/Tabla55[[#This Row],[BASE]] -> 0.2154198 | I19: =+Tabla55[[#This Row],[BASE]]/Tabla55[[#This Row],[COSTO]] -> 4.6420989 | J19: =+VLOOKUP(Tabla55[[#This Row],[ENTRADAS]],#REF!,2,0) -> #REF! | K19: =+D19/(100-65)*100 -> 19946.278 | L19: =+K19/1.08*0.08 -> 1477.502 | M19: =+Tabla55[[#This Row],[PRECIO SUGERIDO]]+Tabla55[[#This Row],[ICO2]] -> 21423.78 | N19: 35000 | O19: =+N19/1.08*0.08 -> 2592.5926 | P19: =+N19-O19 -> 32407.407 | Q19: =+D19/P19 -> 0.2154198 | R19: =+P19/D19 -> 4.6420989 | S19: 38000 | T19: =+Tabla55[[#This Row],[COSTO]]/Tabla55[[#This Row],[Incremento 13%]] -> 0.18371571
A20: 16 | B20: =+ENTRADAS!B29 -> GRATINADO DE JAIBA | C20: Carne de cangrejo gratinada en salsa de la casa acompañada de pan baguette. | D20: =+ENTRADAS!K32 -> 7468.0028 | E20: =+ENTRADAS!K33 -> 41000 | F20: =+E20/1.08*0.08 -> 3037.037 | G20: =+Tabla55[[#This Row],[VENTA]]-Tabla55[[#This Row],[ICO 8%]] -> 37962.963 | H20: =+Tabla55[[#This Row],[COSTO]]/Tabla55[[#This Row],[BASE]] -> 0.19671812 | I20: =+Tabla55[[#This Row],[BASE]]/Tabla55[[#This Row],[COSTO]] -> 5.0834157 | J20: =+VLOOKUP(Tabla55[[#This Row],[ENTRADAS]],#REF!,2,0) -> #REF! | K20: =+D20/(100-65)*100 -> 21337.151 | L20: =+K20/1.08*0.08 -> 1580.5297 | M20: =+Tabla55[[#This Row],[PRECIO SUGERIDO]]+Tabla55[[#This Row],[ICO2]] -> 22917.681 | N20: 41000 | O20: =+N20/1.08*0.08 -> 3037.037 | P20: =+N20-O20 -> 37962.963 | Q20: =+D20/P20 -> 0.19671812 | R20: =+P20/D20 -> 5.0834157 | S20: 46000 | T20: =+Tabla55[[#This Row],[COSTO]]/Tabla55[[#This Row],[Incremento 13%]] -> 0.16234789
B21: =+ENTRADAS!B103 -> CROQUETAS CREMOSA DE JAIBA | C21: Croqueta cremosa de carne de cangrejo al estilo español | D21: =+ENTRADAS!K106 -> 4572.1884 | E21: =+ENTRADAS!K107 -> 35000 | F21: =+E21/1.08*0.08 -> 2592.5926 | G21: =+Tabla55[[#This Row],[VENTA]]-Tabla55[[#This Row],[ICO 8%]] -> 32407.407 | H21: =+Tabla55[[#This Row],[COSTO]]/Tabla55[[#This Row],[BASE]] -> 0.14108467 | I21: =+Tabla55[[#This Row],[BASE]]/Tabla55[[#This Row],[COSTO]] -> 7.0879423 | J21: =+VLOOKUP(Tabla55[[#This Row],[ENTRADAS]],#REF!,2,0) -> #REF! | K21: =+D21/(100-65)*100 -> 13063.395 | L21: =+K21/1.08*0.08 -> 967.65891 | M21: =+Tabla55[[#This Row],[PRECIO SUGERIDO]]+Tabla55[[#This Row],[ICO2]] -> 14031.054 | N21: 35000 | O21: =+N21/1.08*0.08 -> 2592.5926 | P21: =+N21-O21 -> 32407.407 | Q21: =+D21/P21 -> 0.14108467 | R21: =+P21/D21 -> 7.0879423 | S21: 38000 | T21: =+Tabla55[[#This Row],[COSTO]]/Tabla55[[#This Row],[Incremento 13%]] -> 0.12032075
B22: Total | H22: =SUBTOTAL(101,Tabla55[%]) -> 0.25690169 | J22: =SUBTOTAL(109,Tabla55[ROTACION]) -> #REF! | R22: =SUBTOTAL(109,Tabla55[RATION]) -> 53.886634
E26: CARTA | K26: SUGERIDO COSTOS | N26: PRECIO FINAL
B27: LOS ARREBATOS DEL CHEF | C27: DESCRIPCION | D27: COSTO | E27: VENTA | F27: ICO 8% | G27: BASE | H27: % | I27: RENTABILIDAD | J27: ROTACION | K27: PRECIO SUGERIDO | L27: ICO2 | M27: CARTA | N27: PRECIO N | O27: ICO 8%2 | P27: CARTA | Q27: % | R27: RATION | S27: Incremento 13% | T27: Costo2
A28: 1 | B28: =+'LOS ARREBATOS DEL CHEF'!B5 -> PESCA MALANGA | D28: =+'LOS ARREBATOS DEL CHEF'!K8 -> 25181.786 | E28: 66000 | F28: =+E28/1.08*0.08 -> 4888.8889 | G28: =+Tabla5557319[[#This Row],[VENTA]]-Tabla5557319[[#This Row],[ICO 8%]] -> 61111.111 | H28: =+Tabla5557319[[#This Row],[COSTO]]/Tabla5557319[[#This Row],[BASE]] -> 0.41206559 | I28: =+Tabla5557319[[#This Row],[BASE]]/Tabla5557319[[#This Row],[COSTO]] -> 2.4267981 | J28: =+VLOOKUP(Tabla5557319[[#This Row],[LOS ARREBATOS DEL CHEF]],#REF!,2,0) -> #REF! | K28: =+D28/(100-65)*100 -> 71947.96 | L28: =+K28/1.08*0.08 -> 5329.4785 | M28: =+Tabla5557319[[#This Row],[PRECIO SUGERIDO]]+Tabla5557319[[#This Row],[ICO2]] -> 77277.438 | N28: 66000 | O28: =+N28/1.08*0.08 -> 4888.8889 | P28: =+N28-O28 -> 61111.111 | Q28: =+D28/P28 -> 0.41206559 | R28: =+P28/D28 -> 2.4267981 | S28: 79000 | T28: =+Tabla5557319[[#This Row],[COSTO]]/Tabla5557319[[#This Row],[Incremento 13%]] -> 0.31875678
A29: 2 | B29: =+'LOS ARREBATOS DEL CHEF'!B29 -> RISOTTO Y PESCA BLANCA TROPICAL | C29: Pesca en mantequilla de romero con arroz arbóreo de rocoto y coco, vejetales salteados acompañado de chips de yuca y batata | D29: =+'LOS ARREBATOS DEL CHEF'!K32 -> 21443.446 | E29: 74000 | F29: =+E29/1.08*0.08 -> 5481.4815 | G29: =+Tabla5557319[[#This Row],[VENTA]]-Tabla5557319[[#This Row],[ICO 8%]] -> 68518.519 | H29: =+Tabla5557319[[#This Row],[COSTO]]/Tabla5557319[[#This Row],[BASE]] -> 0.31295839 | I29: =+Tabla5557319[[#This Row],[BASE]]/Tabla5557319[[#This Row],[COSTO]] -> 3.1953129 | J29: =+VLOOKUP(Tabla5557319[[#This Row],[LOS ARREBATOS DEL CHEF]],#REF!,2,0) -> #REF! | K29: =+D29/(100-65)*100 -> 61266.987 | L29: =+K29/1.08*0.08 -> 4538.2953 | M29: =+Tabla5557319[[#This Row],[PRECIO SUGERIDO]]+Tabla5557319[[#This Row],[ICO2]] -> 65805.283 | N29: 74000 | O29: =+N29/1.08*0.08 -> 5481.4815 | P29: =+N29-O29 -> 68518.519 | Q29: =+D29/P29 -> 0.31295839 | R29: =+P29/D29 -> 3.1953129 | S29: 77000 | T29: =+Tabla5557319[[#This Row],[COSTO]]/Tabla5557319[[#This Row],[Incremento 13%]] -> 0.27848631
A30: 4 | B30: =+'LOS ARREBATOS DEL CHEF'!B58 -> ARROZ DEL CARIBE | C30: Farsa de contramuslo con queso y albahaca, acompañada de puré de maduro, salsa de coco y ají amarillo, crocantes de vainilla y ensalada | D30: =+'LOS ARREBATOS DEL CHEF'!K61 -> 14664.997 | E30: 54000 | F30: =+E30/1.08*0.08 -> 4000 | G30: =+Tabla5557319[[#This Row],[VENTA]]-Tabla5557319[[#This Row],[ICO 8%]] -> 50000 | H30: =+Tabla5557319[[#This Row],[COSTO]]/Tabla5557319[[#This Row],[BASE]] -> 0.29329993 | I30: =+Tabla5557319[[#This Row],[BASE]]/Tabla5557319[[#This Row],[COSTO]] -> 3.4094791 | J30: =+VLOOKUP(Tabla5557319[[#This Row],[LOS ARREBATOS DEL CHEF]],#REF!,2,0) -> #REF! | K30: =+D30/(100-65)*100 -> 41899.99 | L30: =+K30/1.08*0.08 -> 3103.703 | M30: =+Tabla5557319[[#This Row],[PRECIO SUGERIDO]]+Tabla5557319[[#This Row],[ICO2]] -> 45003.693 | N30: 54000 | O30: =+N30/1.08*0.08 -> 4000 | P30: =+N30-O30 -> 50000 | Q30: =+D30/P30 -> 0.29329993 | R30: =+P30/D30 -> 3.4094791 | S30: 61000 | T30: =+Tabla5557319[[#This Row],[COSTO]]/Tabla5557319[[#This Row],[Incremento 13%]] -> 0.24040978
B31: =+'LOS ARREBATOS DEL CHEF'!B76 -> SOPA DE CANGREJO | D31: =+'LOS ARREBATOS DEL CHEF'!K79 -> 17987.894 | F31: =+E31/1.08*0.08 -> 0 | G31: =+Tabla5557319[[#This Row],[VENTA]]-Tabla5557319[[#This Row],[ICO 8%]] -> 0 | H31: =+Tabla5557319[[#This Row],[COSTO]]/Tabla5557319[[#This Row],[BASE]] -> #DIV/0! | I31: =+Tabla5557319[[#This Row],[BASE]]/Tabla5557319[[#This Row],[COSTO]] -> 0 | J31: =+VLOOKUP(Tabla5557319[[#This Row],[LOS ARREBATOS DEL CHEF]],#REF!,2,0) -> #REF! | K31: =+D31/(100-65)*100 -> 51393.982 | L31: =+K31/1.08*0.08 -> 3806.9617 | M31: =+Tabla5557319[[#This Row],[PRECIO SUGERIDO]]+Tabla5557319[[#This Row],[ICO2]] -> 55200.944 | O31: =+N31/1.08*0.08 -> 0 | P31: =+N31-O31 -> 0 | Q31: =+D31/P31 -> #DIV/0! | R31: =+P31/D31 -> 0 | S31: 59000 | T31: =+Tabla5557319[[#This Row],[COSTO]]/Tabla5557319[[#This Row],[Incremento 13%]] -> 0.30487956
B32: =+'LOS ARREBATOS DEL CHEF'!B95 -> GAMBAS | D32: =+'LOS ARREBATOS DEL CHEF'!K98 -> 19126.897 | F32: =+E32/1.08*0.08 -> 0 | G32: =+Tabla5557319[[#This Row],[VENTA]]-Tabla5557319[[#This Row],[ICO 8%]] -> 0 | H32: =+Tabla5557319[[#This Row],[COSTO]]/Tabla5557319[[#This Row],[BASE]] -> #DIV/0! | I32: =+Tabla5557319[[#This Row],[BASE]]/Tabla5557319[[#This Row],[COSTO]] -> 0 | J32: =+VLOOKUP(Tabla5557319[[#This Row],[LOS ARREBATOS DEL CHEF]],#REF!,2,0) -> #REF! | K32: =+D32/(100-65)*100 -> 54648.277 | L32: =+K32/1.08*0.08 -> 4048.0205 | M32: =+Tabla5557319[[#This Row],[PRECIO SUGERIDO]]+Tabla5557319[[#This Row],[ICO2]] -> 58696.297 | O32: =+N32/1.08*0.08 -> 0 | P32: =+N32-O32 -> 0 | Q32: =+D32/P32 -> #DIV/0! | R32: =+P32/D32 -> 0 | S32: 62000 | T32: =+Tabla5557319[[#This Row],[COSTO]]/Tabla5557319[[#This Row],[Incremento 13%]] -> 0.30849834
H33: =SUBTOTAL(101,Tabla5557319[%]) -> #DIV/0! | J33: =SUBTOTAL(109,Tabla5557319[ROTACION]) -> #REF! | R33: =SUBTOTAL(109,Tabla5557319[RATION]) -> 9.0315902
E36: CARTA | K36: SUGERIDO COSTOS | N36: PRECIO FINAL
B37: LANGOSTINOS | C37: DESCRIPCION | D37: COSTO | E37: VENTA | F37: ICO 8% | G37: BASE | H37: % | I37: RENTABILIDAD | J37: ROTACION | K37: PRECIO SUGERIDO | L37: ICO2 | M37: CARTA | N37: PRECIO N | O37: ICO 8%2 | P37: CARTA | Q37: % | R37: RATION | S37: Incremento 13% | T37: Costo2
A38: 1 | B38: =+LANGOSTINOS!B6 -> LANGOSTINOS ARREBATADOS | C38: Langostinos crocantes en salsa de queso al rocoto, con puré de papa a la parmesana | D38: =+LANGOSTINOS!K9 -> 16534.078 | E38: =+LANGOSTINOS!K10 -> 56000 | F38: =+E38/1.08*0.08 -> 4148.1481 | G38: =+Tabla5557[[#This Row],[VENTA]]-Tabla5557[[#This Row],[ICO 8%]] -> 51851.852 | H38: =+Tabla5557[[#This Row],[COSTO]]/Tabla5557[[#This Row],[BASE]] -> 0.3188715 | I38: =+Tabla5557[[#This Row],[BASE]]/Tabla5557[[#This Row],[COSTO]] -> 3.1360595 | J38: =+VLOOKUP(Tabla5557[[#This Row],[LANGOSTINOS]],#REF!,2,0) -> #REF! | K38: =+D38/(100-65)*100 -> 47240.222 | L38: =+K38/1.08*0.08 -> 3499.2757 | M38: =+Tabla5557[[#This Row],[PRECIO SUGERIDO]]+Tabla5557[[#This Row],[ICO2]] -> 50739.497 | N38: 56000 | O38: =+N38/1.08*0.08 -> 4148.1481 | P38: =+N38-O38 -> 51851.852 | Q38: =+D38/P38 -> 0.3188715 | R38: =+P38/D38 -> 3.1360595 | S38: 60000 | T38: =+Tabla5557[[#This Row],[COSTO]]/Tabla5557[[#This Row],[Incremento 13%]] -> 0.27556796
A39: 2 | B39: =+LANGOSTINOS!B38 -> LANGOSTINOS TIMBIQUI | C39: Langostinos crocantes albardados con tocino, sobre arroz de ají amarillo y reducción de balsámico. | D39: =+LANGOSTINOS!K41 -> 14394.66 | E39: =+LANGOSTINOS!K42 -> 59000 | F39: =+E39/1.08*0.08 -> 4370.3704 | G39: =+Tabla5557[[#This Row],[VENTA]]-Tabla5557[[#This Row],[ICO 8%]] -> 54629.63 | H39: =+Tabla5557[[#This Row],[COSTO]]/Tabla5557[[#This Row],[BASE]] -> 0.26349547 | I39: =+Tabla5557[[#This Row],[BASE]]/Tabla5557[[#This Row],[COSTO]] -> 3.7951316 | J39: =+VLOOKUP(Tabla5557[[#This Row],[LANGOSTINOS]],#REF!,2,0) -> #REF! | K39: =+D39/(100-65)*100 -> 41127.6 | L39: =+K39/1.08*0.08 -> 3046.4889 | M39: =+Tabla5557[[#This Row],[PRECIO SUGERIDO]]+Tabla5557[[#This Row],[ICO2]] -> 44174.089 | N39: 59000 | O39: =+N39/1.08*0.08 -> 4370.3704 | P39: =+N39-O39 -> 54629.63 | Q39: =+D39/P39 -> 0.26349547 | R39: =+P39/D39 -> 3.7951316 | S39: 59000 | T39: =+Tabla5557[[#This Row],[COSTO]]/Tabla5557[[#This Row],[Incremento 13%]] -> 0.24397729
A40: 3 | B40: =+LANGOSTINOS!B24 -> LANGOSTINOS EN COCO Y CURRY | C40: Langostinos al coco y curry servido sobre puré de papas, tomates perla y queso parmesano. | D40: =+LANGOSTINOS!K27 -> 13533.059 | E40: =+LANGOSTINOS!K28 -> 56000 | F40: =+E40/1.08*0.08 -> 4148.1481 | G40: =+Tabla5557[[#This Row],[VENTA]]-Tabla5557[[#This Row],[ICO 8%]] -> 51851.852 | H40: =+Tabla5557[[#This Row],[COSTO]]/Tabla5557[[#This Row],[BASE]] -> 0.26099471 | I40: =+Tabla5557[[#This Row],[BASE]]/Tabla5557[[#This Row],[COSTO]] -> 3.8314953 | J40: =+VLOOKUP(Tabla5557[[#This Row],[LANGOSTINOS]],#REF!,2,0) -> #REF! | K40: =+D40/(100-65)*100 -> 38665.883 | L40: =+K40/1.08*0.08 -> 2864.1395 | M40: =+Tabla5557[[#This Row],[PRECIO SUGERIDO]]+Tabla5557[[#This Row],[ICO2]] -> 41530.023 | N40: 56000 | O40: =+N40/1.08*0.08 -> 4148.1481 | P40: =+N40-O40 -> 51851.852 | Q40: =+D40/P40 -> 0.26099471 | R40: =+P40/D40 -> 3.8314953 | S40: 61000 | T40: =+Tabla5557[[#This Row],[COSTO]]/Tabla5557[[#This Row],[Incremento 13%]] -> 0.22185343
B41: Total | H41: =SUBTOTAL(101,Tabla5557[%]) -> 0.28112056 | J41: =SUBTOTAL(109,Tabla5557[ROTACION]) -> #REF! | R41: =SUBTOTAL(109,Tabla5557[RATION]) -> 10.762686
E44: CARTA | K44: SUGERIDO COSTOS | N44: PRECIO FINAL
B45: CEVICHES | C45: DESCRIPCION | D45: COSTO | E45: VENTA | F45: ICO 8% | G45: BASE | H45: % | I45: RENTABILIDAD | J45: ROTACION | K45: PRECIO SUGERIDO | L45: ICO2 | M45: CARTA | N45: PRECIO N | O45: ICO 8%2 | P45: CARTA | Q45: % | R45: RATION | S45: Incremento 13% | T45: Costo2
A46: 1 | B46: =+CEVICHES!B27 -> CEVICHE DE CHICHARRON | C46: Trozos crocantes de chicharrón bañados en salsa de rocoto, mix de cebollas, tomate cherry rojo, chips de plátano. | D46: =+CEVICHES!K30 -> 14183.873 | E46: =+CEVICHES!K31 -> 46000 | F46: =+E46/1.08*0.08 -> 3407.4074 | G46: =+Tabla5557273[[#This Row],[VENTA]]-Tabla5557273[[#This Row],[ICO 8%]] -> 42592.593 | H46: =+Tabla5557273[[#This Row],[COSTO]]/Tabla5557273[[#This Row],[BASE]] -> 0.33301267 | I46: =+Tabla5557273[[#This Row],[BASE]]/Tabla5557273[[#This Row],[COSTO]] -> 3.0028888 | J46: =+VLOOKUP(Tabla5557273[[#This Row],[CEVICHES]],#REF!,2,0) -> #REF! | K46: =+D46/(100-65)*100 -> 40525.351 | L46: =+K46/1.08*0.08 -> 3001.8778 | M46: =+Tabla5557273[[#This Row],[PRECIO SUGERIDO]]+Tabla5557273[[#This Row],[ICO2]] -> 43527.229 | N46: 46000 | O46: =+N46/1.08*0.08 -> 3407.4074 | P46: =+N46-O46 -> 42592.593 | Q46: =+D46/P46 -> 0.33301267 | R46: =+P46/D46 -> 3.0028888 | S46: 49000 | T46: =+Tabla5557273[[#This Row],[COSTO]]/Tabla5557273[[#This Row],[Incremento 13%]] -> 0.28946679
A47: 2 | B47: =+CEVICHES!B41 -> CEVICHE MIRAFLORES | C47: Ceviche mixto de pescado blanco y calamar marinado en leche de tigre, ají peruano, acompañado de una base de vegetales al fresco, trozos de aguacate y papas nativas. | D47: =+CEVICHES!K44 -> 16688.921 | E47: =+CEVICHES!K45 -> 48000 | F47: =+E47/1.08*0.08 -> 3555.5556 | G47: =+Tabla5557273[[#This Row],[VENTA]]-Tabla5557273[[#This Row],[ICO 8%]] -> 44444.444 | H47: =+Tabla5557273[[#This Row],[COSTO]]/Tabla5557273[[#This Row],[BASE]] -> 0.37550072 | I47: =+Tabla5557273[[#This Row],[BASE]]/Tabla5557273[[#This Row],[COSTO]] -> 2.6631108 | J47: =+VLOOKUP(Tabla5557273[[#This Row],[CEVICHES]],#REF!,2,0) -> #REF! | K47: =+D47/(100-65)*100 -> 47682.631 | L47: =+K47/1.08*0.08 -> 3532.0467 | M47: =+Tabla5557273[[#This Row],[PRECIO SUGERIDO]]+Tabla5557273[[#This Row],[ICO2]] -> 51214.677 | N47: 51000 | O47: =+N47/1.08*0.08 -> 3777.7778 | P47: =+N47-O47 -> 47222.222 | Q47: =+D47/P47 -> 0.35341244 | R47: =+P47/D47 -> 2.8295552 | S47: 54000 | T47: =+Tabla5557273[[#This Row],[COSTO]]/Tabla5557273[[#This Row],[Incremento 13%]] -> 0.30905409
A48: 3 | B48: =+CEVICHES!B6 -> COCTEL CARTAGENERO | C48: Cóctel de camarón en salsa rosada, vino blanco y piña en trozos, acompañado de patacones crocantes, brotes frescos y masago. | D48: =+CEVICHES!K9 -> 14314.865 | E48: =+CEVICHES!K10 -> 48000 | F48: =+E48/1.08*0.08 -> 3555.5556 | G48: =+Tabla5557273[[#This Row],[VENTA]]-Tabla5557273[[#This Row],[ICO 8%]] -> 44444.444 | H48: =+Tabla5557273[[#This Row],[COSTO]]/Tabla5557273[[#This Row],[BASE]] -> 0.32208446 | I48: =+Tabla5557273[[#This Row],[BASE]]/Tabla5557273[[#This Row],[COSTO]] -> 3.1047757 | J48: =+VLOOKUP(Tabla5557273[[#This Row],[CEVICHES]],#REF!,2,0) -> #REF! | K48: =+D48/(100-65)*100 -> 40899.614 | L48: =+K48/1.08*0.08 -> 3029.601 | M48: =+Tabla5557273[[#This Row],[PRECIO SUGERIDO]]+Tabla5557273[[#This Row],[ICO2]] -> 43929.215 | N48: 43000 | O48: =+N48/1.08*0.08 -> 3185.1852 | P48: =+N48-O48 -> 39814.815 | Q48: =+D48/P48 -> 0.35953614 | R48: =+P48/D48 -> 2.7813616 | S48: 54000 | T48: =+Tabla5557273[[#This Row],[COSTO]]/Tabla5557273[[#This Row],[Incremento 13%]] -> 0.26509009
A49: 4 | B49: =+CEVICHES!B61 -> CEVICHE TRUFADO | C49: Cubos de pesca blanca en una cremosa leche de tigre en salsa de trufa. Acompañado de camarones crocantes y un topping de puerro crocante. | D49: =+CEVICHES!K64 -> 16251.53 | E49: =+CEVICHES!K65 -> 52000 | F49: =+E49/1.08*0.08 -> 3851.8519 | G49: =+Tabla5557273[[#This Row],[VENTA]]-Tabla5557273[[#This Row],[ICO 8%]] -> 48148.148 | H49: =+Tabla5557273[[#This Row],[COSTO]]/Tabla5557273[[#This Row],[BASE]] -> 0.33753177 | I49: =+Tabla5557273[[#This Row],[BASE]]/Tabla5557273[[#This Row],[COSTO]] -> 2.9626841 | J49: =+VLOOKUP(Tabla5557273[[#This Row],[CEVICHES]],#REF!,2,0) -> #REF! | K49: =+D49/(100-65)*100 -> 46432.942 | L49: =+K49/1.08*0.08 -> 3439.4772 | M49: =+Tabla5557273[[#This Row],[PRECIO SUGERIDO]]+Tabla5557273[[#This Row],[ICO2]] -> 49872.419 | N49: 49000 | O49: =+N49/1.08*0.08 -> 3629.6296 | P49: =+N49-O49 -> 45370.37 | Q49: =+D49/P49 -> 0.35819698 | R49: =+P49/D49 -> 2.79176 | S49: 58000 | T49: =+Tabla5557273[[#This Row],[COSTO]]/Tabla5557273[[#This Row],[Incremento 13%]] -> 0.28019879
A50: 5 | B50: =+CEVICHES!B81 -> CEVICHE ARENA BLANCA | C50: Ceviche de calamar y camarón en leche de tigre, papas criollas crocantes, trozos de aguacate y queso parmesano. | D50: =+CEVICHES!K84 -> 13015.226 | E50: =+CEVICHES!K85 -> 44000 | F50: =+E50/1.08*0.08 -> 3259.2593 | G50: =+Tabla5557273[[#This Row],[VENTA]]-Tabla5557273[[#This Row],[ICO 8%]] -> 40740.741 | H50: =+Tabla5557273[[#This Row],[COSTO]]/Tabla5557273[[#This Row],[BASE]] -> 0.31946463 | I50: =+Tabla5557273[[#This Row],[BASE]]/Tabla5557273[[#This Row],[COSTO]] -> 3.130237 | J50: =+VLOOKUP(Tabla5557273[[#This Row],[CEVICHES]],#REF!,2,0) -> #REF! | K50: =+D50/(100-65)*100 -> 37186.359 | L50: =+K50/1.08*0.08 -> 2754.5451 | M50: =+Tabla5557273[[#This Row],[PRECIO SUGERIDO]]+Tabla5557273[[#This Row],[ICO2]] -> 39940.904 | N50: 39000 | O50: =+N50/1.08*0.08 -> 2888.8889 | P50: =+N50-O50 -> 36111.111 | Q50: =+D50/P50 -> 0.36042163 | R50: =+P50/D50 -> 2.7745282 | S50: 46000 | T50: =+Tabla5557273[[#This Row],[COSTO]]/Tabla5557273[[#This Row],[Incremento 13%]] -> 0.28293969
B51: Total | H51: =SUBTOTAL(101,Tabla5557273[%]) -> 0.33751885 | J51: =SUBTOTAL(109,Tabla5557273[ROTACION]) -> #REF! | R51: =SUBTOTAL(109,Tabla5557273[RATION]) -> 14.180094
E55: CARTA | K55: SUGERIDO COSTOS | N55: PRECIO FINAL
B56: ENSALADAS | C56: DESCRIPCION | D56: COSTO | E56: VENTA | F56: ICO 8% | G56: BASE | H56: % | I56: RENTABILIDAD | J56: ROTACION | K56: PRECIO SUGERIDO | L56: ICO2 | M56: CARTA | N56: PRECIO N | O56: ICO 8%2 | P56: CARTA | Q56: % | R56: RATION | S56: Incremento 13% | T56: Costo2
A57: 1 | B57: =+ENSALADAS!B20 -> ENSALADA DEL TROPICO | C57: Mezclum de lechugas, queso costeño, piña, tomates despelucados, coco deshidratado con aderezo mayo-hierbabuena. | D57: =+ENSALADAS!K24 -> 7790.2541 | E57: =+ENSALADAS!K25 -> 32000 | F57: =+E57/1.08*0.08 -> 2370.3704 | G57: =+Tabla5557274[[#This Row],[VENTA]]-Tabla5557274[[#This Row],[ICO 8%]] -> 29629.63 | H57: =+Tabla5557274[[#This Row],[COSTO]]/Tabla5557274[[#This Row],[BASE]] -> 0.26292108 | I57: =+Tabla5557274[[#This Row],[BASE]]/Tabla5557274[[#This Row],[COSTO]] -> 3.8034227 | J57: =+VLOOKUP(Tabla5557274[[#This Row],[ENSALADAS]],#REF!,2,0) -> #REF! | K57: =+D57/(100-65)*100 -> 22257.869 | L57: =+K57/1.08*0.08 -> 1648.731 | M57: =+Tabla5557274[[#This Row],[PRECIO SUGERIDO]]+Tabla5557274[[#This Row],[ICO2]] -> 23906.6 | N57: 32000 | O57: =+N57/1.08*0.08 -> 2370.3704 | P57: =+N57-O57 -> 29629.63 | Q57: =+D57/P57 -> 0.26292108 | R57: =+P57/D57 -> 3.8034227 | S57: 36000 | T57: =+Tabla5557274[[#This Row],[COSTO]]/Tabla5557274[[#This Row],[Incremento 13%]] -> 0.21639595
A58: 2 | B58: =+ENSALADAS!B6 -> ENSALADA MEDITERRANEA | C58: Mezclum de lechugas, variedad de tomates, cebolla encurtida, aceitunas y queso parmesano en escamas con aderezo mayo-balsámico. | D58: =+ENSALADAS!K9 -> 10849.059 | E58: =+ENSALADAS!K10 -> 34000 | F58: =+E58/1.08*0.08 -> 2518.5185 | G58: =+Tabla5557274[[#This Row],[VENTA]]-Tabla5557274[[#This Row],[ICO 8%]] -> 31481.481 | H58: =+Tabla5557274[[#This Row],[COSTO]]/Tabla5557274[[#This Row],[BASE]] -> 0.34461716 | I58: =+Tabla5557274[[#This Row],[BASE]]/Tabla5557274[[#This Row],[COSTO]] -> 2.9017707 | J58: =+VLOOKUP(Tabla5557274[[#This Row],[ENSALADAS]],#REF!,2,0) -> #REF! | K58: =+D58/(100-65)*100 -> 30997.311 | L58: =+K58/1.08*0.08 -> 2296.0971 | M58: =+Tabla5557274[[#This Row],[PRECIO SUGERIDO]]+Tabla5557274[[#This Row],[ICO2]] -> 33293.408 | N58: 34000 | O58: =+N58/1.08*0.08 -> 2518.5185 | P58: =+N58-O58 -> 31481.481 | Q58: =+D58/P58 -> 0.34461716 | R58: =+P58/D58 -> 2.9017707 | S58: 38000 | T58: =+Tabla5557274[[#This Row],[COSTO]]/Tabla5557274[[#This Row],[Incremento 13%]] -> 0.28550155
B59: Total | H59: =SUBTOTAL(101,Tabla5557274[%]) -> 0.30376912 | J59: =SUBTOTAL(109,Tabla5557274[ROTACION]) -> #REF! | R59: =SUBTOTAL(109,Tabla5557274[RATION]) -> 6.7051935
E63: CARTA | K63: SUGERIDO COSTOS | N63: PRECIO FINAL
B64: ARROCES | C64: DESCRIPCION | D64: COSTO | E64: VENTA | F64: ICO 8% | G64: BASE | H64: % | I64: RENTABILIDAD | J64: ROTACION | K64: PRECIO SUGERIDO | L64: ICO2 | M64: CARTA | N64: PRECIO N | O64: ICO 8%2 | P64: CARTA | Q64: % | R64: RATION | S64: Incremento 13% | T64: Costo2
B65: =+ARROCES!B68 -> ARROZ HOLANDÃ‰S | C65: Arroz cremoso de queso parmesano, con solomito y camarón con un topin de puerro crocante. | D65: =+ARROCES!K71 -> 18745.681 | E65: =+ARROCES!K72 -> 56000 | F65: =+E65/1.08*0.08 -> 4148.1481 | G65: =+Tabla5557275[[#This Row],[VENTA]]-Tabla5557275[[#This Row],[ICO 8%]] -> 51851.852 | H65: =+Tabla5557275[[#This Row],[COSTO]]/Tabla5557275[[#This Row],[BASE]] -> 0.36152385 | I65: =+Tabla5557275[[#This Row],[BASE]]/Tabla5557275[[#This Row],[COSTO]] -> 2.7660692 | J65: =+VLOOKUP(Tabla5557275[[#This Row],[ARROCES]],#REF!,2,0) -> #REF! | K65: =+D65/(100-65)*100 -> 53559.089 | L65: =+K65/1.08*0.08 -> 3967.3399 | M65: =+Tabla5557275[[#This Row],[PRECIO SUGERIDO]]+Tabla5557275[[#This Row],[ICO2]] -> 57526.429 | N65: 58000 | O65: =+N65/1.08*0.08 -> 4296.2963 | P65: =+N65-O65 -> 53703.704 | Q65: =+D65/P65 -> 0.34905751 | R65: =+P65/D65 -> 2.8648574 | S65: 62000 | T65: =+Tabla5557275[[#This Row],[COSTO]]/Tabla5557275[[#This Row],[Incremento 13%]] -> 0.3023497
B66: =+ARROCES!B6 -> ARROZ MEDITERRANEO | C66: Arroz con mariscos en pasta de pimentón ahumado, vegetales y chips crocantes de plátano, acompañado de leche de tigre. | D66: =+ARROCES!K9 -> 18448.732 | E66: =+ARROCES!K10 -> 59000 | F66: =+E66/1.08*0.08 -> 4370.3704 | G66: =+Tabla5557275[[#This Row],[VENTA]]-Tabla5557275[[#This Row],[ICO 8%]] -> 54629.63 | H66: =+Tabla5557275[[#This Row],[COSTO]]/Tabla5557275[[#This Row],[BASE]] -> 0.3377056 | I66: =+Tabla5557275[[#This Row],[BASE]]/Tabla5557275[[#This Row],[COSTO]] -> 2.9611591 | J66: =+VLOOKUP(Tabla5557275[[#This Row],[ARROCES]],#REF!,2,0) -> #REF! | K66: =+D66/(100-65)*100 -> 52710.662 | L66: =+K66/1.08*0.08 -> 3904.4935 | M66: =+Tabla5557275[[#This Row],[PRECIO SUGERIDO]]+Tabla5557275[[#This Row],[ICO2]] -> 56615.156 | O66: =+N66/1.08*0.08 -> 0 | P66: =+N66-O66 -> 0 | Q66: =+D66/P66 -> #DIV/0! | R66: =+P66/D66 -> 0 | S66: 66000 | T66: =+Tabla5557275[[#This Row],[COSTO]]/Tabla5557275[[#This Row],[Incremento 13%]] -> 0.27952624
B67: =+ARROCES!B124 -> ARROZ PALENQUE | C67: Arroz salteado con pescado y variedad de vegetales, trozos de mazorca parrillada y chimichurri mixto. | D67: =+ARROCES!K127 -> 16079.418 | E67: =+ARROCES!K54 -> 54000 | F67: =+E67/1.08*0.08 -> 4000 | G67: =+Tabla5557275[[#This Row],[VENTA]]-Tabla5557275[[#This Row],[ICO 8%]] -> 50000 | H67: =+Tabla5557275[[#This Row],[COSTO]]/Tabla5557275[[#This Row],[BASE]] -> 0.32158835 | I67: =+Tabla5557275[[#This Row],[BASE]]/Tabla5557275[[#This Row],[COSTO]] -> 3.1095654 | J67: =+VLOOKUP(Tabla5557275[[#This Row],[ARROCES]],#REF!,2,0) -> #REF! | K67: =+D67/(100-65)*100 -> 45941.193 | L67: =+K67/1.08*0.08 -> 3403.0513 | M67: =+Tabla5557275[[#This Row],[PRECIO SUGERIDO]]+Tabla5557275[[#This Row],[ICO2]] -> 49344.244 | O67: =+N67/1.08*0.08 -> 0 | P67: =+N67-O67 -> 0 | Q67: =+D67/P67 -> #DIV/0! | R67: =+P67/D67 -> 0 | S67: 61000 | T67: =+Tabla5557275[[#This Row],[COSTO]]/Tabla5557275[[#This Row],[Incremento 13%]] -> 0.26359701
B68: =+ARROCES!B29 -> ARROZ DEL TROPICO | C68: Arroz cremoso con solomito, frutas y vegetales en salsa de balsámico y queso. | D68: =+ARROCES!K32 -> 21420.171 | E68: =+ARROCES!K33 -> 63000 | F68: =+E68/1.08*0.08 -> 4666.6667 | G68: =+Tabla5557275[[#This Row],[VENTA]]-Tabla5557275[[#This Row],[ICO 8%]] -> 58333.333 | H68: =+Tabla5557275[[#This Row],[COSTO]]/Tabla5557275[[#This Row],[BASE]] -> 0.36720292 | I68: =+Tabla5557275[[#This Row],[BASE]]/Tabla5557275[[#This Row],[COSTO]] -> 2.7232899 | J68: =+VLOOKUP(Tabla5557275[[#This Row],[ARROCES]],#REF!,2,0) -> #REF! | K68: =+D68/(100-65)*100 -> 61200.487 | L68: =+K68/1.08*0.08 -> 4533.3694 | M68: =+Tabla5557275[[#This Row],[PRECIO SUGERIDO]]+Tabla5557275[[#This Row],[ICO2]] -> 65733.857 | O68: =+N68/1.08*0.08 -> 0 | P68: =+N68-O68 -> 0 | Q68: =+D68/P68 -> #DIV/0! | R68: =+P68/D68 -> 0 | S68: 70000 | T68: =+Tabla5557275[[#This Row],[COSTO]]/Tabla5557275[[#This Row],[Incremento 13%]] -> 0.30600244
B69: =+ARROCES!B85 -> ARROZ CALDOSO | C69: Camarones salteados en base de pimientos y pescado coronado con ceviche. | D69: 11763 | E69: =+ARROCES!K89 -> 59000 | F69: =+E69/1.08*0.08 -> 4370.3704 | G69: =+Tabla5557275[[#This Row],[VENTA]]-Tabla5557275[[#This Row],[ICO 8%]] -> 54629.63 | H69: =+Tabla5557275[[#This Row],[COSTO]]/Tabla5557275[[#This Row],[BASE]] -> 0.21532271 | I69: =+Tabla5557275[[#This Row],[BASE]]/Tabla5557275[[#This Row],[COSTO]] -> 4.6441919 | J69: =+VLOOKUP(Tabla5557275[[#This Row],[ARROCES]],#REF!,2,0) -> #REF! | K69: =+D69/(100-65)*100 -> 33608.571 | L69: =+K69/1.08*0.08 -> 2489.5238 | M69: =+Tabla5557275[[#This Row],[PRECIO SUGERIDO]]+Tabla5557275[[#This Row],[ICO2]] -> 36098.095 | O69: =+N69/1.08*0.08 -> 0 | P69: =+N69-O69 -> 0 | Q69: =+D69/P69 -> #DIV/0! | R69: =+P69/D69 -> 0 | S69: 62000 | T69: =+Tabla5557275[[#This Row],[COSTO]]/Tabla5557275[[#This Row],[Incremento 13%]] -> 0.18972581
B70: =+ARROCES!B106 -> ARROZ VEGETARIANO | C70: Arroz salteado al wok con mix de vegetales en salsa soya acompañado con croquetas de alverja. | D70: =+ARROCES!K109 -> 18795.786 | E70: =+ARROCES!K110 -> 64000 | F70: =+E70/1.08*0.08 -> 4740.7407 | G70: =+Tabla5557275[[#This Row],[VENTA]]-Tabla5557275[[#This Row],[ICO 8%]] -> 59259.259 | H70: =+Tabla5557275[[#This Row],[COSTO]]/Tabla5557275[[#This Row],[BASE]] -> 0.3171789 | I70: =+Tabla5557275[[#This Row],[BASE]]/Tabla5557275[[#This Row],[COSTO]] -> 3.1527949 | J70: =+VLOOKUP(Tabla5557275[[#This Row],[ARROCES]],#REF!,2,0) -> #REF! | K70: =+D70/(100-65)*100 -> 53702.247 | L70: =+K70/1.08*0.08 -> 3977.9442 | M70: =+Tabla5557275[[#This Row],[PRECIO SUGERIDO]]+Tabla5557275[[#This Row],[ICO2]] -> 57680.191 | O70: =+N70/1.08*0.08 -> 0 | P70: =+N70-O70 -> 0 | Q70: =+D70/P70 -> #DIV/0! | R70: =+P70/D70 -> 0 | S70: 64000 | T70: =+Tabla5557275[[#This Row],[COSTO]]/Tabla5557275[[#This Row],[Incremento 13%]] -> 0.29368416
B71: Total | H71: =SUBTOTAL(101,Tabla5557275[%]) -> 0.32008706 | J71: =SUBTOTAL(109,Tabla5557275[ROTACION]) -> #REF! | R71: =SUBTOTAL(103,Tabla5557275[RATION]) -> 6
E75: CARTA | K75: SUGERIDO COSTOS | N75: PRECIO FINAL
B76: FUERTES MAR | C76: DESCRIPCION | D76: COSTO | E76: VENTA | F76: ICO 8% | G76: BASE | H76: % | I76: RENTABILIDAD | J76: ROTACION | K76: PRECIO SUGERIDO | L76: ICO2 | M76: CARTA | N76: PRECIO N | O76: ICO 8%2 | P76: CARTA | Q76: % | R76: RATION | S76: Incremento 13% | T76: Costo2
B77: =+'FUERTES MAR'!B33 -> CAZUELA DEL MANGLE | C77: Cazuela al estilo Malanga, mariscos saltados en bísquet, acompañados de arroz con coco y crocantes de plátano. | D77: =+'FUERTES MAR'!K36 -> #N/A | E77: =+'FUERTES MAR'!K37 -> 68000 | F77: =+E77/1.08*0.08 -> 5037.037 | G77: =+Tabla5557276[[#This Row],[VENTA]]-Tabla5557276[[#This Row],[ICO 8%]] -> 62962.963 | H77: =+Tabla5557276[[#This Row],[COSTO]]/Tabla5557276[[#This Row],[BASE]] -> #N/A | I77: =+Tabla5557276[[#This Row],[BASE]]/Tabla5557276[[#This Row],[COSTO]] -> #N/A | J77: =+VLOOKUP(Tabla5557276[[#This Row],[FUERTES MAR]],#REF!,2,0) -> #REF! | K77: =+D77/(100-65)*100 -> #N/A | L77: =+K77/1.08*0.08 -> #N/A | M77: =+Tabla5557276[[#This Row],[PRECIO SUGERIDO]]+Tabla5557276[[#This Row],[ICO2]] -> #N/A | N77: 70000 | O77: =+N77/1.08*0.08 -> 5185.1852 | P77: =+N77-O77 -> 64814.815 | Q77: =+D77/P77 -> #N/A | R77: =+P77/D77 -> #N/A | S77: 76000 | T77: =+Tabla5557276[[#This Row],[COSTO]]/Tabla5557276[[#This Row],[Incremento 13%]] -> #N/A
B78: =+'FUERTES MAR'!B79 -> SALMON AGRIDULCE | C78: Filete de salmón a la plancha bañado en salsa agridulce,acompañado de ensalada fresca, con aguacate y puré de papas. | D78: =+'FUERTES MAR'!K82 -> 17874.68 | E78: =+'FUERTES MAR'!K83 -> 63000 | F78: =+E78/1.08*0.08 -> 4666.6667 | G78: =+Tabla5557276[[#This Row],[VENTA]]-Tabla5557276[[#This Row],[ICO 8%]] -> 58333.333 | H78: =+Tabla5557276[[#This Row],[COSTO]]/Tabla5557276[[#This Row],[BASE]] -> 0.30642308 | I78: =+Tabla5557276[[#This Row],[BASE]]/Tabla5557276[[#This Row],[COSTO]] -> 3.2634617 | J78: =+VLOOKUP(Tabla5557276[[#This Row],[FUERTES MAR]],#REF!,2,0) -> #REF! | K78: =+D78/(100-65)*100 -> 51070.514 | L78: =+K78/1.08*0.08 -> 3783.001 | M78: =+Tabla5557276[[#This Row],[PRECIO SUGERIDO]]+Tabla5557276[[#This Row],[ICO2]] -> 54853.515 | N78: 56000 | O78: =+N78/1.08*0.08 -> 4148.1481 | P78: =+N78-O78 -> 51851.852 | Q78: =+D78/P78 -> 0.34472597 | R78: =+P78/D78 -> 2.9008548 | S78: 67000 | T78: =+Tabla5557276[[#This Row],[COSTO]]/Tabla5557276[[#This Row],[Incremento 13%]] -> 0.26678627
B79: =+'FUERTES MAR'!B244 -> RISSOTO CARBONERO | C79: Filete de salmón, sobre un arroz arbóreo de coco en tinta de calamar, acompañado de langostino crocante bañado en suero de la casa, parmesano y chimichurri mixto. | D79: =+'FUERTES MAR'!K247 -> 24233.722 | E79: =+'FUERTES MAR'!K248 -> 77000 | F79: =+E79/1.08*0.08 -> 5703.7037 | G79: =+Tabla5557276[[#This Row],[VENTA]]-Tabla5557276[[#This Row],[ICO 8%]] -> 71296.296 | H79: =+Tabla5557276[[#This Row],[COSTO]]/Tabla5557276[[#This Row],[BASE]] -> 0.33990155 | I79: =+Tabla5557276[[#This Row],[BASE]]/Tabla5557276[[#This Row],[COSTO]] -> 2.9420283 | J79: =+VLOOKUP(Tabla5557276[[#This Row],[FUERTES MAR]],#REF!,2,0) -> #REF! | K79: =+D79/(100-65)*100 -> 69239.205 | L79: =+K79/1.08*0.08 -> 5128.83 | M79: =+Tabla5557276[[#This Row],[PRECIO SUGERIDO]]+Tabla5557276[[#This Row],[ICO2]] -> 74368.035 | N79: 75000 | O79: =+N79/1.08*0.08 -> 5555.5556 | P79: =+N79-O79 -> 69444.444 | Q79: =+D79/P79 -> 0.34896559 | R79: =+P79/D79 -> 2.865612 | S79: 80000 | T79: =+Tabla5557276[[#This Row],[COSTO]]/Tabla5557276[[#This Row],[Incremento 13%]] -> 0.30292152
B80: =+'FUERTES MAR'!B166 -> PESCA CARTAGENERA | C80: Pesca de mar en salsa de la casa y camarones, acompañada de arroz con coco y patacones con suero costeño. | D80: =+'FUERTES MAR'!K169 -> #N/A | E80: =+'FUERTES MAR'!K170 -> 59000 | F80: =+E80/1.08*0.08 -> 4370.3704 | G80: =+Tabla5557276[[#This Row],[VENTA]]-Tabla5557276[[#This Row],[ICO 8%]] -> 54629.63 | H80: =+Tabla5557276[[#This Row],[COSTO]]/Tabla5557276[[#This Row],[BASE]] -> #N/A | I80: =+Tabla5557276[[#This Row],[BASE]]/Tabla5557276[[#This Row],[COSTO]] -> #N/A | J80: =+VLOOKUP(Tabla5557276[[#This Row],[FUERTES MAR]],#REF!,2,0) -> #REF! | K80: =+D80/(100-65)*100 -> #N/A | L80: =+K80/1.08*0.08 -> #N/A | M80: =+Tabla5557276[[#This Row],[PRECIO SUGERIDO]]+Tabla5557276[[#This Row],[ICO2]] -> #N/A | O80: =+N80/1.08*0.08 -> 0 | P80: =+N80-O80 -> 0 | Q80: =+D80/P80 -> #N/A | R80: =+P80/D80 -> #N/A | S80: 68000 | T80: =+Tabla5557276[[#This Row],[COSTO]]/Tabla5557276[[#This Row],[Incremento 13%]] -> #N/A
B81: =+'FUERTES MAR'!B95 -> SALMÃ“N DE LA COLINA | C81: Salmón sellado a la plancha en salsa parrillera, con arroz acevichado al cilantro, vegetales salteados y maíz dulce. | D81: =+'FUERTES MAR'!K98 -> 17874.68 | E81: =+'FUERTES MAR'!K99 -> 63000 | F81: =+E81/1.08*0.08 -> 4666.6667 | G81: =+Tabla5557276[[#This Row],[VENTA]]-Tabla5557276[[#This Row],[ICO 8%]] -> 58333.333 | H81: =+Tabla5557276[[#This Row],[COSTO]]/Tabla5557276[[#This Row],[BASE]] -> 0.30642308 | I81: =+Tabla5557276[[#This Row],[BASE]]/Tabla5557276[[#This Row],[COSTO]] -> 3.2634617 | J81: =+VLOOKUP(Tabla5557276[[#This Row],[FUERTES MAR]],#REF!,2,0) -> #REF! | K81: =+D81/(100-65)*100 -> 51070.514 | L81: =+K81/1.08*0.08 -> 3783.001 | M81: =+Tabla5557276[[#This Row],[PRECIO SUGERIDO]]+Tabla5557276[[#This Row],[ICO2]] -> 54853.515 | O81: =+N81/1.08*0.08 -> 0 | P81: =+N81-O81 -> 0 | Q81: =+D81/P81 -> #DIV/0! | R81: =+P81/D81 -> 0 | S81: 66000 | T81: =+Tabla5557276[[#This Row],[COSTO]]/Tabla5557276[[#This Row],[Incremento 13%]] -> 0.27082848
B82: =+'FUERTES MAR'!B58 -> FRUTOS DEL MAR | C82: Salteado de mariscos sobre pescado a la plancha en salsa balsámica a la parmesana, acompañado de ensalada al fresco y puré rústico de papa. | D82: =+'FUERTES MAR'!K61 -> 22166.204 | E82: =+'FUERTES MAR'!K62 -> 65000 | F82: =+E82/1.08*0.08 -> 4814.8148 | G82: =+Tabla5557276[[#This Row],[VENTA]]-Tabla5557276[[#This Row],[ICO 8%]] -> 60185.185 | H82: =+Tabla5557276[[#This Row],[COSTO]]/Tabla5557276[[#This Row],[BASE]] -> 0.3683 | I82: =+Tabla5557276[[#This Row],[BASE]]/Tabla5557276[[#This Row],[COSTO]] -> 2.7151778 | J82: =+VLOOKUP(Tabla5557276[[#This Row],[FUERTES MAR]],#REF!,2,0) -> #REF! | K82: =+D82/(100-65)*100 -> 63332.011 | L82: =+K82/1.08*0.08 -> 4691.2601 | M82: =+Tabla5557276[[#This Row],[PRECIO SUGERIDO]]+Tabla5557276[[#This Row],[ICO2]] -> 68023.271 | O82: =+N82/1.08*0.08 -> 0 | P82: =+N82-O82 -> 0 | Q82: =+D82/P82 -> #DIV/0! | R82: =+P82/D82 -> 0 | S82: 73000 | T82: =+Tabla5557276[[#This Row],[COSTO]]/Tabla5557276[[#This Row],[Incremento 13%]] -> 0.30364663
B83: =+'FUERTES MAR'!B110 -> TIMBAL DE PESCADO | C83: Timbal de pescado sobre arroz con camarones y vegetales salteados, parmesano, crocantes de plátano y suero de la casa. | D83: =+'FUERTES MAR'!K113 -> 14653.232 | E83: =+'FUERTES MAR'!K114 -> 49000 | F83: =+E83/1.08*0.08 -> 3629.6296 | G83: =+Tabla5557276[[#This Row],[VENTA]]-Tabla5557276[[#This Row],[ICO 8%]] -> 45370.37 | H83: =+Tabla5557276[[#This Row],[COSTO]]/Tabla5557276[[#This Row],[BASE]] -> 0.3229692 | I83: =+Tabla5557276[[#This Row],[BASE]]/Tabla5557276[[#This Row],[COSTO]] -> 3.0962705 | J83: =+VLOOKUP(Tabla5557276[[#This Row],[FUERTES MAR]],#REF!,2,0) -> #REF! | K83: =+D83/(100-65)*100 -> 41866.377 | L83: =+K83/1.08*0.08 -> 3101.2131 | M83: =+Tabla5557276[[#This Row],[PRECIO SUGERIDO]]+Tabla5557276[[#This Row],[ICO2]] -> 44967.59 | O83: =+N83/1.08*0.08 -> 0 | P83: =+N83-O83 -> 0 | Q83: =+D83/P83 -> #DIV/0! | R83: =+P83/D83 -> 0 | S83: 55000 | T83: =+Tabla5557276[[#This Row],[COSTO]]/Tabla5557276[[#This Row],[Incremento 13%]] -> 0.2664224
B84: =+'FUERTES MAR'!B263 -> PESCA AL AJILLO | D84: =+'FUERTES MAR'!K266 -> 16524.331 | E84: =+'FUERTES MAR'!K267 -> 57000 | F84: =+E84/1.08*0.08 -> 4222.2222 | G84: =+Tabla5557276[[#This Row],[VENTA]]-Tabla5557276[[#This Row],[ICO 8%]] -> 52777.778 | H84: =+Tabla5557276[[#This Row],[COSTO]]/Tabla5557276[[#This Row],[BASE]] -> 0.31309258 | I84: =+Tabla5557276[[#This Row],[BASE]]/Tabla5557276[[#This Row],[COSTO]] -> 3.1939434 | J84: =+VLOOKUP(Tabla5557276[[#This Row],[FUERTES MAR]],#REF!,2,0) -> #REF! | K84: =+D84/(100-65)*100 -> 47212.374 | L84: =+K84/1.08*0.08 -> 3497.2129 | M84: =+Tabla5557276[[#This Row],[PRECIO SUGERIDO]]+Tabla5557276[[#This Row],[ICO2]] -> 50709.587 | O84: =+N84/1.08*0.08 -> 0 | P84: =+N84-O84 -> 0 | Q84: =+D84/P84 -> #DIV/0! | R84: =+P84/D84 -> 0 | S84: 62000 | T84: =+Tabla5557276[[#This Row],[COSTO]]/Tabla5557276[[#This Row],[Incremento 13%]] -> 0.26652146
B85: =+'FUERTES MAR'!B146 -> PESCA DEL ARRECIFE | C85: Pescado crocante sobre su esqueleto bañado con camarones y una salsa de jugos de tomate, acompañado de arroz con coco y patacones crocantes en suero y un toque de salsa de café. | D85: =+'FUERTES MAR'!K149 -> #N/A | E85: =+'FUERTES MAR'!K150 -> 61000 | F85: =+E85/1.08*0.08 -> 4518.5185 | G85: =+Tabla5557276[[#This Row],[VENTA]]-Tabla5557276[[#This Row],[ICO 8%]] -> 56481.481 | H85: =+Tabla5557276[[#This Row],[COSTO]]/Tabla5557276[[#This Row],[BASE]] -> #N/A | I85: =+Tabla5557276[[#This Row],[BASE]]/Tabla5557276[[#This Row],[COSTO]] -> #N/A | J85: =+VLOOKUP(Tabla5557276[[#This Row],[FUERTES MAR]],#REF!,2,0) -> #REF! | K85: =+D85/(100-65)*100 -> #N/A | L85: =+K85/1.08*0.08 -> #N/A | M85: =+Tabla5557276[[#This Row],[PRECIO SUGERIDO]]+Tabla5557276[[#This Row],[ICO2]] -> #N/A | O85: =+N85/1.08*0.08 -> 0 | P85: =+N85-O85 -> 0 | Q85: =+D85/P85 -> #N/A | R85: =+P85/D85 -> #N/A | S85: 62000 | T85: =+Tabla5557276[[#This Row],[COSTO]]/Tabla5557276[[#This Row],[Incremento 13%]] -> #N/A
B86: =+'FUERTES MAR'!B129 -> CEVICHE PARRILLERO | C86: Pulpo, pescado y calamar a la parrilla sobre una plancha, acompañado de mix de cebolla acevichada y carimañolas. | D86: =+'FUERTES MAR'!K132 -> 27618.834 | E86: =+'FUERTES MAR'!K133 -> 82000 | F86: =+E86/1.08*0.08 -> 6074.0741 | G86: =+Tabla5557276[[#This Row],[VENTA]]-Tabla5557276[[#This Row],[ICO 8%]] -> 75925.926 | H86: =+Tabla5557276[[#This Row],[COSTO]]/Tabla5557276[[#This Row],[BASE]] -> 0.36376026 | I86: =+Tabla5557276[[#This Row],[BASE]]/Tabla5557276[[#This Row],[COSTO]] -> 2.7490634 | J86: =+VLOOKUP(Tabla5557276[[#This Row],[FUERTES MAR]],#REF!,2,0) -> #REF! | K86: =+D86/(100-65)*100 -> 78910.955 | L86: =+K86/1.08*0.08 -> 5845.2559 | M86: =+Tabla5557276[[#This Row],[PRECIO SUGERIDO]]+Tabla5557276[[#This Row],[ICO2]] -> 84756.211 | O86: =+N86/1.08*0.08 -> 0 | P86: =+N86-O86 -> 0 | Q86: =+D86/P86 -> #DIV/0! | R86: =+P86/D86 -> 0 | S86: 92000 | T86: =+Tabla5557276[[#This Row],[COSTO]]/Tabla5557276[[#This Row],[Incremento 13%]] -> 0.30020472
B87: =+'FUERTES MAR'!B208 -> PULPO DE LA CASA | C87: Pulpo parrillado sobre pure trufado y chimichurry. | D87: =+'FUERTES MAR'!K211 -> 26946.269 | E87: =+'FUERTES MAR'!K212 -> 93000 | F87: =+E87/1.08*0.08 -> 6888.8889 | G87: =+Tabla5557276[[#This Row],[VENTA]]-Tabla5557276[[#This Row],[ICO 8%]] -> 86111.111 | H87: =+Tabla5557276[[#This Row],[COSTO]]/Tabla5557276[[#This Row],[BASE]] -> 0.31292442 | I87: =+Tabla5557276[[#This Row],[BASE]]/Tabla5557276[[#This Row],[COSTO]] -> 3.1956599 | J87: =+VLOOKUP(Tabla5557276[[#This Row],[FUERTES MAR]],#REF!,2,0) -> #REF! | K87: =+D87/(100-65)*100 -> 76989.34 | L87: =+K87/1.08*0.08 -> 5702.9141 | M87: =+Tabla5557276[[#This Row],[PRECIO SUGERIDO]]+Tabla5557276[[#This Row],[ICO2]] -> 82692.255 | O87: =+N87/1.08*0.08 -> 0 | P87: =+N87-O87 -> 0 | Q87: =+D87/P87 -> #DIV/0! | R87: =+P87/D87 -> 0 | S87: 99000 | T87: =+Tabla5557276[[#This Row],[COSTO]]/Tabla5557276[[#This Row],[Incremento 13%]] -> 0.27218454
B88: =+'FUERTES MAR'!B225 -> PESCADO ENCOCADO | C88: Pesca del día encocada acompañada de arroz de coco y bastones de plátano. | D88: =+'FUERTES MAR'!K228 -> #N/A | E88: =+'FUERTES MAR'!K229 -> 69000 | F88: =+E88/1.08*0.08 -> 5111.1111 | G88: =+Tabla5557276[[#This Row],[VENTA]]-Tabla5557276[[#This Row],[ICO 8%]] -> 63888.889 | H88: =+Tabla5557276[[#This Row],[COSTO]]/Tabla5557276[[#This Row],[BASE]] -> #N/A | I88: =+Tabla5557276[[#This Row],[BASE]]/Tabla5557276[[#This Row],[COSTO]] -> #N/A | J88: =+VLOOKUP(Tabla5557276[[#This Row],[FUERTES MAR]],#REF!,2,0) -> #REF! | K88: =+D88/(100-65)*100 -> #N/A | L88: =+K88/1.08*0.08 -> #N/A | M88: =+Tabla5557276[[#This Row],[PRECIO SUGERIDO]]+Tabla5557276[[#This Row],[ICO2]] -> #N/A | O88: =+N88/1.08*0.08 -> 0 | P88: =+N88-O88 -> 0 | Q88: =+D88/P88 -> #N/A | R88: =+P88/D88 -> #N/A | S88: 75000 | T88: =+Tabla5557276[[#This Row],[COSTO]]/Tabla5557276[[#This Row],[Incremento 13%]] -> #N/A
B89: =+'FUERTES MAR'!B190 -> ATUN MASAI | C89: Atún maguro importado encostrado en alverja y ajonjolí sobre un arroz meloso de Bailey. | D89: =+'FUERTES MAR'!K193 -> 16759.932 | E89: =+'FUERTES MAR'!K194 -> 65000 | F89: =+E89/1.08*0.08 -> 4814.8148 | G89: =+Tabla5557276[[#This Row],[VENTA]]-Tabla5557276[[#This Row],[ICO 8%]] -> 60185.185 | H89: =+Tabla5557276[[#This Row],[COSTO]]/Tabla5557276[[#This Row],[BASE]] -> 0.27847272 | I89: =+Tabla5557276[[#This Row],[BASE]]/Tabla5557276[[#This Row],[COSTO]] -> 3.591016 | J89: =+VLOOKUP(Tabla5557276[[#This Row],[FUERTES MAR]],#REF!,2,0) -> #REF! | K89: =+D89/(100-65)*100 -> 47885.52 | L89: =+K89/1.08*0.08 -> 3547.0756 | M89: =+Tabla5557276[[#This Row],[PRECIO SUGERIDO]]+Tabla5557276[[#This Row],[ICO2]] -> 51432.596 | N89: 69000 | O89: =+N89/1.08*0.08 -> 5111.1111 | P89: =+N89-O89 -> 63888.889 | Q89: =+D89/P89 -> 0.26232937 | R89: =+P89/D89 -> 3.8120016 | S89: 69000 | T89: =+Tabla5557276[[#This Row],[COSTO]]/Tabla5557276[[#This Row],[Incremento 13%]] -> 0.24289757
B90: =+'FUERTES MAR'!B6 -> ISLOTE MALANGA | C90: Langosta a la parrilla con mariscos salteados y vegetales al wok, acompañado de mazorca dulce, mix de cebollas, papa nativa y salsa rocoto. | D90: =+'FUERTES MAR'!K9 -> 77225.904 | E90: =+'FUERTES MAR'!K10 -> 280000 | F90: =+E90/1.08*0.08 -> 20740.741 | G90: =+Tabla5557276[[#This Row],[VENTA]]-Tabla5557276[[#This Row],[ICO 8%]] -> 259259.26 | H90: =+Tabla5557276[[#This Row],[COSTO]]/Tabla5557276[[#This Row],[BASE]] -> 0.29787135 | I90: =+Tabla5557276[[#This Row],[BASE]]/Tabla5557276[[#This Row],[COSTO]] -> 3.3571541 | J90: =+VLOOKUP(Tabla5557276[[#This Row],[FUERTES MAR]],#REF!,2,0) -> #REF! | K90: =+D90/(100-65)*100 -> 220645.44 | L90: =+K90/1.08*0.08 -> 16344.107 | M90: =+Tabla5557276[[#This Row],[PRECIO SUGERIDO]]+Tabla5557276[[#This Row],[ICO2]] -> 236989.55 | O90: =+N90/1.08*0.08 -> 0 | P90: =+N90-O90 -> 0 | Q90: =+D90/P90 -> #DIV/0! | R90: =+P90/D90 -> 0 | S90: 280000 | T90: =+Tabla5557276[[#This Row],[COSTO]]/Tabla5557276[[#This Row],[Incremento 13%]] -> 0.2758068
B91: Total | H91: =SUBTOTAL(101,Tabla5557276[%]) -> #N/A | J91: =SUBTOTAL(109,Tabla5557276[ROTACION]) -> #REF! | R91: =SUBTOTAL(103,Tabla5557276[RATION]) -> 14
E95: CARTA | K95: SUGERIDO COSTOS | N95: PRECIO FINAL
B96: FUERTES TIERRA | C96: DESCRIPCION | D96: COSTO | E96: VENTA | F96: ICO 8% | G96: BASE | H96: % | I96: RENTABILIDAD | J96: ROTACION | K96: PRECIO SUGERIDO | L96: ICO2 | M96: CARTA | N96: PRECIO N | O96: ICO 8%2 | P96: CARTA | Q96: % | R96: RATION | S96: Incremento 13% | T96: Costo2
B97: =+'FUERTES TIERRA'!B6 -> POSTA CARIBEÃ‘A | C97: Posta al estilo cartagenero acompañada de patacones y arroz con coco. / Cartagena-style posta accompanied by patacones and coconut rice. | D97: =+'FUERTES TIERRA'!K9 -> #N/A | E97: =+'FUERTES TIERRA'!K10 -> 51000 | F97: =+E97/1.08*0.08 -> 3777.7778 | G97: =+Tabla5557277[[#This Row],[VENTA]]-Tabla5557277[[#This Row],[ICO 8%]] -> 47222.222 | H97: =+Tabla5557277[[#This Row],[COSTO]]/Tabla5557277[[#This Row],[BASE]] -> #N/A | I97: =+Tabla5557277[[#This Row],[BASE]]/Tabla5557277[[#This Row],[COSTO]] -> #N/A | J97: =+VLOOKUP(Tabla5557277[[#This Row],[FUERTES TIERRA]],#REF!,2,0) -> #REF! | K97: =+D97/(100-65)*100 -> #N/A | L97: =+K97/1.08*0.08 -> #N/A | M97: =+Tabla5557277[[#This Row],[PRECIO SUGERIDO]]+Tabla5557277[[#This Row],[ICO2]] -> #N/A | N97: 57000 | O97: =+N97/1.08*0.08 -> 4222.2222 | P97: =+N97-O97 -> 52777.778 | Q97: =+D97/P97 -> #N/A | R97: =+P97/D97 -> #N/A | S97: 60000 | T97: =+Tabla5557277[[#This Row],[COSTO]]/Tabla5557277[[#This Row],[Incremento 13%]] -> #N/A
B98: =+'FUERTES TIERRA'!B35 -> TENTACION DEL TROPICO | C98: Solomito sobre plátano maduro sellado a la plancha, coronado con tomates, cebollas asadas y huevo frito al gusto, acompañado de zanahoria crocante y salsa de queso. | D98: =+'FUERTES TIERRA'!K38 -> 17972.05 | E98: =+'FUERTES TIERRA'!K39 -> 56000 | F98: =+E98/1.08*0.08 -> 4148.1481 | G98: =+Tabla5557277[[#This Row],[VENTA]]-Tabla5557277[[#This Row],[ICO 8%]] -> 51851.852 | H98: =+Tabla5557277[[#This Row],[COSTO]]/Tabla5557277[[#This Row],[BASE]] -> 0.34660382 | I98: =+Tabla5557277[[#This Row],[BASE]]/Tabla5557277[[#This Row],[COSTO]] -> 2.8851384 | J98: =+VLOOKUP(Tabla5557277[[#This Row],[FUERTES TIERRA]],#REF!,2,0) -> #REF! | K98: =+D98/(100-65)*100 -> 51348.714 | L98: =+K98/1.08*0.08 -> 3803.6085 | M98: =+Tabla5557277[[#This Row],[PRECIO SUGERIDO]]+Tabla5557277[[#This Row],[ICO2]] -> 55152.323 | N98: 55500 | O98: =+N98/1.08*0.08 -> 4111.1111 | P98: =+N98-O98 -> 51388.889 | Q98: =+D98/P98 -> 0.34972638 | R98: =+P98/D98 -> 2.8593782 | S98: 62000 | T98: =+Tabla5557277[[#This Row],[COSTO]]/Tabla5557277[[#This Row],[Incremento 13%]] -> 0.28987177
B99: =+'FUERTES TIERRA'!B52 -> LOMO PRIMAVERA | C99: Solomito en salsa cremosa de soya, sobre una base de arroz con tocineta , champiñón y topping de zanahoria crocante. | D99: =+'FUERTES TIERRA'!K55 -> 22027.53 | E99: =+'FUERTES TIERRA'!K56 -> 63000 | F99: =+E99/1.08*0.08 -> 4666.6667 | G99: =+Tabla5557277[[#This Row],[VENTA]]-Tabla5557277[[#This Row],[ICO 8%]] -> 58333.333 | H99: =+Tabla5557277[[#This Row],[COSTO]]/Tabla5557277[[#This Row],[BASE]] -> 0.37761481 | I99: =+Tabla5557277[[#This Row],[BASE]]/Tabla5557277[[#This Row],[COSTO]] -> 2.6482012 | J99: =+VLOOKUP(Tabla5557277[[#This Row],[FUERTES TIERRA]],#REF!,2,0) -> #REF! | K99: =+D99/(100-65)*100 -> 62935.801 | L99: =+K99/1.08*0.08 -> 4661.9112 | M99: =+Tabla5557277[[#This Row],[PRECIO SUGERIDO]]+Tabla5557277[[#This Row],[ICO2]] -> 67597.713 | N99: 68000 | O99: =+N99/1.08*0.08 -> 5037.037 | P99: =+N99-O99 -> 62962.963 | Q99: =+D99/P99 -> 0.34984901 | R99: =+P99/D99 -> 2.8583759 | S99: 73000 | T99: =+Tabla5557277[[#This Row],[COSTO]]/Tabla5557277[[#This Row],[Incremento 13%]] -> 0.30174699
B100: =+'FUERTES TIERRA'!B23 -> LOMO AL CAFÃ‰ | C100: Lomo enrollado con tocineta ahumada, bañado con salsa de café, acompañado de ensalada fresca y puré de papa a la parmesana. | D100: =+'FUERTES TIERRA'!K26 -> 18821.345 | E100: =+'FUERTES TIERRA'!K27 -> 59000 | F100: =+E100/1.08*0.08 -> 4370.3704 | G100: =+Tabla5557277[[#This Row],[VENTA]]-Tabla5557277[[#This Row],[ICO 8%]] -> 54629.63 | H100: =+Tabla5557277[[#This Row],[COSTO]]/Tabla5557277[[#This Row],[BASE]] -> 0.34452631 | I100: =+Tabla5557277[[#This Row],[BASE]]/Tabla5557277[[#This Row],[COSTO]] -> 2.9025359 | J100: =+VLOOKUP(Tabla5557277[[#This Row],[FUERTES TIERRA]],#REF!,2,0) -> #REF! | K100: =+D100/(100-65)*100 -> 53775.271 | L100: =+K100/1.08*0.08 -> 3983.3534 | M100: =+Tabla5557277[[#This Row],[PRECIO SUGERIDO]]+Tabla5557277[[#This Row],[ICO2]] -> 57758.624 | N100: 59000 | O100: =+N100/1.08*0.08 -> 4370.3704 | P100: =+N100-O100 -> 54629.63 | Q100: =+D100/P100 -> 0.34452631 | R100: =+P100/D100 -> 2.9025359 | S100: 64000 | T100: =+Tabla5557277[[#This Row],[COSTO]]/Tabla5557277[[#This Row],[Incremento 13%]] -> 0.29408351
B101: =+'FUERTES TIERRA'!B110 -> COSTILLAS ARREBATADAS | C101: Costillas bañadas en salsa bbq o miel mostaza, flameadas con ron, acompañadas de tomates parrillados, puré de la casa o papas a la francesa. | D101: =+'FUERTES TIERRA'!K113 -> 24682.402 | E101: =+'FUERTES TIERRA'!K114 -> 74000 | F101: =+E101/1.08*0.08 -> 5481.4815 | G101: =+Tabla5557277[[#This Row],[VENTA]]-Tabla5557277[[#This Row],[ICO 8%]] -> 68518.519 | H101: =+Tabla5557277[[#This Row],[COSTO]]/Tabla5557277[[#This Row],[BASE]] -> 0.36022965 | I101: =+Tabla5557277[[#This Row],[BASE]]/Tabla5557277[[#This Row],[COSTO]] -> 2.7760069 | J101: =+VLOOKUP(Tabla5557277[[#This Row],[FUERTES TIERRA]],#REF!,2,0) -> #REF! | K101: =+D101/(100-65)*100 -> 70521.149 | L101: =+K101/1.08*0.08 -> 5223.7888 | M101: =+Tabla5557277[[#This Row],[PRECIO SUGERIDO]]+Tabla5557277[[#This Row],[ICO2]] -> 75744.938 | N101: 77000 | O101: =+N101/1.08*0.08 -> 5703.7037 | P101: =+N101-O101 -> 71296.296 | Q101: =+D101/P101 -> 0.34619473 | R101: =+P101/D101 -> 2.8885477 | S101: 83000 | T101: =+Tabla5557277[[#This Row],[COSTO]]/Tabla5557277[[#This Row],[Incremento 13%]] -> 0.29737834
B102: =+'FUERTES TIERRA'!B91 -> LOMO MUCURA | C102: Lomo sellado, sobre puré cremoso de plátano, chips de yuca y salsa de pimientas. | D102: =+'FUERTES TIERRA'!K94 -> 16875.946 | E102: =+'FUERTES TIERRA'!K95 -> 63000 | F102: =+E102/1.08*0.08 -> 4666.6667 | G102: =+Tabla5557277[[#This Row],[VENTA]]-Tabla5557277[[#This Row],[ICO 8%]] -> 58333.333 | H102: =+Tabla5557277[[#This Row],[COSTO]]/Tabla5557277[[#This Row],[BASE]] -> 0.28930194 | I102: =+Tabla5557277[[#This Row],[BASE]]/Tabla5557277[[#This Row],[COSTO]] -> 3.4565963 | J102: =+VLOOKUP(Tabla5557277[[#This Row],[FUERTES TIERRA]],#REF!,2,0) -> #REF! | K102: =+D102/(100-65)*100 -> 48216.989 | L102: =+K102/1.08*0.08 -> 3571.6289 | M102: =+Tabla5557277[[#This Row],[PRECIO SUGERIDO]]+Tabla5557277[[#This Row],[ICO2]] -> 51788.618 | N102: 53000 | O102: =+N102/1.08*0.08 -> 3925.9259 | P102: =+N102-O102 -> 49074.074 | Q102: =+D102/P102 -> 0.34388721 | R102: =+P102/D102 -> 2.9079302 | S102: 65000 | T102: =+Tabla5557277[[#This Row],[COSTO]]/Tabla5557277[[#This Row],[Incremento 13%]] -> 0.25962994
B103: =+'FUERTES TIERRA'!B124 -> COSTILLAS AHUMADAS | C103: Costillas bañadas en salsa bbq de guayaba, ahumadas, acompañas de tomates parrillados, papas a la francesa y/o puré de papa. | D103: =+'FUERTES TIERRA'!K127 -> 18238.32 | E103: =+'FUERTES TIERRA'!K128 -> 74000 | F103: =+E103/1.08*0.08 -> 5481.4815 | G103: =+Tabla5557277[[#This Row],[VENTA]]-Tabla5557277[[#This Row],[ICO 8%]] -> 68518.519 | H103: =+Tabla5557277[[#This Row],[COSTO]]/Tabla5557277[[#This Row],[BASE]] -> 0.26618089 | I103: =+Tabla5557277[[#This Row],[BASE]]/Tabla5557277[[#This Row],[COSTO]] -> 3.7568437 | J103: =+VLOOKUP(Tabla5557277[[#This Row],[FUERTES TIERRA]],#REF!,2,0) -> #REF! | K103: =+D103/(100-65)*100 -> 52109.487 | L103: =+K103/1.08*0.08 -> 3859.962 | M103: =+Tabla5557277[[#This Row],[PRECIO SUGERIDO]]+Tabla5557277[[#This Row],[ICO2]] -> 55969.449 | N103: 57000 | O103: =+N103/1.08*0.08 -> 4222.2222 | P103: =+N103-O103 -> 52777.778 | Q103: =+D103/P103 -> 0.34556817 | R103: =+P103/D103 -> 2.893785 | S103: 83000 | T103: =+Tabla5557277[[#This Row],[COSTO]]/Tabla5557277[[#This Row],[Incremento 13%]] -> 0.2197388
B104: =+'FUERTES TIERRA'!B69 -> LOMO EN SALSA DE COROZO | D104: =+'FUERTES TIERRA'!K72 -> 22632.251 | E104: =+'FUERTES TIERRA'!K73 -> 65000 | F104: =+E104/1.08*0.08 -> 4814.8148 | G104: =+Tabla5557277[[#This Row],[VENTA]]-Tabla5557277[[#This Row],[ICO 8%]] -> 60185.185 | H104: =+Tabla5557277[[#This Row],[COSTO]]/Tabla5557277[[#This Row],[BASE]] -> 0.37604356 | I104: =+Tabla5557277[[#This Row],[BASE]]/Tabla5557277[[#This Row],[COSTO]] -> 2.6592664 | J104: =+VLOOKUP(Tabla5557277[[#This Row],[FUERTES TIERRA]],#REF!,2,0) -> #REF! | K104: =+D104/(100-65)*100 -> 64663.575 | L104: =+K104/1.08*0.08 -> 4789.8945 | M104: =+Tabla5557277[[#This Row],[PRECIO SUGERIDO]]+Tabla5557277[[#This Row],[ICO2]] -> 69453.47 | N104: 70000 | O104: =+N104/1.08*0.08 -> 5185.1852 | P104: =+N104-O104 -> 64814.815 | Q104: =+D104/P104 -> 0.34918331 | R104: =+P104/D104 -> 2.8638253 | S104: 73000 | T104: =+Tabla5557277[[#This Row],[COSTO]]/Tabla5557277[[#This Row],[Incremento 13%]] -> 0.31003084
B105: Total | H105: =SUBTOTAL(101,Tabla5557277[%]) -> #N/A | J105: =SUBTOTAL(109,Tabla5557277[ROTACION]) -> #REF! | R105: =SUBTOTAL(103,Tabla5557277[RATION]) -> 8
E109: CARTA | K109: SUGERIDO COSTOS | N109: PRECIO FINAL
B110: FUERTES MAR Y TIERRA | C110: DESCRIPCION | D110: COSTO | E110: VENTA | F110: ICO 8% | G110: BASE | H110: % | I110: RENTABILIDAD | J110: ROTACION | K110: PRECIO SUGERIDO | L110: ICO2 | M110: CARTA | N110: PRECIO N | O110: ICO 8%2 | P110: CARTA | Q110: % | R110: RATION | S110: Incremento 13% | T110: Costo2
A111: 1 | B111: =+'FUERTES MAR Y TIERRA'!B70 -> LOMO MAR Y TIERRA | C111: Solomito con camarones en salsa de queso acompañado con vegetales salteados y puré de la casa coronado con langostino. | D111: =+'FUERTES MAR Y TIERRA'!K74 -> 23967.389 | E111: =+'FUERTES MAR Y TIERRA'!K75 -> 71000 | F111: =+E111/1.08*0.08 -> 5259.2593 | G111: =+Tabla5557279[[#This Row],[VENTA]]-Tabla5557279[[#This Row],[ICO 8%]] -> 65740.741 | H111: =+Tabla5557279[[#This Row],[COSTO]]/Tabla5557279[[#This Row],[BASE]] -> 0.36457437 | I111: =+Tabla5557279[[#This Row],[BASE]]/Tabla5557279[[#This Row],[COSTO]] -> 2.7429246 | J111: =+VLOOKUP(Tabla5557279[[#This Row],[FUERTES MAR Y TIERRA]],#REF!,2,0) -> #REF! | K111: =+D111/(100-67)*100 -> 72628.451 | L111: =+K111/1.08*0.08 -> 5379.8853 | M111: =+Tabla5557279[[#This Row],[PRECIO SUGERIDO]]+Tabla5557279[[#This Row],[ICO2]] -> 78008.337 | N111: 78000 | O111: =+N111/1.08*0.08 -> 5777.7778 | P111: =+N111-O111 -> 72222.222 | Q111: =+D111/P111 -> 0.33185615 | R111: =+P111/D111 -> 3.0133538 | S111: 80000 | T111: =+Tabla5557279[[#This Row],[COSTO]]/Tabla5557279[[#This Row],[Incremento 13%]] -> 0.29959236
A112: 2 | B112: =+'FUERTES MAR Y TIERRA'!B51 -> FETUCCINI MAR Y TIERRA | C112: Pasta fetuccini salteada con solomito,camarones en tres quesos y un topping de kanikama. | D112: =+'FUERTES MAR Y TIERRA'!K55 -> 18952.804 | E112: =+'FUERTES MAR Y TIERRA'!K56 -> 62000 | F112: =+E112/1.08*0.08 -> 4592.5926 | G112: =+Tabla5557279[[#This Row],[VENTA]]-Tabla5557279[[#This Row],[ICO 8%]] -> 57407.407 | H112: =+Tabla5557279[[#This Row],[COSTO]]/Tabla5557279[[#This Row],[BASE]] -> 0.33014561 | I112: =+Tabla5557279[[#This Row],[BASE]]/Tabla5557279[[#This Row],[COSTO]] -> 3.0289665 | J112: =+VLOOKUP(Tabla5557279[[#This Row],[FUERTES MAR Y TIERRA]],#REF!,2,0) -> #REF! | K112: =+D112/(100-67)*100 -> 57432.738 | L112: =+K112/1.08*0.08 -> 4254.2769 | M112: =+Tabla5557279[[#This Row],[PRECIO SUGERIDO]]+Tabla5557279[[#This Row],[ICO2]] -> 61687.015 | N112: 62000 | O112: =+N112/1.08*0.08 -> 4592.5926 | P112: =+N112-O112 -> 57407.407 | Q112: =+D112/P112 -> 0.33014561 | R112: =+P112/D112 -> 3.0289665 | S112: 64000 | T112: =+Tabla5557279[[#This Row],[COSTO]]/Tabla5557279[[#This Row],[Incremento 13%]] -> 0.29613756
A113: 3 | B113: =+'FUERTES MAR Y TIERRA'!B6 -> LOMO MALANGA | C113: Solomito sellado en soya, bañado en salsa de mariscos al rocoto, acompañado de papas criollas crocantes, maicitos y ensalada al fresco | D113: =+'FUERTES MAR Y TIERRA'!K9 -> 25906.293 | E113: =+'FUERTES MAR Y TIERRA'!K10 -> 76000 | F113: =+E113/1.08*0.08 -> 5629.6296 | G113: =+Tabla5557279[[#This Row],[VENTA]]-Tabla5557279[[#This Row],[ICO 8%]] -> 70370.37 | H113: =+Tabla5557279[[#This Row],[COSTO]]/Tabla5557279[[#This Row],[BASE]] -> 0.36814206 | I113: =+Tabla5557279[[#This Row],[BASE]]/Tabla5557279[[#This Row],[COSTO]] -> 2.7163427 | J113: =+VLOOKUP(Tabla5557279[[#This Row],[FUERTES MAR Y TIERRA]],#REF!,2,0) -> #REF! | K113: =+D113/(100-67)*100 -> 78503.919 | L113: =+K113/1.08*0.08 -> 5815.1051 | M113: =+Tabla5557279[[#This Row],[PRECIO SUGERIDO]]+Tabla5557279[[#This Row],[ICO2]] -> 84319.025 | N113: 98500 | O113: =+N113/1.08*0.08 -> 7296.2963 | P113: =+N113-O113 -> 91203.704 | Q113: =+D113/P113 -> 0.2840487 | R113: =+P113/D113 -> 3.5205231 | S113: 81000 | T113: =+Tabla5557279[[#This Row],[COSTO]]/Tabla5557279[[#This Row],[Incremento 13%]] -> 0.31983078
A114: 4 | B114: =+'FUERTES MAR Y TIERRA'!B30 -> AREPA DE LA CASA | C114: Arepa rellena con sobrebarriga y plátano maduro bañada en salsa de queso al vino blanco y camarones. | D114: =+'FUERTES MAR Y TIERRA'!K34 -> 15468.178 | E114: =+'FUERTES MAR Y TIERRA'!K35 -> 49000 | F114: =+E114/1.08*0.08 -> 3629.6296 | G114: =+Tabla5557279[[#This Row],[VENTA]]-Tabla5557279[[#This Row],[ICO 8%]] -> 45370.37 | H114: =+Tabla5557279[[#This Row],[COSTO]]/Tabla5557279[[#This Row],[BASE]] -> 0.34093127 | I114: =+Tabla5557279[[#This Row],[BASE]]/Tabla5557279[[#This Row],[COSTO]] -> 2.9331425 | J114: =+VLOOKUP(Tabla5557279[[#This Row],[FUERTES MAR Y TIERRA]],#REF!,2,0) -> #REF! | K114: =+D114/(100-67)*100 -> 46873.267 | L114: =+K114/1.08*0.08 -> 3472.0939 | M114: =+Tabla5557279[[#This Row],[PRECIO SUGERIDO]]+Tabla5557279[[#This Row],[ICO2]] -> 50345.361 | N114: 49000 | O114: =+N114/1.08*0.08 -> 3629.6296 | P114: =+N114-O114 -> 45370.37 | Q114: =+D114/P114 -> 0.34093127 | R114: =+P114/D114 -> 2.9331425 | S114: 52000 | T114: =+Tabla5557279[[#This Row],[COSTO]]/Tabla5557279[[#This Row],[Incremento 13%]] -> 0.29746496
A115: 5 | B115: =+'FUERTES MAR Y TIERRA'!B94 -> BOWL DEL CARIBE CON CAMARONES | D115: =+'FUERTES MAR Y TIERRA'!K98 -> 15330.33 | E115: =+'FUERTES MAR Y TIERRA'!K99 -> 56000 | F115: =+E115/1.08*0.08 -> 4148.1481 | G115: =+Tabla5557279[[#This Row],[VENTA]]-Tabla5557279[[#This Row],[ICO 8%]] -> 51851.852 | H115: =+Tabla5557279[[#This Row],[COSTO]]/Tabla5557279[[#This Row],[BASE]] -> 0.29565636 | I115: =+Tabla5557279[[#This Row],[BASE]]/Tabla5557279[[#This Row],[COSTO]] -> 3.3823051 | J115: =+VLOOKUP(Tabla5557279[[#This Row],[FUERTES MAR Y TIERRA]],#REF!,2,0) -> #REF! | K115: =+D115/(100-67)*100 -> 46455.544 | L115: =+K115/1.08*0.08 -> 3441.1514 | M115: =+Tabla5557279[[#This Row],[PRECIO SUGERIDO]]+Tabla5557279[[#This Row],[ICO2]] -> 49896.696 | N115: 56000 | O115: =+N115/1.08*0.08 -> 4148.1481 | P115: =+N115-O115 -> 51851.852 | Q115: =+D115/P115 -> 0.29565636 | R115: =+P115/D115 -> 3.3823051 | S115: 59000 | T115: =+Tabla5557279[[#This Row],[COSTO]]/Tabla5557279[[#This Row],[Incremento 13%]] -> 0.25983609
A116: 6 | B116: =+'FUERTES MAR Y TIERRA'!B115 -> BOWL DEL CARIBE CON SOBRE BARRIGA | D116: =+'FUERTES MAR Y TIERRA'!K119 -> 11767.125 | E116: =+'FUERTES MAR Y TIERRA'!K120 -> 52000 | F116: =+E116/1.08*0.08 -> 3851.8519 | G116: =+Tabla5557279[[#This Row],[VENTA]]-Tabla5557279[[#This Row],[ICO 8%]] -> 48148.148 | H116: =+Tabla5557279[[#This Row],[COSTO]]/Tabla5557279[[#This Row],[BASE]] -> 0.24439413 | I116: =+Tabla5557279[[#This Row],[BASE]]/Tabla5557279[[#This Row],[COSTO]] -> 4.0917513 | J116: =+VLOOKUP(Tabla5557279[[#This Row],[FUERTES MAR Y TIERRA]],#REF!,2,0) -> #REF! | K116: =+D116/(100-67)*100 -> 35657.954 | L116: =+K116/1.08*0.08 -> 2641.3299 | M116: =+Tabla5557279[[#This Row],[PRECIO SUGERIDO]]+Tabla5557279[[#This Row],[ICO2]] -> 38299.284 | N116: 52000 | O116: =+N116/1.08*0.08 -> 3851.8519 | P116: =+N116-O116 -> 48148.148 | Q116: =+D116/P116 -> 0.24439413 | R116: =+P116/D116 -> 4.0917513 | S116: 56000 | T116: =+Tabla5557279[[#This Row],[COSTO]]/Tabla5557279[[#This Row],[Incremento 13%]] -> 0.21012723
B117: Total | H117: =SUBTOTAL(101,Tabla5557279[%]) -> 0.32397397 | J117: =SUBTOTAL(109,Tabla5557279[ROTACION]) -> #REF! | R117: =SUBTOTAL(109,Tabla5557279[RATION]) -> 19.970042
E120: CARTA | K120: SUGERIDO COSTOS | N120: PRECIO FINAL
B121: MENU INFANTIL | C121: DESCRIPCION | D121: COSTO | E121: VENTA | F121: ICO 8% | G121: BASE | H121: % | I121: RENTABILIDAD | J121: ROTACION | K121: PRECIO SUGERIDO | L121: ICO2 | M121: CARTA | N121: PRECIO N | O121: ICO 8%2 | P121: CARTA | Q121: % | R121: RATION | S121: Incremento 13% | T121: Costo2
B122: =+'MENU INFANTIL'!B6 -> MENU INFANTIL DE POLLO | C122: Proteína a la selección (Pollo, carne o pescado), acompañada de papas a la francesa. | D122: =+'MENU INFANTIL'!K9 -> 7820.2459 | E122: =+'MENU INFANTIL'!K10 -> 34000 | F122: =+E122/1.08*0.08 -> 2518.5185 | G122: =+Tabla5557279288[[#This Row],[VENTA]]-Tabla5557279288[[#This Row],[ICO 8%]] -> 31481.481 | H122: =+Tabla5557279288[[#This Row],[COSTO]]/Tabla5557279288[[#This Row],[BASE]] -> 0.24840781 | I122: =+Tabla5557279288[[#This Row],[BASE]]/Tabla5557279288[[#This Row],[COSTO]] -> 4.0256383 | J122: =+VLOOKUP(Tabla5557279288[[#This Row],[MENU INFANTIL]],#REF!,2,0) -> #REF! | K122: =+D122/(100-67)*100 -> 23697.715 | L122: =+K122/1.08*0.08 -> 1755.3863 | M122: =+Tabla5557279288[[#This Row],[PRECIO SUGERIDO]]+Tabla5557279288[[#This Row],[ICO2]] -> 25453.101 | N122: 34000 | O122: =+N122/1.08*0.08 -> 2518.5185 | P122: =+N122-O122 -> 31481.481 | Q122: =+D122/P122 -> 0.24840781 | R122: =+P122/D122 -> 4.0256383 | S122: 35000 | T122: =+Tabla5557279288[[#This Row],[COSTO]]/Tabla5557279288[[#This Row],[Incremento 13%]] -> 0.2234356
B123: =+'MENU INFANTIL'!B29 -> MENU INFANTIL DE SOLOMITO | C123: Proteína a la selección (Pollo, carne o pescado), acompañada de papas a la francesa. | D123: =+'MENU INFANTIL'!K32 -> 9645.7843 | E123: =+'MENU INFANTIL'!K33 -> 34000 | F123: =+E123/1.08*0.08 -> 2518.5185 | G123: =+Tabla5557279288[[#This Row],[VENTA]]-Tabla5557279288[[#This Row],[ICO 8%]] -> 31481.481 | H123: =+Tabla5557279288[[#This Row],[COSTO]]/Tabla5557279288[[#This Row],[BASE]] -> 0.3063955 | I123: =+Tabla5557279288[[#This Row],[BASE]]/Tabla5557279288[[#This Row],[COSTO]] -> 3.2637555 | J123: =+VLOOKUP(Tabla5557279288[[#This Row],[MENU INFANTIL]],#REF!,2,0) -> #REF! | K123: =+D123/(100-67)*100 -> 29229.649 | L123: =+K123/1.08*0.08 -> 2165.1592 | M123: =+Tabla5557279288[[#This Row],[PRECIO SUGERIDO]]+Tabla5557279288[[#This Row],[ICO2]] -> 31394.809 | N123: 34000 | O123: =+N123/1.08*0.08 -> 2518.5185 | P123: =+N123-O123 -> 31481.481 | Q123: =+D123/P123 -> 0.3063955 | R123: =+P123/D123 -> 3.2637555 | S123: 35000 | T123: =+Tabla5557279288[[#This Row],[COSTO]]/Tabla5557279288[[#This Row],[Incremento 13%]] -> 0.27559384
B124: =+'MENU INFANTIL'!B17 -> MENU INFANTIL DE PESCADO | C124: Proteína a la selección (Pollo, carne o pescado), acompañada de papas a la francesa. | D124: =+'MENU INFANTIL'!K20 -> 8825.198 | E124: =+'MENU INFANTIL'!K21 -> 34000 | F124: =+E124/1.08*0.08 -> 2518.5185 | G124: =+Tabla5557279288[[#This Row],[VENTA]]-Tabla5557279288[[#This Row],[ICO 8%]] -> 31481.481 | H124: =+Tabla5557279288[[#This Row],[COSTO]]/Tabla5557279288[[#This Row],[BASE]] -> 0.28032982 | I124: =+Tabla5557279288[[#This Row],[BASE]]/Tabla5557279288[[#This Row],[COSTO]] -> 3.5672267 | J124: =+VLOOKUP(Tabla5557279288[[#This Row],[MENU INFANTIL]],#REF!,2,0) -> #REF! | K124: =+D124/(100-67)*100 -> 26743.024 | L124: =+K124/1.08*0.08 -> 1980.9647 | M124: =+Tabla5557279288[[#This Row],[PRECIO SUGERIDO]]+Tabla5557279288[[#This Row],[ICO2]] -> 28723.989 | N124: 34000 | O124: =+N124/1.08*0.08 -> 2518.5185 | P124: =+N124-O124 -> 31481.481 | Q124: =+D124/P124 -> 0.28032982 | R124: =+P124/D124 -> 3.5672267 | S124: 35000 | T124: =+Tabla5557279288[[#This Row],[COSTO]]/Tabla5557279288[[#This Row],[Incremento 13%]] -> 0.25214851
B125: Total | H125: =SUBTOTAL(101,Tabla5557279288[%]) -> 0.27837771 | J125: =SUBTOTAL(109,Tabla5557279288[ROTACION]) -> #REF! | R125: =SUBTOTAL(109,Tabla5557279288[RATION]) -> 10.85662
...

Sheet SUB RECETAS COCINA
B7: SUB. SALSA TARTARA | J7: ANALISIS RECETA | M7: Preparacion
B8: ArtÃ­culo | C8: Unidad Medida | D8: Unidades Netas | E8: % Merma | F8: Unidades | G8: Coste Componente | H8: Coste LÃ­nea | J8: COSTO DEL PLATO | K8: =SUM(Tabla1103453454455456479116117118120740126148156186[Coste LÃ­nea]) -> 7224.8993
B9: PIMENTON X KILO | C9: g | D9: 30 | E9: 0 | F9: 30 | G9: =+VLOOKUP(Tabla1103453454455456479116117118120740126148156186[[#This Row],[ArtÃ­culo]],Tabla34[#All],3,0) -> 6 | H9: =+Tabla1103453454455456479116117118120740126148156186[[#This Row],[Coste Componente]]*Tabla1103453454455456479116117118120740126148156186[[#This Row],[Unidades]] -> 180 | J9: MARGEN DE ERROR DEL 10% | K9: =+K8*5% -> 361.24497
B10: ALCAPARRA ALFRESCO X 500GR | C10: g | D10: 20 | E10: 0 | F10: 20 | G10: =+VLOOKUP(Tabla1103453454455456479116117118120740126148156186[[#This Row],[ArtÃ­culo]],Tabla34[#All],3,0) -> 27.146 | H10: =+Tabla1103453454455456479116117118120740126148156186[[#This Row],[Coste Componente]]*Tabla1103453454455456479116117118120740126148156186[[#This Row],[Unidades]] -> 542.92 | J10: COSTO + MARGEN ERROR | K10: =+K8+K9 -> 7586.1443
B11: CEBOLLA RAMA LIMPIA X KILO | C11: g | D11: 20 | E11: 0 | F11: 20 | G11: =+VLOOKUP(Tabla1103453454455456479116117118120740126148156186[[#This Row],[ArtÃ­culo]],Tabla34[#All],3,0) -> 5 | H11: =+Tabla1103453454455456479116117118120740126148156186[[#This Row],[Coste Componente]]*Tabla1103453454455456479116117118120740126148156186[[#This Row],[Unidades]] -> 100 | J11: Rendimiento | K11: 325
B12: COMINO MOLIDO X 500GR | C12: g | D12: 1 | E12: 0 | F12: 1 | G12: =+VLOOKUP(Tabla1103453454455456479116117118120740126148156186[[#This Row],[ArtÃ­culo]],Tabla34[#All],3,0) -> 60.0108 | H12: =+Tabla1103453454455456479116117118120740126148156186[[#This Row],[Coste Componente]]*Tabla1103453454455456479116117118120740126148156186[[#This Row],[Unidades]] -> 60.0108 | J12: IPOCONSUMO | K12: =+K10/K11 -> 23.341982
B13: PEREJIL CRESPO X KILO | C13: g | D13: 5 | E13: 0 | F13: 5 | G13: =+VLOOKUP(Tabla1103453454455456479116117118120740126148156186[[#This Row],[ArtÃ­culo]],Tabla34[#All],3,0) -> 8 | H13: =+Tabla1103453454455456479116117118120740126148156186[[#This Row],[Coste Componente]]*Tabla1103453454455456479116117118120740126148156186[[#This Row],[Unidades]] -> 40 | M13: Emplatado
B14: CEBOLLIN*KILO | C14: g | D14: 30 | E14: 0 | F14: 30 | G14: =+VLOOKUP(Tabla1103453454455456479116117118120740126148156186[[#This Row],[ArtÃ­culo]],Tabla34[#All],3,0) -> 16 | H14: =+Tabla1103453454455456479116117118120740126148156186[[#This Row],[Coste Componente]]*Tabla1103453454455456479116117118120740126148156186[[#This Row],[Unidades]] -> 480
B15: MAYONESA FRUCO GALON X3770G | C15: g | D15: 170 | E15: 0 | F15: 170 | G15: =+VLOOKUP(Tabla1103453454455456479116117118120740126148156186[[#This Row],[ArtÃ­culo]],Tabla34[#All],3,0) -> 26.272577 | H15: =+Tabla1103453454455456479116117118120740126148156186[[#This Row],[Coste Componente]]*Tabla1103453454455456479116117118120740126148156186[[#This Row],[Unidades]] -> 4466.338
B16: AJI DULCE X KILO | C16: g | D16: 15 | E16: 0 | F16: 15 | G16: =+VLOOKUP(Tabla1103453454455456479116117118120740126148156186[[#This Row],[ArtÃ­culo]],Tabla34[#All],3,0) -> 9.8 | H16: =+Tabla1103453454455456479116117118120740126148156186[[#This Row],[Coste Componente]]*Tabla1103453454455456479116117118120740126148156186[[#This Row],[Unidades]] -> 147
B17: CILANTRO LIMPIO X KILO | C17: g | D17: 5 | E17: 0 | F17: 5 | G17: =+VLOOKUP(Tabla1103453454455456479116117118120740126148156186[[#This Row],[ArtÃ­culo]],Tabla34[#All],3,0) -> 12 | H17: =+Tabla1103453454455456479116117118120740126148156186[[#This Row],[Coste Componente]]*Tabla1103453454455456479116117118120740126148156186[[#This Row],[Unidades]] -> 60
B18: LIMON TAHITI X KILO | C18: g | D18: 120 | E18: 0 | F18: 120 | G18: =+VLOOKUP(Tabla1103453454455456479116117118120740126148156186[[#This Row],[ArtÃ­culo]],Tabla34[#All],3,0) -> 4.5 | H18: =+Tabla1103453454455456479116117118120740126148156186[[#This Row],[Coste Componente]]*Tabla1103453454455456479116117118120740126148156186[[#This Row],[Unidades]] -> 540
B19: AJINOMOTO X KILO | C19: g | D19: 5 | E19: 0 | F19: 5 | G19: =+VLOOKUP(Tabla1103453454455456479116117118120740126148156186[[#This Row],[ArtÃ­culo]],Tabla34[#All],3,0) -> 13.401291 | H19: =+Tabla1103453454455456479116117118120740126148156186[[#This Row],[Coste Componente]]*Tabla1103453454455456479116117118120740126148156186[[#This Row],[Unidades]] -> 67.006457
B20: SAL REFISAL X 1000G | C20: g | D20: 6 | E20: 0 | F20: 6 | G20: =+VLOOKUP(Tabla1103453454455456479116117118120740126148156186[[#This Row],[ArtÃ­culo]],Tabla34[#All],3,0) -> 2.401 | H20: =+Tabla1103453454455456479116117118120740126148156186[[#This Row],[Coste Componente]]*Tabla1103453454455456479116117118120740126148156186[[#This Row],[Unidades]] -> 14.406
B21: PIMIENTA NEGRA MOLIDA BADIA 453GR | C21: g | D21: 1 | E21: 0 | F21: 1 | G21: =+VLOOKUP(Tabla1103453454455456479116117118120740126148156186[[#This Row],[ArtÃ­culo]],Tabla34[#All],3,0) -> 57.218062 | H21: =+Tabla1103453454455456479116117118120740126148156186[[#This Row],[Coste Componente]]*Tabla1103453454455456479116117118120740126148156186[[#This Row],[Unidades]] -> 57.218062
B22: CEBOLLA MORADA LIMPIA | C22: g | D22: 100 | E22: 0 | F22: 100 | G22: =+VLOOKUP(Tabla1103453454455456479116117118120740126148156186[[#This Row],[ArtÃ­culo]],Tabla34[#All],3,0) -> 4.7 | H22: =+Tabla1103453454455456479116117118120740126148156186[[#This Row],[Coste Componente]]*Tabla1103453454455456479116117118120740126148156186[[#This Row],[Unidades]] -> 470
H23: =SUBTOTAL(109,Tabla1103453454455456479116117118120740126148156186[Coste LÃ­nea]) -> 7224.8993
B26: SUB. ACEITE DE ACHIOTE | J26: ANALISIS RECETA | M26: Preparacion
B27: ArtÃ­culo | C27: Unidad Medida | D27: Unidades Netas | E27: % Merma | F27: Unidades | G27: Coste Componente | H27: Coste LÃ­nea | J27: COSTO DEL PLATO | K27: =SUM(Tabla1103453454455456479116117118120740126148156186184[Coste LÃ­nea]) -> 12627.899
B28: ACEITE VEGETAL X 20LT | C28: g | D28: 1000 | E28: 0 | F28: 1000 | G28: =+VLOOKUP(Tabla1103453454455456479116117118120740126148156186184[[#This Row],[ArtÃ­culo]],Tabla34[#All],3,0) -> 7.68385 | H28: =+Tabla1103453454455456479116117118120740126148156186184[[#This Row],[Coste Componente]]*Tabla1103453454455456479116117118120740126148156186184[[#This Row],[Unidades]] -> 7683.85 | J28: MARGEN DE ERROR DEL 10% | K28: =+K27*5% -> 631.39497
B29: ACHIOTE EN GRANO*1000 | C29: g | D29: 250 | E29: 0 | F29: 250 | G29: =+VLOOKUP(Tabla1103453454455456479116117118120740126148156186184[[#This Row],[ArtÃ­culo]],Tabla34[#All],3,0) -> 19.776197 | H29: =+Tabla1103453454455456479116117118120740126148156186184[[#This Row],[Coste Componente]]*Tabla1103453454455456479116117118120740126148156186184[[#This Row],[Unidades]] -> 4944.0494 | J29: COSTO + MARGEN ERROR | K29: =+K27+K28 -> 13259.294
H30: =SUBTOTAL(109,Tabla1103453454455456479116117118120740126148156186184[Coste LÃ­nea]) -> 12627.899 | J30: Rendimiento | K30: 1000
J31: IPOCONSUMO | K31: =+K29/K30 -> 13.259294
M32: Emplatado
B33: SUB. ACEVICHADA | J33: ANALISIS RECETA
B34: ArtÃ­culo | C34: Unidad Medida | D34: Unidades Netas | E34: % Merma | F34: Unidades | G34: Coste Componente | H34: Coste LÃ­nea | J34: COSTO DEL PLATO | K34: =SUM(Tabla1103453454455456479116117118120740126148156186185[Coste LÃ­nea]) -> 172105.01
B35: MAYONESA FRUCO GALON X3770G | C35: g | D35: 2810 | E35: 0 | F35: 2810 | G35: =+VLOOKUP(Tabla1103453454455456479116117118120740126148156186185[[#This Row],[ArtÃ­culo]],Tabla34[#All],3,0) -> 26.272577 | H35: =+Tabla1103453454455456479116117118120740126148156186185[[#This Row],[Coste Componente]]*Tabla1103453454455456479116117118120740126148156186185[[#This Row],[Unidades]] -> 73825.94 | J35: MARGEN DE ERROR DEL 10% | K35: =+K34*5% -> 8605.2504
B36: LIMON TAHITI X KILO | C36: g | D36: 1840 | E36: 78 | F36: 8363.637 | G36: =+VLOOKUP(Tabla1103453454455456479116117118120740126148156186185[[#This Row],[ArtÃ­culo]],Tabla34[#All],3,0) -> 4.5 | H36: =+Tabla1103453454455456479116117118120740126148156186185[[#This Row],[Coste Componente]]*Tabla1103453454455456479116117118120740126148156186185[[#This Row],[Unidades]] -> 37636.367 | J36: COSTO + MARGEN ERROR | K36: =+K34+K35 -> 180710.26
B37: SUB. PASTA ROCOTO | C37: g | D37: 1440 | E37: 0 | F37: 1440 | G37: =+VLOOKUP(Tabla1103453454455456479116117118120740126148156186185[[#This Row],[ArtÃ­culo]],Tabla34[#All],3,0) -> 40.42512 | H37: =+Tabla1103453454455456479116117118120740126148156186185[[#This Row],[Coste Componente]]*Tabla1103453454455456479116117118120740126148156186185[[#This Row],[Unidades]] -> 58212.172 | J37: Rendimiento | K37: 6300
B38: SUB. PASTA DE AJO | C38: g | D38: 70 | E38: 0 | F38: 70 | G38: =+VLOOKUP(Tabla1103453454455456479116117118120740126148156186185[[#This Row],[ArtÃ­culo]],Tabla34[#All],3,0) -> 14.257835 | H38: =+Tabla1103453454455456479116117118120740126148156186185[[#This Row],[Coste Componente]]*Tabla1103453454455456479116117118120740126148156186185[[#This Row],[Unidades]] -> 998.04848 | J38: IPOCONSUMO | K38: =+K36/K37 -> 28.684168
B39: SAL REFISAL X 1000G | C39: g | D39: 120 | E39: 0 | F39: 120 | G39: =+VLOOKUP(Tabla1103453454455456479116117118120740126148156186185[[#This Row],[ArtÃ­culo]],Tabla34[#All],3,0) -> 2.401 | H39: =+Tabla1103453454455456479116117118120740126148156186185[[#This Row],[Coste Componente]]*Tabla1103453454455456479116117118120740126148156186185[[#This Row],[Unidades]] -> 288.12
B40: PIMIENTA NEGRA MOLIDA BADIA 453GR | C40: g | D40: 20 | E40: 0 | F40: 20 | G40: =+VLOOKUP(Tabla1103453454455456479116117118120740126148156186185[[#This Row],[ArtÃ­culo]],Tabla34[#All],3,0) -> 57.218062 | H40: =+Tabla1103453454455456479116117118120740126148156186185[[#This Row],[Coste Componente]]*Tabla1103453454455456479116117118120740126148156186185[[#This Row],[Unidades]] -> 1144.3612
H41: =SUBTOTAL(109,Tabla1103453454455456479116117118120740126148156186185[Coste LÃ­nea]) -> 172105.01
B43: SUB. ADEREZO PICADILLO | J43: ANALISIS RECETA | M43: Preparacion
B44: ArtÃ­culo | C44: Unidad Medida | D44: Unidades Netas | E44: % Merma | F44: Unidades | G44: Coste Componente | H44: Coste LÃ­nea | J44: COSTO DEL PLATO | K44: =SUM(Tabla1103453454455456479116117118120740126148156186227[Coste LÃ­nea]) -> 3798.1416
B45: CEBOLLA BLANCA LIMPIA X KILO | C45: g | D45: 185 | E45: 0 | F45: 185 | G45: =+VLOOKUP(Tabla1103453454455456479116117118120740126148156186227[[#This Row],[ArtÃ­culo]],Tabla34[#All],3,0) -> 2.8 | H45: =+Tabla1103453454455456479116117118120740126148156186227[[#This Row],[Coste Componente]]*Tabla1103453454455456479116117118120740126148156186227[[#This Row],[Unidades]] -> 518 | J45: MARGEN DE ERROR DEL 10% | K45: =+K44*5% -> 189.90708
B46: AJI DULCE X KILO | C46: g | D46: 65 | E46: 0 | F46: 65 | G46: =+VLOOKUP(Tabla1103453454455456479116117118120740126148156186227[[#This Row],[ArtÃ­culo]],Tabla34[#All],3,0) -> 9.8 | H46: =+Tabla1103453454455456479116117118120740126148156186227[[#This Row],[Coste Componente]]*Tabla1103453454455456479116117118120740126148156186227[[#This Row],[Unidades]] -> 637 | J46: COSTO + MARGEN ERROR | K46: =+K44+K45 -> 3988.0487
B47: ALCAPARRA ALFRESCO X 500GR | C47: g | D47: 25 | E47: 0 | F47: 25 | G47: =+VLOOKUP(Tabla1103453454455456479116117118120740126148156186227[[#This Row],[ArtÃ­culo]],Tabla34[#All],3,0) -> 27.146 | H47: =+Tabla1103453454455456479116117118120740126148156186227[[#This Row],[Coste Componente]]*Tabla1103453454455456479116117118120740126148156186227[[#This Row],[Unidades]] -> 678.65 | J47: Rendimiento | K47: 2135
B48: ACEITE MESTRE OLEO X 3000CC | C48: g | D48: 80 | E48: 0 | F48: 80 | G48: =+VLOOKUP(Tabla1103453454455456479116117118120740126148156186227[[#This Row],[ArtÃ­culo]],Tabla34[#All],3,0) -> 18.859 | H48: =+Tabla1103453454455456479116117118120740126148156186227[[#This Row],[Coste Componente]]*Tabla1103453454455456479116117118120740126148156186227[[#This Row],[Unidades]] -> 1508.72 | J48: IPOCONSUMO | K48: =+K46/K47 -> 1.8679385
B49: SAL REFISAL X 1000G | C49: g | D49: 20 | E49: 0 | F49: 20 | G49: =+VLOOKUP(Tabla1103453454455456479116117118120740126148156186227[[#This Row],[ArtÃ­culo]],Tabla34[#All],3,0) -> 2.401 | H49: =+Tabla1103453454455456479116117118120740126148156186227[[#This Row],[Coste Componente]]*Tabla1103453454455456479116117118120740126148156186227[[#This Row],[Unidades]] -> 48.02 | M49: Emplatado
B50: VINAGRE BLANCO FRUCO X 3060ML | C50: g | D50: 40 | E50: 0 | F50: 40 | G50: =+VLOOKUP(Tabla1103453454455456479116117118120740126148156186227[[#This Row],[ArtÃ­culo]],Tabla34[#All],3,0) -> 10.193791 | H50: =+Tabla1103453454455456479116117118120740126148156186227[[#This Row],[Coste Componente]]*Tabla1103453454455456479116117118120740126148156186227[[#This Row],[Unidades]] -> 407.75163
H51: =SUBTOTAL(109,Tabla1103453454455456479116117118120740126148156186227[Coste LÃ­nea]) -> 3798.1416
B53: SUB. AREPAS MALANGA | J53: ANALISIS RECETA | M53: Preparacion
B54: ArtÃ­culo | C54: Unidad Medida | D54: Unidades Netas | E54: % Merma | F54: Unidades | G54: Coste Componente | H54: Coste LÃ­nea | J54: COSTO DEL PLATO | K54: =SUM(Tabla1103453454455456479116117118120740126148156186243[Coste LÃ­nea]) -> 4102.6548
B55: SUB. MASA DE AREPAS | C55: g | D55: 50 | E55: 0 | F55: 50 | G55: =+VLOOKUP(Tabla1103453454455456479116117118120740126148156186243[[#This Row],[ArtÃ­culo]],Tabla34[#All],3,0) -> 1.508661 | H55: =+Tabla1103453454455456479116117118120740126148156186243[[#This Row],[Coste Componente]]*Tabla1103453454455456479116117118120740126148156186243[[#This Row],[Unidades]] -> 75.43305 | J55: MARGEN DE ERROR DEL 10% | K55: =+K54*5% -> 205.13274
B56: PLATANO MADURO | C56: g | D56: 30 | E56: 30 | F56: 42.857 | G56: =+VLOOKUP(Tabla1103453454455456479116117118120740126148156186243[[#This Row],[ArtÃ­culo]],Tabla34[#All],3,0) -> 3.5 | H56: =+Tabla1103453454455456479116117118120740126148156186243[[#This Row],[Coste Componente]]*Tabla1103453454455456479116117118120740126148156186243[[#This Row],[Unidades]] -> 149.9995 | J56: COSTO + MARGEN ERROR | K56: =+K54+K55 -> 4307.7875
B57: SUB. SOBREBARRIGA | C57: uds | D57: 1 | E57: 0 | F57: 1 | G57: =+VLOOKUP(Tabla1103453454455456479116117118120740126148156186243[[#This Row],[ArtÃ­culo]],Tabla34[#All],3,0) -> 3877.2222 | H57: =+Tabla1103453454455456479116117118120740126148156186243[[#This Row],[Coste Componente]]*Tabla1103453454455456479116117118120740126148156186243[[#This Row],[Unidades]] -> 3877.2222 | J57: Rendimiento | K57: 1 | M57: Emplatado
H58: =SUBTOTAL(109,Tabla1103453454455456479116117118120740126148156186243[Coste LÃ­nea]) -> 4102.6548 | J58: IPOCONSUMO | K58: =+K56/K57 -> 4307.7875
B61: SUB. ARROZ ARBOREO | J61: ANALISIS RECETA | M61: Preparacion
B62: ArtÃ­culo | C62: Unidad Medida | D62: Unidades Netas | E62: % Merma | F62: Unidades | G62: Coste Componente | H62: Coste LÃ­nea | J62: COSTO DEL PLATO | K62: =SUM(Tabla1103453454455456479116117118120740126148156186246[Coste LÃ­nea]) -> 252.7163
B63: ARROZ ARBOREO COLAVITA X 1 KG | C63: g | D63: 500 | E63: 0 | F63: 500 | G63: =+VLOOKUP(Tabla1103453454455456479116117118120740126148156186246[[#This Row],[ArtÃ­culo]],Tabla34[#All],3,0) -> 0 | H63: =+Tabla1103453454455456479116117118120740126148156186246[[#This Row],[Coste Componente]]*Tabla1103453454455456479116117118120740126148156186246[[#This Row],[Unidades]] -> 0 | J63: MARGEN DE ERROR DEL 10% | K63: =+K62*5% -> 12.635815
B64: AGUA EPM | C64: g | D64: 900 | E64: 0 | F64: 900 | G64: =+VLOOKUP(Tabla1103453454455456479116117118120740126148156186246[[#This Row],[ArtÃ­culo]],Tabla34[#All],3,0) -> 0 | H64: =+Tabla1103453454455456479116117118120740126148156186246[[#This Row],[Coste Componente]]*Tabla1103453454455456479116117118120740126148156186246[[#This Row],[Unidades]] -> 0 | J64: COSTO + MARGEN ERROR | K64: =+K62+K63 -> 265.35211
B65: CEBOLLA BLANCA LIMPIA X KILO | C65: g | D65: 50 | E65: 17 | F65: 60.241 | G65: =+VLOOKUP(Tabla1103453454455456479116117118120740126148156186246[[#This Row],[ArtÃ­culo]],Tabla34[#All],3,0) -> 2.8 | H65: =+Tabla1103453454455456479116117118120740126148156186246[[#This Row],[Coste Componente]]*Tabla1103453454455456479116117118120740126148156186246[[#This Row],[Unidades]] -> 168.6748 | J65: Rendimiento | K65: 1100 | M65: Emplatado
B66: SAL REFISAL X 1000G | C66: g | D66: 3 | E66: 0 | F66: 3 | G66: =+VLOOKUP(Tabla1103453454455456479116117118120740126148156186246[[#This Row],[ArtÃ­culo]],Tabla34[#All],3,0) -> 2.401 | H66: =+Tabla1103453454455456479116117118120740126148156186246[[#This Row],[Coste Componente]]*Tabla1103453454455456479116117118120740126148156186246[[#This Row],[Unidades]] -> 7.203 | J66: IPOCONSUMO | K66: =+K64/K65 -> 0.2412292
B67: ACEITE VEGETAL X 20LT | C67: g | D67: 10 | E67: 0 | F67: 10 | G67: =+VLOOKUP(Tabla1103453454455456479116117118120740126148156186246[[#This Row],[ArtÃ­culo]],Tabla34[#All],3,0) -> 7.68385 | H67: =+Tabla1103453454455456479116117118120740126148156186246[[#This Row],[Coste Componente]]*Tabla1103453454455456479116117118120740126148156186246[[#This Row],[Unidades]] -> 76.8385
H68: =SUBTOTAL(109,Tabla1103453454455456479116117118120740126148156186246[Coste LÃ­nea]) -> 252.7163
B71: SUB. ARROZ COCIDO | J71: ANALISIS RECETA | M71: Preparacion
B72: ArtÃ­culo | C72: Unidad Medida | D72: Unidades Netas | E72: % Merma | F72: Unidades | G72: Coste Componente | H72: Coste LÃ­nea | J72: COSTO DEL PLATO | K72: =SUM(Tabla1103453454455456479116117118120740126148156186249[Coste LÃ­nea]) -> 34171.105
B73: ARROZ CASTELLANO X 1KG | C73: g | D73: 3000 | E73: 0 | F73: 3000 | G73: =+VLOOKUP(Tabla1103453454455456479116117118120740126148156186249[[#This Row],[ArtÃ­culo]],Tabla34[#All],3,0) -> 10.616 | H73: =+Tabla1103453454455456479116117118120740126148156186249[[#This Row],[Coste Componente]]*Tabla1103453454455456479116117118120740126148156186249[[#This Row],[Unidades]] -> 31848 | J73: MARGEN DE ERROR DEL 10% | K73: =+K72*5% -> 1708.5553
B74: SAL REFISAL X 1000G | C74: g | D74: 25 | E74: 0 | F74: 25 | G74: =+VLOOKUP(Tabla1103453454455456479116117118120740126148156186249[[#This Row],[ArtÃ­culo]],Tabla34[#All],3,0) -> 2.401 | H74: =+Tabla1103453454455456479116117118120740126148156186249[[#This Row],[Coste Componente]]*Tabla1103453454455456479116117118120740126148156186249[[#This Row],[Unidades]] -> 60.025 | J74: COSTO + MARGEN ERROR | K74: =+K72+K73 -> 35879.66
B75: AGUA EPM | C75: g | D75: 8000 | E75: 0 | F75: 8000 | G75: =+VLOOKUP(Tabla1103453454455456479116117118120740126148156186249[[#This Row],[ArtÃ­culo]],Tabla34[#All],3,0) -> 0 | H75: =+Tabla1103453454455456479116117118120740126148156186249[[#This Row],[Coste Componente]]*Tabla1103453454455456479116117118120740126148156186249[[#This Row],[Unidades]] -> 0 | J75: Rendimiento | K75: 9230 | M75: Emplatado
B76: ACEITE MESTRE OLEO X 3000CC | C76: g | D76: 120 | E76: 0 | F76: 120 | G76: =+VLOOKUP(Tabla1103453454455456479116117118120740126148156186249[[#This Row],[ArtÃ­culo]],Tabla34[#All],3,0) -> 18.859 | H76: =+Tabla1103453454455456479116117118120740126148156186249[[#This Row],[Coste Componente]]*Tabla1103453454455456479116117118120740126148156186249[[#This Row],[Unidades]] -> 2263.08 | J76: IPOCONSUMO | K76: =+K74/K75 -> 3.8872871
H77: =SUBTOTAL(109,Tabla1103453454455456479116117118120740126148156186249[Coste LÃ­nea]) -> 34171.105
B80: SUB. BASE LECHE DE TIGRE MALANGA | J80: ANALISIS RECETA | M80: Preparacion
B81: ArtÃ­culo | C81: Unidad Medida | D81: Unidades Netas | E81: % Merma | F81: Unidades | G81: Coste Componente | H81: Coste LÃ­nea | J81: COSTO DEL PLATO | K81: =SUM(Tabla1103453454455456479116117118120740126148156186251[Coste LÃ­nea]) -> 12987.74 | M81: 1.Desvenar el rocoto, retirarle las semillas y lavar, pelar el jengibre y trocear junto con el cilantro, apio y pescado, llevar todo a un bol junto con los demás ingredientes y dejar marinar 10 segundos
B82: APIO X KILO | C82: g | D82: 100 | E82: 30 | F82: 142.857 | G82: =+VLOOKUP(Tabla1103453454455456479116117118120740126148156186251[[#This Row],[ArtÃ­culo]],Tabla34[#All],3,0) -> 2.3 | H82: =+Tabla1103453454455456479116117118120740126148156186251[[#This Row],[Coste Componente]]*Tabla1103453454455456479116117118120740126148156186251[[#This Row],[Unidades]] -> 328.5711 | J82: MARGEN DE ERROR DEL 10% | K82: =+K81*5% -> 649.38698 | M82: 2.Llevar todo a la licuadora y procesar por 10 segundos tamizar por un colador fino y reservar en refrigeración
B83: AJO LIMPIO X KILO | C83: g | D83: 10 | E83: 0 | F83: 10 | G83: =+VLOOKUP(Tabla1103453454455456479116117118120740126148156186251[[#This Row],[ArtÃ­culo]],Tabla34[#All],3,0) -> 19 | H83: =+Tabla1103453454455456479116117118120740126148156186251[[#This Row],[Coste Componente]]*Tabla1103453454455456479116117118120740126148156186251[[#This Row],[Unidades]] -> 190 | J83: COSTO + MARGEN ERROR | K83: =+K81+K82 -> 13637.126
B84: CILANTRO LIMPIO X KILO | C84: g | D84: 7 | E84: 40 | F84: 11.667 | G84: =+VLOOKUP(Tabla1103453454455456479116117118120740126148156186251[[#This Row],[ArtÃ­culo]],Tabla34[#All],3,0) -> 12 | H84: =+Tabla1103453454455456479116117118120740126148156186251[[#This Row],[Coste Componente]]*Tabla1103453454455456479116117118120740126148156186251[[#This Row],[Unidades]] -> 140.004 | J84: Rendimiento | K84: 630 | M84: Emplatado
B85: JENGIBRE X KILO | C85: g | D85: 50 | E85: 10 | F85: 55.556 | G85: =+VLOOKUP(Tabla1103453454455456479116117118120740126148156186251[[#This Row],[ArtÃ­culo]],Tabla34[#All],3,0) -> 10.2 | H85: =+Tabla1103453454455456479116117118120740126148156186251[[#This Row],[Coste Componente]]*Tabla1103453454455456479116117118120740126148156186251[[#This Row],[Unidades]] -> 566.6712 | J85: IPOCONSUMO | K85: =+K83/K84 -> 21.646233
B86: FILETE DE TILAPIA FRESCA LO | C86: g | D86: 150 | E86: 10 | F86: 166.667 | G86: =+VLOOKUP(Tabla1103453454455456479116117118120740126148156186251[[#This Row],[ArtÃ­culo]],Tabla34[#All],3,0) -> 39 | H86: =+Tabla1103453454455456479116117118120740126148156186251[[#This Row],[Coste Componente]]*Tabla1103453454455456479116117118120740126148156186251[[#This Row],[Unidades]] -> 6500.013
B87: LIMON TAHITI X KILO | C87: g | D87: 150 | E87: 78 | F87: 681.818 | G87: =+VLOOKUP(Tabla1103453454455456479116117118120740126148156186251[[#This Row],[ArtÃ­culo]],Tabla34[#All],3,0) -> 4.5 | H87: =+Tabla1103453454455456479116117118120740126148156186251[[#This Row],[Coste Componente]]*Tabla1103453454455456479116117118120740126148156186251[[#This Row],[Unidades]] -> 3068.181
B88: AJI DULCE X KILO | C88: g | D88: 15 | E88: 10 | F88: 16.667 | G88: =+VLOOKUP(Tabla1103453454455456479116117118120740126148156186251[[#This Row],[ArtÃ­culo]],Tabla34[#All],3,0) -> 9.8 | H88: =+Tabla1103453454455456479116117118120740126148156186251[[#This Row],[Coste Componente]]*Tabla1103453454455456479116117118120740126148156186251[[#This Row],[Unidades]] -> 163.3366
B89: BOLSA DE HIELO IGLU 18 KG | C89: g | D89: 500 | E89: 0 | F89: 500 | G89: =+VLOOKUP(Tabla1103453454455456479116117118120740126148156186251[[#This Row],[ArtÃ­culo]],Tabla34[#All],3,0) -> 1 | H89: =+Tabla1103453454455456479116117118120740126148156186251[[#This Row],[Coste Componente]]*Tabla1103453454455456479116117118120740126148156186251[[#This Row],[Unidades]] -> 500
B90: AJI ROCOTO X KILO | C90: g | D90: 35 | E90: 40 | F90: 58.333 | G90: =+VLOOKUP(Tabla1103453454455456479116117118120740126148156186251[[#This Row],[ArtÃ­culo]],Tabla34[#All],3,0) -> 18 | H90: =+Tabla1103453454455456479116117118120740126148156186251[[#This Row],[Coste Componente]]*Tabla1103453454455456479116117118120740126148156186251[[#This Row],[Unidades]] -> 1049.994
B91: SUB. FONDO CLARO DE PESCADO | C91: g | D91: 175 | E91: 0 | F91: 175 | G91: =+VLOOKUP(Tabla1103453454455456479116117118120740126148156186251[[#This Row],[ArtÃ­culo]],Tabla34[#All],3,0) -> 1.7196863 | H91: =+Tabla1103453454455456479116117118120740126148156186251[[#This Row],[Coste Componente]]*Tabla1103453454455456479116117118120740126148156186251[[#This Row],[Unidades]] -> 300.94511
B92: SAL REFISAL X 1000G | C92: g | D92: 8 | E92: 0 | F92: 8 | G92: =+VLOOKUP(Tabla1103453454455456479116117118120740126148156186251[[#This Row],[ArtÃ­culo]],Tabla34[#All],3,0) -> 2.401 | H92: =+Tabla1103453454455456479116117118120740126148156186251[[#This Row],[Coste Componente]]*Tabla1103453454455456479116117118120740126148156186251[[#This Row],[Unidades]] -> 19.208
B93: AJINOMOTO X KILO | C93: g | D93: 12 | E93: 0 | F93: 12 | G93: =+VLOOKUP(Tabla1103453454455456479116117118120740126148156186251[[#This Row],[ArtÃ­culo]],Tabla34[#All],3,0) -> 13.401291 | H93: =+Tabla1103453454455456479116117118120740126148156186251[[#This Row],[Coste Componente]]*Tabla1103453454455456479116117118120740126148156186251[[#This Row],[Unidades]] -> 160.8155
H94: =SUBTOTAL(109,Tabla1103453454455456479116117118120740126148156186251[Coste LÃ­nea]) -> 12987.74
B97: SUB. BBQ DE GUAYABA | J97: ANALISIS RECETA | M97: Preparacion
B98: ArtÃ­culo | C98: Unidad Medida | D98: Unidades Netas | E98: % Merma | F98: Unidades | G98: Coste Componente | H98: Coste LÃ­nea | J98: COSTO DEL PLATO | K98: =SUM(Tabla1103453454455456479116117118120740126148156186253[Coste LÃ­nea]) -> 87860.856
B99: SALSA DE TOMATE FRUCO GX 4350G | C99: g | D99: 3000 | E99: 0 | F99: 3000 | G99: =+VLOOKUP(Tabla1103453454455456479116117118120740126148156186253[[#This Row],[ArtÃ­culo]],Tabla34[#All],3,0) -> 18.828046 | H99: =+Tabla1103453454455456479116117118120740126148156186253[[#This Row],[Coste Componente]]*Tabla1103453454455456479116117118120740126148156186253[[#This Row],[Unidades]] -> 56484.138 | J99: MARGEN DE ERROR DEL 10% | K99: =+K98*5% -> 4393.0428
B100: AHUMADO/SALSA HUMO ASTEK X 3850ML | C100: g | D100: 500 | E100: 0 | F100: 500 | G100: =+VLOOKUP(Tabla1103453454455456479116117118120740126148156186253[[#This Row],[ArtÃ­culo]],Tabla34[#All],3,0) -> 10.5 | H100: =+Tabla1103453454455456479116117118120740126148156186253[[#This Row],[Coste Componente]]*Tabla1103453454455456479116117118120740126148156186253[[#This Row],[Unidades]] -> 5250 | J100: COSTO + MARGEN ERROR | K100: =+K98+K99 -> 92253.899
B101: VINAGRE BLANCO FRUCO X 3060ML | C101: g | D101: 200 | E101: 0 | F101: 200 | G101: =+VLOOKUP(Tabla1103453454455456479116117118120740126148156186253[[#This Row],[ArtÃ­culo]],Tabla34[#All],3,0) -> 10.193791 | H101: =+Tabla1103453454455456479116117118120740126148156186253[[#This Row],[Coste Componente]]*Tabla1103453454455456479116117118120740126148156186253[[#This Row],[Unidades]] -> 2038.7582 | J101: Rendimiento | K101: 5286 | M101: Emplatado
B102: AZUCAR MANUELITA BOLSA X 5LB | C102: g | D102: 900 | E102: 0 | F102: 900 | G102: =+VLOOKUP(Tabla1103453454455456479116117118120740126148156186253[[#This Row],[ArtÃ­culo]],Tabla34[#All],3,0) -> 4.8816667 | H102: =+Tabla1103453454455456479116117118120740126148156186253[[#This Row],[Coste Componente]]*Tabla1103453454455456479116117118120740126148156186253[[#This Row],[Unidades]] -> 4393.5 | J102: IPOCONSUMO | K102: =+K100/K101 -> 17.452497
B103: BOCADILLO DE GUAYABA X150G | C103: g | D103: 1270 | E103: 0 | F103: 1270 | G103: =+VLOOKUP(Tabla1103453454455456479116117118120740126148156186253[[#This Row],[ArtÃ­culo]],Tabla34[#All],3,0) -> 13.698 | H103: =+Tabla1103453454455456479116117118120740126148156186253[[#This Row],[Coste Componente]]*Tabla1103453454455456479116117118120740126148156186253[[#This Row],[Unidades]] -> 17396.46
B104: CERVEZA NEGRA COCINA | C104: uds | D104: 1 | E104: 0 | F104: 1 | G104: =+VLOOKUP(Tabla1103453454455456479116117118120740126148156186253[[#This Row],[ArtÃ­culo]],Tabla34[#All],3,0) -> 2298 | H104: =+Tabla1103453454455456479116117118120740126148156186253[[#This Row],[Coste Componente]]*Tabla1103453454455456479116117118120740126148156186253[[#This Row],[Unidades]] -> 2298
H105: =SUBTOTAL(109,Tabla1103453454455456479116117118120740126148156186253[Coste LÃ­nea]) -> 87860.856
B108: SUB. BBQ DE MANGO | J108: ANALISIS RECETA | M108: Preparacion
B109: ArtÃ­culo | C109: Unidad Medida | D109: Unidades Netas | E109: % Merma | F109: Unidades | G109: Coste Componente | H109: Coste LÃ­nea | J109: COSTO DEL PLATO | K109: =SUM(Tabla1103453454455456479116117118120740126148156186254[Coste LÃ­nea]) -> 14546.251
B110: BBQ BOLSA 5000G BARY CJ | C110: g | D110: 350 | E110: 0 | F110: 350 | G110: =+VLOOKUP(Tabla1103453454455456479116117118120740126148156186254[[#This Row],[ArtÃ­culo]],Tabla34[#All],3,0) -> 11.78 | H110: =+Tabla1103453454455456479116117118120740126148156186254[[#This Row],[Coste Componente]]*Tabla1103453454455456479116117118120740126148156186254[[#This Row],[Unidades]] -> 4123 | J110: MARGEN DE ERROR DEL 10% | K110: =+K109*5% -> 727.31256
B111: SALSA DE HUMO INNOVAL X 1000 | C111: g | D111: 150 | E111: 0 | F111: 150 | G111: =+VLOOKUP(Tabla1103453454455456479116117118120740126148156186254[[#This Row],[ArtÃ­culo]],Tabla34[#All],3,0) -> 10.749943 | H111: =+Tabla1103453454455456479116117118120740126148156186254[[#This Row],[Coste Componente]]*Tabla1103453454455456479116117118120740126148156186254[[#This Row],[Unidades]] -> 1612.4915 | J111: COSTO + MARGEN ERROR | K111: =+K109+K110 -> 15273.564
B112: MIEL DE ABEJA PURA S/ VALENTINX 480G | C112: g | D112: 100 | E112: 0 | F112: 100 | G112: =+VLOOKUP(Tabla1103453454455456479116117118120740126148156186254[[#This Row],[ArtÃ­culo]],Tabla34[#All],3,0) -> 40.047917 | H112: =+Tabla1103453454455456479116117118120740126148156186254[[#This Row],[Coste Componente]]*Tabla1103453454455456479116117118120740126148156186254[[#This Row],[Unidades]] -> 4004.7917 | J112: Rendimiento | K112: 5286 | M112: Emplatado
B113: MANGO TOMMY X KILO | C113: g | D113: 1000 | E113: 0 | F113: 1000 | G113: =+VLOOKUP(Tabla1103453454455456479116117118120740126148156186254[[#This Row],[ArtÃ­culo]],Tabla34[#All],3,0) -> 2.5 | H113: =+Tabla1103453454455456479116117118120740126148156186254[[#This Row],[Coste Componente]]*Tabla1103453454455456479116117118120740126148156186254[[#This Row],[Unidades]] -> 2500 | J113: IPOCONSUMO | K113: =+K111/K112 -> 2.889437
B114: RON MEDELLIN 3 AÃ‘OS 750ML | C114: oz | D114: 0.5 | E114: 0 | F114: 0.5 | G114: =+VLOOKUP(Tabla1103453454455456479116117118120740126148156186254[[#This Row],[ArtÃ­culo]],Tabla34[#All],3,0) -> 2082.9167 | H114: =+Tabla1103453454455456479116117118120740126148156186254[[#This Row],[Coste Componente]]*Tabla1103453454455456479116117118120740126148156186254[[#This Row],[Unidades]] -> 1041.4583
B115: VINAGRE BLANCO FRUCO X 3060ML | C115: g | D115: 40 | E115: 0 | F115: 40 | G115: =+VLOOKUP(Tabla1103453454455456479116117118120740126148156186254[[#This Row],[ArtÃ­culo]],Tabla34[#All],3,0) -> 10.193791 | H115: =+Tabla1103453454455456479116117118120740126148156186254[[#This Row],[Coste Componente]]*Tabla1103453454455456479116117118120740126148156186254[[#This Row],[Unidades]] -> 407.75163
B116: SAL REFISAL X 1000G | C116: g | D116: 5 | E116: 0 | F116: 5 | G116: =+VLOOKUP(Tabla1103453454455456479116117118120740126148156186254[[#This Row],[ArtÃ­culo]],Tabla34[#All],3,0) -> 2.401 | H116: =+Tabla1103453454455456479116117118120740126148156186254[[#This Row],[Coste Componente]]*Tabla1103453454455456479116117118120740126148156186254[[#This Row],[Unidades]] -> 12.005
B117: ACEITE DE AJONJOLI KADOYA X 1.62LT | C117: g | D117: 10 | E117: 0 | F117: 10 | G117: =+VLOOKUP(Tabla1103453454455456479116117118120740126148156186254[[#This Row],[ArtÃ­culo]],Tabla34[#All],3,0) -> 84.475309 | H117: =+Tabla1103453454455456479116117118120740126148156186254[[#This Row],[Coste Componente]]*Tabla1103453454455456479116117118120740126148156186254[[#This Row],[Unidades]] -> 844.75309
H118: =SUBTOTAL(109,Tabla1103453454455456479116117118120740126148156186254[Coste LÃ­nea]) -> 14546.251
B122: SUB. BIZCOCHUELO | J122: ANALISIS RECETA | M122: Preparacion
B123: ArtÃ­culo | C123: Unidad Medida | D123: Unidades Netas | E123: % Merma | F123: Unidades | G123: Coste Componente | H123: Coste LÃ­nea | J123: COSTO DEL PLATO | K123: =SUM(Tabla1103453454455456479116117118120740126148156186254256[Coste LÃ­nea]) -> 12447.718
...

Sheet JUGOS NATURALES
B6: LIMONADA NATURAL | J6: ANALISIS RECETA | M6: Preparacion
B7: Ingrediente | C7: Und | D7: Cant. | E7: Columna1 | F7: Columna2 | G7: Costo | H7: Total costo | J7: COSTO DEL PLATO | K7: =SUM(Tabla1103453454455456479455868778695108117127136[Total costo]) -> 595.81166
B8: SUB. LIMON DESHIDRATADO | C8: g | D8: 2 | E8: 0 | F8: 2 | H8: =+Tabla1103453454455456479455868778695108117127136[[#This Row],[Costo]]*Tabla1103453454455456479455868778695108117127136[[#This Row],[Columna2]] -> 0 | J8: MARGEN DE ERROR DEL 10% | K8: =+K7*10% -> 59.581166
B9: SUB. ALMIBAR | C9: g | D9: 40 | E9: 0 | F9: 40 | G9: =+VLOOKUP(Tabla1103453454455456479455868778695108117127136[[#This Row],[Ingrediente]],Tabla34[#All],3,0) -> 5.7702916 | H9: =+Tabla1103453454455456479455868778695108117127136[[#This Row],[Costo]]*Tabla1103453454455456479455868778695108117127136[[#This Row],[Columna2]] -> 230.81166 | J9: COSTO + MARGEN ERROR | K9: =+K7+K8 -> 655.39283
B10: BOLSA DE HIELO IGLU 18 KG | C10: g | D10: 140 | E10: 0 | F10: 140 | G10: =+VLOOKUP(Tabla1103453454455456479455868778695108117127136[[#This Row],[Ingrediente]],Tabla34[#All],3,0) -> 1 | H10: =+Tabla1103453454455456479455868778695108117127136[[#This Row],[Costo]]*Tabla1103453454455456479455868778695108117127136[[#This Row],[Columna2]] -> 140 | J10: VALOR DE VENTA | K10: 10000
B11: AGUA EPM | C11: g | D11: 200 | E11: 0 | F11: 200 | H11: =+Tabla1103453454455456479455868778695108117127136[[#This Row],[Costo]]*Tabla1103453454455456479455868778695108117127136[[#This Row],[Columna2]] -> 0 | J11: IPOCONSUMO | K11: =+K10/1.08*0.08 -> 740.74074
B12: LIMON TAHITI *KILO BAR | C12: g | D12: 50 | E12: 0 | F12: 50 | G12: =+VLOOKUP(Tabla1103453454455456479455868778695108117127136[[#This Row],[Ingrediente]],Tabla34[#All],3,0) -> 4.5 | H12: =+Tabla1103453454455456479455868778695108117127136[[#This Row],[Costo]]*Tabla1103453454455456479455868778695108117127136[[#This Row],[Columna2]] -> 225 | J12: VALOR ANTES DE IPO | K12: =+K10-K11 -> 9259.2593
H13: =SUBTOTAL(109,Tabla1103453454455456479455868778695108117127136[Total costo]) -> 595.81166 | J13: MARGEN. | K13: =+K9/K12 -> 0.070782426
J14: GANANCIA | K14: =+K12-K9 -> 8603.8664
J15: MARGEN PORCENTUAL | K15: =+K14/K9 -> 13.127801
B18: LIMONADA DE COCO | J18: ANALISIS RECETA | M18: Preparacion
B19: Ingrediente | C19: Und | D19: Cant. | E19: Columna1 | F19: Columna2 | G19: Costo | H19: Total costo | J19: COSTO DEL PLATO | K19: =SUM(Tabla110345345445545647936465969788796109118128137[Total costo]) -> 4251.7502
B20: OCHUVA CON CAPACHO | C20: g | D20: 1 | E20: 0 | F20: 1 | G20: =+VLOOKUP(Tabla110345345445545647936465969788796109118128137[[#This Row],[Ingrediente]],Tabla34[#All],3,0) -> 9 | H20: =+Tabla110345345445545647936465969788796109118128137[[#This Row],[Costo]]*Tabla110345345445545647936465969788796109118128137[[#This Row],[Columna2]] -> 9 | J20: MARGEN DE ERROR DEL 10% | K20: =+K19*10% -> 425.17502
B21: PULPA DE COCO PAQUETE X10UND | C21: uds | D21: 1 | E21: 0 | F21: 1 | G21: =+VLOOKUP(Tabla110345345445545647936465969788796109118128137[[#This Row],[Ingrediente]],Tabla34[#All],3,0) -> 3300 | H21: =+Tabla110345345445545647936465969788796109118128137[[#This Row],[Costo]]*Tabla110345345445545647936465969788796109118128137[[#This Row],[Columna2]] -> 3300 | J21: COSTO + MARGEN ERROR | K21: =+K19+K20 -> 4676.9252
B22: SUB. COCO DESHIDRATADO | C22: g | D22: 10 | E22: 0 | F22: 10 | G22: =+VLOOKUP(Tabla110345345445545647936465969788796109118128137[[#This Row],[Ingrediente]],Tabla34[#All],3,0) -> 45.040724 | H22: =+Tabla110345345445545647936465969788796109118128137[[#This Row],[Costo]]*Tabla110345345445545647936465969788796109118128137[[#This Row],[Columna2]] -> 450.40724 | J22: VALOR DE VENTA | K22: 13000
B23: SUB. ALMIBAR | C23: g | D23: 10 | E23: 0 | F23: 10 | G23: =+VLOOKUP(Tabla110345345445545647936465969788796109118128137[[#This Row],[Ingrediente]],Tabla34[#All],3,0) -> 5.7702916 | H23: =+Tabla110345345445545647936465969788796109118128137[[#This Row],[Costo]]*Tabla110345345445545647936465969788796109118128137[[#This Row],[Columna2]] -> 57.702916 | J23: IPOCONSUMO | K23: =+K22/1.08*0.08 -> 962.96296
B24: SUB. ZUMO DE LIMON | C24: g | D24: 40 | E24: 0 | F24: 40 | G24: =+VLOOKUP(Tabla110345345445545647936465969788796109118128137[[#This Row],[Ingrediente]],Tabla34[#All],3,0) -> 10.866 | H24: =+Tabla110345345445545647936465969788796109118128137[[#This Row],[Costo]]*Tabla110345345445545647936465969788796109118128137[[#This Row],[Columna2]] -> 434.64 | J24: VALOR ANTES DE IPO | K24: =+K22-K23 -> 12037.037
H25: =SUBTOTAL(109,Tabla110345345445545647936465969788796109118128137[Total costo]) -> 4251.7502 | J25: MARGEN. | K25: =+K21/K24 -> 0.38854455
J26: GANANCIA | K26: =+K24-K21 -> 7360.1119
J27: MARGEN PORCENTUAL | K27: =+K26/K21 -> 1.5737074
B29: JUGO FRUTOS ROJOS | J29: ANALISIS RECETA | M29: Preparacion
B30: Ingrediente | C30: Und | D30: Cant. | E30: Columna1 | F30: Columna2 | G30: Costo | H30: Total costo | J30: COSTO DEL PLATO | K30: =SUM(Tabla11034534544554564793637476070798897110119129138[Total costo]) -> 2136.45
B31: AZUCAR MANUELITA BOLSA X 5LB | C31: g | D31: 30 | E31: 0 | F31: 30 | G31: =+VLOOKUP(Tabla11034534544554564793637476070798897110119129138[[#This Row],[Ingrediente]],Tabla34[#All],3,0) -> 4.8816667 | H31: =+Tabla11034534544554564793637476070798897110119129138[[#This Row],[Costo]]*Tabla11034534544554564793637476070798897110119129138[[#This Row],[Columna2]] -> 146.45 | J31: MARGEN DE ERROR DEL 10% | K31: =+K30*10% -> 213.645
B32: PULPA DE FRUTOS DE ARANDANOS*10UND | C32: uds | D32: 1 | E32: 0 | F32: 1 | G32: =+VLOOKUP(Tabla11034534544554564793637476070798897110119129138[[#This Row],[Ingrediente]],Tabla34[#All],3,0) -> 1900 | H32: =+Tabla11034534544554564793637476070798897110119129138[[#This Row],[Costo]]*Tabla11034534544554564793637476070798897110119129138[[#This Row],[Columna2]] -> 1900 | J32: COSTO + MARGEN ERROR | K32: =+K30+K31 -> 2350.095
B33: FLOR DE JAMAICA X KILO | C33: g | D33: 1 | E33: 0 | F33: 1 | G33: =+VLOOKUP(Tabla11034534544554564793637476070798897110119129138[[#This Row],[Ingrediente]],Tabla34[#All],3,0) -> 90 | H33: =+Tabla11034534544554564793637476070798897110119129138[[#This Row],[Costo]]*Tabla11034534544554564793637476070798897110119129138[[#This Row],[Columna2]] -> 90 | J33: VALOR DE VENTA | K33: 13000
B34: AGUA EPM | C34: g | D34: 200 | E34: 0 | F34: 200 | H34: =+Tabla11034534544554564793637476070798897110119129138[[#This Row],[Costo]]*Tabla11034534544554564793637476070798897110119129138[[#This Row],[Columna2]] -> 0 | J34: IPOCONSUMO | K34: =+K33/1.08*0.08 -> 962.96296
H35: =SUBTOTAL(109,Tabla11034534544554564793637476070798897110119129138[Total costo]) -> 2136.45 | J35: VALOR ANTES DE IPO | K35: =+K33-K34 -> 12037.037
J36: MARGEN. | K36: =+K32/K35 -> 0.19523866
J37: GANANCIA | K37: =+K35-K32 -> 9686.942
J38: MARGEN PORCENTUAL | K38: =+K37/K32 -> 4.1219364
B40: JUGO DE MANGO | J40: ANALISIS RECETA | M40: Preparacion
B41: Ingrediente | C41: Und | D41: Cant. | E41: Columna1 | F41: Columna2 | G41: Costo | H41: Total costo | J41: COSTO DEL PLATO | K41: =SUM(Tabla11034534544554564793638486171808998111120130139[Total costo]) -> 1969.1211
B42: PULPA MANGO 1000 GR | C42: uds | D42: 1 | E42: 0 | F42: 1 | G42: =+VLOOKUP(Tabla11034534544554564793638486171808998111120130139[[#This Row],[Ingrediente]],Tabla34[#All],3,0) -> 1800 | H42: =+Tabla11034534544554564793638486171808998111120130139[[#This Row],[Costo]]*Tabla11034534544554564793638486171808998111120130139[[#This Row],[Columna2]] -> 1800 | J42: MARGEN DE ERROR DEL 10% | K42: =+K41*10% -> 196.91211
B43: AZUCAR MANUELITA BOLSA X 5LB | C43: g | D43: 30 | E43: 0 | F43: 30 | G43: =+VLOOKUP(Tabla11034534544554564793638486171808998111120130139[[#This Row],[Ingrediente]],Tabla34[#All],3,0) -> 4.8816667 | H43: =+Tabla11034534544554564793638486171808998111120130139[[#This Row],[Costo]]*Tabla11034534544554564793638486171808998111120130139[[#This Row],[Columna2]] -> 146.45 | J43: COSTO + MARGEN ERROR | K43: =+K41+K42 -> 2166.0332
B44: SUB. MANGO DESHIDRATADO | C44: g | D44: 1 | E44: 0 | F44: 1 | G44: =+VLOOKUP(Tabla11034534544554564793638486171808998111120130139[[#This Row],[Ingrediente]],Tabla34[#All],3,0) -> 22.671053 | H44: =+Tabla11034534544554564793638486171808998111120130139[[#This Row],[Costo]]*Tabla11034534544554564793638486171808998111120130139[[#This Row],[Columna2]] -> 22.671053 | J44: VALOR DE VENTA | K44: 13500
B45: AGUA EPM | C45: g | D45: 200 | E45: 0 | F45: 200 | H45: =+Tabla11034534544554564793638486171808998111120130139[[#This Row],[Costo]]*Tabla11034534544554564793638486171808998111120130139[[#This Row],[Columna2]] -> 0 | J45: IPOCONSUMO | K45: =+K44/1.08*0.08 -> 1000
H46: =SUBTOTAL(109,Tabla11034534544554564793638486171808998111120130139[Total costo]) -> 1969.1211 | J46: VALOR ANTES DE IPO | K46: =+K44-K45 -> 12500
J47: MARGEN. | K47: =+K43/K46 -> 0.17328265
J48: GANANCIA | K48: =+K46-K43 -> 10333.967
J49: MARGEN PORCENTUAL | K49: =+K48/K43 -> 4.7709181
B53: MANGO BICHE | J53: ANALISIS RECETA | M53: Preparacion
B54: Ingrediente | C54: Und | D54: Cant. | E54: Columna1 | F54: Columna2 | G54: Costo | H54: Total costo | J54: COSTO DEL PLATO | K54: =SUM(Tabla11034534544554564793638486171808998111120130139162[Total costo]) -> 3776.5467
B55: PULPA MANGO BICHE 1200GR | C55: uds | D55: 1 | E55: 0 | F55: 1 | G55: =+VLOOKUP(Tabla11034534544554564793638486171808998111120130139162[[#This Row],[Ingrediente]],Tabla34[#All],3,0) -> 2714.2857 | H55: =+Tabla11034534544554564793638486171808998111120130139162[[#This Row],[Costo]]*Tabla11034534544554564793638486171808998111120130139162[[#This Row],[Columna2]] -> 2714.2857 | J55: MARGEN DE ERROR DEL 10% | K55: =+K54*10% -> 377.65467
B56: SAL REFISAL X 1000G | C56: g | D56: 1 | E56: 0 | F56: 1 | G56: =+VLOOKUP(Tabla11034534544554564793638486171808998111120130139162[[#This Row],[Ingrediente]],Tabla34[#All],3,0) -> 2.401 | H56: =+Tabla11034534544554564793638486171808998111120130139162[[#This Row],[Costo]]*Tabla11034534544554564793638486171808998111120130139162[[#This Row],[Columna2]] -> 2.401 | J56: COSTO + MARGEN ERROR | K56: =+K54+K55 -> 4154.2014
B57: SALSA EN POLVO TAJIN CLASICO X 142G | C57: g | D57: 1 | E57: 0 | F57: 1 | G57: =+VLOOKUP(Tabla11034534544554564793638486171808998111120130139162[[#This Row],[Ingrediente]],Tabla34[#All],3,0) -> 61.6825 | H57: =+Tabla11034534544554564793638486171808998111120130139162[[#This Row],[Costo]]*Tabla11034534544554564793638486171808998111120130139162[[#This Row],[Columna2]] -> 61.6825 | J57: VALOR DE VENTA | K57: 13500
B58: AGUA EPM | C58: g | D58: 150 | E58: 0 | F58: 150 | H58: =+Tabla11034534544554564793638486171808998111120130139162[[#This Row],[Costo]]*Tabla11034534544554564793638486171808998111120130139162[[#This Row],[Columna2]] -> 0 | J58: IPOCONSUMO | K58: =+K57/1.08*0.08 -> 1000
B59: SUB. ZUMO DE LIMON | C59: g | D59: 60 | E59: 0 | F59: 60 | G59: =+VLOOKUP(Tabla11034534544554564793638486171808998111120130139162[[#This Row],[Ingrediente]],Tabla34[#All],3,0) -> 10.866 | H59: =+Tabla11034534544554564793638486171808998111120130139162[[#This Row],[Costo]]*Tabla11034534544554564793638486171808998111120130139162[[#This Row],[Columna2]] -> 651.96 | J59: VALOR ANTES DE IPO | K59: =+K57-K58 -> 12500
B60: SUB. ALMIBAR | C60: g | D60: 60 | E60: 0 | F60: 60 | G60: =+VLOOKUP(Tabla11034534544554564793638486171808998111120130139162[[#This Row],[Ingrediente]],Tabla34[#All],3,0) -> 5.7702916 | H60: =+Tabla11034534544554564793638486171808998111120130139162[[#This Row],[Costo]]*Tabla11034534544554564793638486171808998111120130139162[[#This Row],[Columna2]] -> 346.2175 | J60: MARGEN. | K60: =+K56/K59 -> 0.33233611
H61: =SUBTOTAL(109,Tabla11034534544554564793638486171808998111120130139162[Total costo]) -> 3776.5467 | J61: GANANCIA | K61: =+K59-K56 -> 8345.7986
J62: MARGEN PORCENTUAL | K62: =+K61/K56 -> 2.0090019

Sheet LANGOSTINOS
B6: LANGOSTINOS ARREBATADOS | J6: ANALISIS RECETA | M6: Preparacion
B7: Ingrediente | C7: Und | D7: Cant. | E7: Columna1 | F7: Columna2 | G7: Costo | H7: Total costo | J7: COSTO DEL PLATO | K7: =SUM(Tabla11034534544554564794558[Total costo]) -> 15030.98 | M7: 1. Apanar los langostinos y llevarlos a fritura profunda.
B8: LANGOSTINOS CRUDO 16/20 X UNIDAD | C8: uds | D8: 4 | E8: 0 | F8: 4 | G8: =+VLOOKUP(Tabla11034534544554564794558[[#This Row],[Ingrediente]],Tabla34[#All],3,0) -> 1600 | H8: =+Tabla11034534544554564794558[[#This Row],[Costo]]*Tabla11034534544554564794558[[#This Row],[Columna2]] -> 6400 | J8: MARGEN DE ERROR DEL 10% | K8: =+K7*10% -> 1503.098 | M8: 2. Llevar a una manga pastelera el puré de papa (boquilla rizada).
B9: QUESO ALPINA PARMESANO RAYADO 2.5 L | C9: g | D9: 30 | E9: 0 | F9: 30 | G9: =+VLOOKUP(Tabla11034534544554564794558[[#This Row],[Ingrediente]],Tabla34[#All],3,0) -> 60.9875 | H9: =+Tabla11034534544554564794558[[#This Row],[Costo]]*Tabla11034534544554564794558[[#This Row],[Columna2]] -> 1829.625 | J9: COSTO + MARGEN ERROR | K9: =+K7+K8 -> 16534.078 | M9: 3. Para la salsa llevamos en un wok la crema de leche, parmesano, pasta de rocoto, sal (punto de napa)
B10: SUB. PURE DE PAPA | C10: g | D10: 150 | E10: 0 | F10: 150 | G10: =+VLOOKUP(Tabla11034534544554564794558[[#This Row],[Ingrediente]],Tabla34[#All],3,0) -> 16.73096 | H10: =+Tabla11034534544554564794558[[#This Row],[Costo]]*Tabla11034534544554564794558[[#This Row],[Columna2]] -> 2509.6441 | J10: VALOR DE VENTA | K10: 56000
B11: SUB. PASTA ROCOTO | C11: g | D11: 40 | E11: 0 | F11: 40 | G11: =+VLOOKUP(Tabla11034534544554564794558[[#This Row],[Ingrediente]],Tabla34[#All],3,0) -> 40.42512 | H11: =+Tabla11034534544554564794558[[#This Row],[Costo]]*Tabla11034534544554564794558[[#This Row],[Columna2]] -> 1617.0048 | J11: IPOCONSUMO | K11: =+K10/1.08*0.08 -> 4148.1481
B12: SUB. HUEVO BATIDO | C12: g | D12: 30 | E12: 0 | F12: 30 | G12: =+VLOOKUP(Tabla11034534544554564794558[[#This Row],[Ingrediente]],Tabla34[#All],3,0) -> 18.782609 | H12: =+Tabla11034534544554564794558[[#This Row],[Costo]]*Tabla11034534544554564794558[[#This Row],[Columna2]] -> 563.47826 | J12: VALOR ANTES DE IPO | K12: =+K10-K11 -> 51851.852 | M12: Emplatado
B13: SUB. CHIMICHURRY ROJO | C13: g | D13: 20 | E13: 0 | F13: 20 | G13: =+VLOOKUP(Tabla11034534544554564794558[[#This Row],[Ingrediente]],Tabla34[#All],3,0) -> 20.160619 | H13: =+Tabla11034534544554564794558[[#This Row],[Costo]]*Tabla11034534544554564794558[[#This Row],[Columna2]] -> 403.21238 | J13: MARGEN. | K13: =+K9/K12 -> 0.3188715 | M13: 1. En una parrilla redonda y caliente poner el puré de papa con la ayuda de la manga pastelera.
B14: SUB. ACEVICHADA | C14: g | D14: 15 | E14: 0 | F14: 15 | G14: =+VLOOKUP(Tabla11034534544554564794558[[#This Row],[Ingrediente]],Tabla34[#All],3,0) -> 26.416185 | H14: =+Tabla11034534544554564794558[[#This Row],[Costo]]*Tabla11034534544554564794558[[#This Row],[Columna2]] -> 396.24277 | J14: GANANCIA | K14: =+K12-K9 -> 35317.774 | M14: 2. En los costados del puré colocar la salsa hecha en el wok.
B15: CREMA DE LECHE X 9700G | C15: g | D15: 20 | E15: 0 | F15: 20 | G15: =+VLOOKUP(Tabla11034534544554564794558[[#This Row],[Ingrediente]],Tabla34[#All],3,0) -> 19.804167 | H15: =+Tabla11034534544554564794558[[#This Row],[Costo]]*Tabla11034534544554564794558[[#This Row],[Columna2]] -> 396.08333 | J15: MARGEN PORCENTUAL | K15: =+K14/K9 -> 2.1360595 | M15: 3. Sobre la salsa le agregamos la acevichada realizando líneas con la ayuda de un tetero.
B16: BROTES DE RABANO 50 | C16: g | D16: 1 | E16: 0 | F16: 1 | G16: =+VLOOKUP(Tabla11034534544554564794558[[#This Row],[Ingrediente]],Tabla34[#All],3,0) -> 307.5 | H16: =+Tabla11034534544554564794558[[#This Row],[Costo]]*Tabla11034534544554564794558[[#This Row],[Columna2]] -> 307.5 | M16: Decoramos con mézclum, chimichurri y esparcimos ajonjolí.
B17: HARINA DE TRIGO HAZ DE OROS BOLSA X550g | C17: g | D17: 60 | E17: 0 | F17: 60 | G17: =+VLOOKUP(Tabla11034534544554564794558[[#This Row],[Ingrediente]],Tabla34[#All],3,0) -> 4.2672 | H17: =+Tabla11034534544554564794558[[#This Row],[Costo]]*Tabla11034534544554564794558[[#This Row],[Columna2]] -> 256.032
B18: COCO RALLADO NRO1 IPRODESA XK CD21 | C18: g | D18: 5 | E18: 0 | F18: 5 | G18: =+VLOOKUP(Tabla11034534544554564794558[[#This Row],[Ingrediente]],Tabla34[#All],3,0) -> 37.6305 | H18: =+Tabla11034534544554564794558[[#This Row],[Costo]]*Tabla11034534544554564794558[[#This Row],[Columna2]] -> 188.1525
B19: VINO TINTO CAVIC TETRAPACK X 1LT | C19: g | D19: 5 | E19: 0 | F19: 5 | G19: =+VLOOKUP(Tabla11034534544554564794558[[#This Row],[Ingrediente]],Tabla34[#All],3,0) -> 15.193341 | H19: =+Tabla11034534544554564794558[[#This Row],[Costo]]*Tabla11034534544554564794558[[#This Row],[Columna2]] -> 75.966706
B20: AJONJOLI NEGRO X 500GR | C20: g | D20: 1 | E20: 0 | F20: 1 | G20: =+VLOOKUP(Tabla11034534544554564794558[[#This Row],[Ingrediente]],Tabla34[#All],3,0) -> 73.78 | H20: =+Tabla11034534544554564794558[[#This Row],[Costo]]*Tabla11034534544554564794558[[#This Row],[Columna2]] -> 73.78
B21: SUB. PASTA DE AJO | C21: g | D21: 1 | E21: 0 | F21: 1 | G21: =+VLOOKUP(Tabla11034534544554564794558[[#This Row],[Ingrediente]],Tabla34[#All],3,0) -> 14.257835 | H21: =+Tabla11034534544554564794558[[#This Row],[Costo]]*Tabla11034534544554564794558[[#This Row],[Columna2]] -> 14.257835
H22: =SUBTOTAL(109,Tabla11034534544554564794558[Total costo]) -> 15030.98
B24: LANGOSTINOS EN COCO Y CURRY | J24: ANALISIS RECETA | M24: Preparacion
B25: Ingrediente | C25: Und | D25: Cant. | E25: Columna1 | F25: Columna2 | G25: Costo | H25: Total costo | J25: COSTO DEL PLATO | K25: =SUM(Tabla1103453454455456479364659[Total costo]) -> 12302.781 | M25: 1. Salteamos los langostinos previamente sazonados, aparte sofreímos la cebolla, agregamos el curry, crema de coco y la crema de leche para la salsa.
B26: LANGOSTINOS CRUDO 16/20 X UNIDAD | C26: uds | D26: 4 | E26: 0 | F26: 4 | G26: =+VLOOKUP(Tabla1103453454455456479364659[[#This Row],[Ingrediente]],Tabla34[#All],3,0) -> 1600 | H26: =+Tabla1103453454455456479364659[[#This Row],[Costo]]*Tabla1103453454455456479364659[[#This Row],[Columna2]] -> 6400 | J26: MARGEN DE ERROR DEL 10% | K26: =+K25*10% -> 1230.2781 | M26: 2. Calentamos el puré y agregamos tomate perla y queso parmesano
B27: SUB. PURE DE PAPA | C27: g | D27: 150 | E27: 0 | F27: 150 | G27: =+VLOOKUP(Tabla1103453454455456479364659[[#This Row],[Ingrediente]],Tabla34[#All],3,0) -> 16.73096 | H27: =+Tabla1103453454455456479364659[[#This Row],[Costo]]*Tabla1103453454455456479364659[[#This Row],[Columna2]] -> 2509.6441 | J27: COSTO + MARGEN ERROR | K27: =+K25+K26 -> 13533.059
B28: CREMA DE COCO ROLAND X 960 GR | C28: g | D28: 30 | E28: 0 | F28: 30 | G28: =+VLOOKUP(Tabla1103453454455456479364659[[#This Row],[Ingrediente]],Tabla34[#All],3,0) -> 39.071701 | H28: =+Tabla1103453454455456479364659[[#This Row],[Costo]]*Tabla1103453454455456479364659[[#This Row],[Columna2]] -> 1172.151 | J28: VALOR DE VENTA | K28: 56000 | M28: Emplatado
B29: CREMA DE LECHE X 9700G | C29: g | D29: 60 | E29: 0 | F29: 60 | G29: =+VLOOKUP(Tabla1103453454455456479364659[[#This Row],[Ingrediente]],Tabla34[#All],3,0) -> 19.804167 | H29: =+Tabla1103453454455456479364659[[#This Row],[Costo]]*Tabla1103453454455456479364659[[#This Row],[Columna2]] -> 1188.25 | J29: IPOCONSUMO | K29: =+K28/1.08*0.08 -> 4148.1481 | M29: 1. En el centro del plato colocamos el puré.
B30: QUESO ALPINA PARMESANO RAYADO 2.5 L | C30: g | D30: 5 | E30: 0 | F30: 5 | G30: =+VLOOKUP(Tabla1103453454455456479364659[[#This Row],[Ingrediente]],Tabla34[#All],3,0) -> 60.9875 | H30: =+Tabla1103453454455456479364659[[#This Row],[Costo]]*Tabla1103453454455456479364659[[#This Row],[Columna2]] -> 304.9375 | J30: VALOR ANTES DE IPO | K30: =+K28-K29 -> 51851.852 | M30: 2. Coronamos con los cuatro langostinos
B31: BROTES DE RABANO 50 | C31: g | D31: 1 | E31: 0 | F31: 1 | G31: =+VLOOKUP(Tabla1103453454455456479364659[[#This Row],[Ingrediente]],Tabla34[#All],3,0) -> 307.5 | H31: =+Tabla1103453454455456479364659[[#This Row],[Costo]]*Tabla1103453454455456479364659[[#This Row],[Columna2]] -> 307.5 | J31: MARGEN. | K31: =+K27/K30 -> 0.26099471 | M31: 3. Servimos la salsa aparte
B32: SUB. TIERRA DE ARVERJA | C32: g | D32: 5 | E32: 0 | F32: 5 | G32: =+VLOOKUP(Tabla1103453454455456479364659[[#This Row],[Ingrediente]],Tabla34[#All],3,0) -> 44.585987 | H32: =+Tabla1103453454455456479364659[[#This Row],[Costo]]*Tabla1103453454455456479364659[[#This Row],[Columna2]] -> 222.92994 | J32: GANANCIA | K32: =+K30-K27 -> 38318.793 | M32: 4. La tierra de lentejas va alrededor del puré, los tomates perla y las flores comestibles
B33: TOMATE PERLA X KILO | C33: g | D33: 5.0000001 | E33: 5 | F33: 5.263158 | G33: =+VLOOKUP(Tabla1103453454455456479364659[[#This Row],[Ingrediente]],Tabla34[#All],3,0) -> 37.5 | H33: =+Tabla1103453454455456479364659[[#This Row],[Costo]]*Tabla1103453454455456479364659[[#This Row],[Columna2]] -> 197.36843 | J33: MARGEN PORCENTUAL | K33: =+K32/K27 -> 2.8314953
B34: CURRY BADIA X454G | C34: g | D34: 5 | E34: 0 | F34: 5 | G34: =+VLOOKUP(Tabla1103453454455456479364659[[#This Row],[Ingrediente]],Tabla34[#All],3,0) -> 0 | H34: =+Tabla1103453454455456479364659[[#This Row],[Costo]]*Tabla1103453454455456479364659[[#This Row],[Columna2]] -> 0
H35: =SUBTOTAL(109,Tabla1103453454455456479364659[Total costo]) -> 12302.781
B38: LANGOSTINOS TIMBIQUI | J38: ANALISIS RECETA | M38: Preparacion
B39: Ingrediente | C39: Und | D39: Cant. | E39: Columna1 | F39: Columna2 | G39: Costo | H39: Total costo | J39: COSTO DEL PLATO | K39: =SUM(Tabla110345345445545647936374760[Total costo]) -> 13086.055
B40: LANGOSTINOS CRUDO 16/20 X UNIDAD | C40: uds | D40: 4 | E40: 0 | F40: 4 | G40: =+VLOOKUP(Tabla110345345445545647936374760[[#This Row],[Ingrediente]],Tabla34[#All],3,0) -> 1600 | H40: =+Tabla110345345445545647936374760[[#This Row],[Costo]]*Tabla110345345445545647936374760[[#This Row],[Columna2]] -> 6400 | J40: MARGEN DE ERROR DEL 10% | K40: =+K39*10% -> 1308.6055
B41: QUESO COSTEÃ‘O BLOQUE 2,5K | C41: g | D41: 60 | E41: 0 | F41: 60 | G41: =+VLOOKUP(Tabla110345345445545647936374760[[#This Row],[Ingrediente]],Tabla34[#All],3,0) -> 32.29 | H41: =+Tabla110345345445545647936374760[[#This Row],[Costo]]*Tabla110345345445545647936374760[[#This Row],[Columna2]] -> 1937.4 | J41: COSTO + MARGEN ERROR | K41: =+K39+K40 -> 14394.66
B42: SUB. PURE DE MADURO | C42: uds | D42: 1 | E42: 0 | F42: 1 | G42: =+VLOOKUP(Tabla110345345445545647936374760[[#This Row],[Ingrediente]],Tabla34[#All],3,0) -> 848.48485 | H42: =+Tabla110345345445545647936374760[[#This Row],[Costo]]*Tabla110345345445545647936374760[[#This Row],[Columna2]] -> 848.48485 | J42: VALOR DE VENTA | K42: 59000
B43: AGUACATE CHOCKETTE X KILO | C43: g | D43: 50 | E43: 25 | F43: 66.667 | G43: =+VLOOKUP(Tabla110345345445545647936374760[[#This Row],[Ingrediente]],Tabla34[#All],3,0) -> 8.5 | H43: =+Tabla110345345445545647936374760[[#This Row],[Costo]]*Tabla110345345445545647936374760[[#This Row],[Columna2]] -> 566.6695 | J43: IPOCONSUMO | K43: =+K42/1.08*0.08 -> 4370.3704
B44: CREMA DE LECHE X 9700G | C44: g | D44: 30 | E44: 0 | F44: 30 | G44: =+VLOOKUP(Tabla110345345445545647936374760[[#This Row],[Ingrediente]],Tabla34[#All],3,0) -> 19.804167 | H44: =+Tabla110345345445545647936374760[[#This Row],[Costo]]*Tabla110345345445545647936374760[[#This Row],[Columna2]] -> 594.125 | J44: VALOR ANTES DE IPO | K44: =+K42-K43 -> 54629.63 | M44: Emplatado
B45: SUERO ATOYABUEY BONGA DEL SINU 5000 | C45: g | D45: 20 | E45: 0 | F45: 20 | G45: =+VLOOKUP(Tabla110345345445545647936374760[[#This Row],[Ingrediente]],Tabla34[#All],3,0) -> 24.7145 | H45: =+Tabla110345345445545647936374760[[#This Row],[Costo]]*Tabla110345345445545647936374760[[#This Row],[Columna2]] -> 494.29 | J45: MARGEN. | K45: =+K41/K44 -> 0.26349547
B46: QUESO ALPINA AZUL BLQ 8 LBS APROX | C46: g | D46: 5 | E46: 0 | F46: 5 | G46: =+VLOOKUP(Tabla110345345445545647936374760[[#This Row],[Ingrediente]],Tabla34[#All],3,0) -> 71.281042 | H46: =+Tabla110345345445545647936374760[[#This Row],[Costo]]*Tabla110345345445545647936374760[[#This Row],[Columna2]] -> 356.40521 | J46: GANANCIA | K46: =+K44-K41 -> 40234.969
B47: BROTES DE RABANO 50 | C47: g | D47: 1 | E47: 0 | F47: 1 | G47: =+VLOOKUP(Tabla110345345445545647936374760[[#This Row],[Ingrediente]],Tabla34[#All],3,0) -> 307.5 | H47: =+Tabla110345345445545647936374760[[#This Row],[Costo]]*Tabla110345345445545647936374760[[#This Row],[Columna2]] -> 307.5 | J47: MARGEN PORCENTUAL | K47: =+K46/K41 -> 2.7951316
B48: QUESO ALPINA PARMESANO RAYADO 2.5 L | C48: g | D48: 5 | E48: 0 | F48: 5 | G48: =+VLOOKUP(Tabla110345345445545647936374760[[#This Row],[Ingrediente]],Tabla34[#All],3,0) -> 60.9875 | H48: =+Tabla110345345445545647936374760[[#This Row],[Costo]]*Tabla110345345445545647936374760[[#This Row],[Columna2]] -> 304.9375
B49: SUB. ACEVICHADA | C49: g | D49: 10 | E49: 0 | F49: 10 | G49: =+VLOOKUP(Tabla110345345445545647936374760[[#This Row],[Ingrediente]],Tabla34[#All],3,0) -> 26.416185 | H49: =+Tabla110345345445545647936374760[[#This Row],[Costo]]*Tabla110345345445545647936374760[[#This Row],[Columna2]] -> 264.16185
B50: SUB. ADEREZO PICADILLO | C50: g | D50: 20 | E50: 0 | F50: 20 | G50: =+VLOOKUP(Tabla110345345445545647936374760[[#This Row],[Ingrediente]],Tabla34[#All],3,0) -> 11.137326 | H50: =+Tabla110345345445545647936374760[[#This Row],[Costo]]*Tabla110345345445545647936374760[[#This Row],[Columna2]] -> 222.74653
B51: SUB. HUEVO BATIDO | C51: g | D51: 10 | E51: 0 | F51: 10 | G51: =+VLOOKUP(Tabla110345345445545647936374760[[#This Row],[Ingrediente]],Tabla34[#All],3,0) -> 18.782609 | H51: =+Tabla110345345445545647936374760[[#This Row],[Costo]]*Tabla110345345445545647936374760[[#This Row],[Columna2]] -> 187.82609
B52: QUESO MOZZARELLA BLOQUE X 2,5K | C52: g | D52: 15 | E52: 0 | F52: 15 | G52: =+VLOOKUP(Tabla110345345445545647936374760[[#This Row],[Ingrediente]],Tabla34[#All],3,0) -> 24.1152 | H52: =+Tabla110345345445545647936374760[[#This Row],[Costo]]*Tabla110345345445545647936374760[[#This Row],[Columna2]] -> 361.728
B53: SUB. MAYONESA DE MARACUYA | C53: g | D53: 5 | E53: 0 | F53: 5 | G53: =+VLOOKUP(Tabla110345345445545647936374760[[#This Row],[Ingrediente]],Tabla34[#All],3,0) -> 30.254664 | H53: =+Tabla110345345445545647936374760[[#This Row],[Costo]]*Tabla110345345445545647936374760[[#This Row],[Columna2]] -> 151.27332
B54: HARINA DE TRIGO HAZ DE OROS BOLSA X550g | C54: g | D54: 10 | E54: 0 | F54: 10 | G54: =+VLOOKUP(Tabla110345345445545647936374760[[#This Row],[Ingrediente]],Tabla34[#All],3,0) -> 4.2672 | H54: =+Tabla110345345445545647936374760[[#This Row],[Costo]]*Tabla110345345445545647936374760[[#This Row],[Columna2]] -> 42.672
B55: SALSA DE SOYA X 2O LITROS | C55: g | D55: 3 | E55: 0 | F55: 3 | G55: =+VLOOKUP(Tabla110345345445545647936374760[[#This Row],[Ingrediente]],Tabla34[#All],3,0) -> 8.925 | H55: =+Tabla110345345445545647936374760[[#This Row],[Costo]]*Tabla110345345445545647936374760[[#This Row],[Columna2]] -> 26.775
B56: SUB. PASTA DE AJO | C56: g | D56: 1 | E56: 0 | F56: 1 | G56: =+VLOOKUP(Tabla110345345445545647936374760[[#This Row],[Ingrediente]],Tabla34[#All],3,0) -> 14.257835 | H56: =+Tabla110345345445545647936374760[[#This Row],[Costo]]*Tabla110345345445545647936374760[[#This Row],[Columna2]] -> 14.257835
B57: SAL REFISAL X 1000G | C57: g | D57: 2 | E57: 0 | F57: 2 | G57: =+VLOOKUP(Tabla110345345445545647936374760[[#This Row],[Ingrediente]],Tabla34[#All],3,0) -> 2.401 | H57: =+Tabla110345345445545647936374760[[#This Row],[Costo]]*Tabla110345345445545647936374760[[#This Row],[Columna2]] -> 4.802
H58: =SUBTOTAL(109,Tabla110345345445545647936374760[Total costo]) -> 13086.055

Sheet ENTRADAS
B6: BOCADOS DEL ORIENTE | J6: ANALISIS RECETA | M6: Preparacion
B7: Ingrediente | C7: Und | D7: Unidades Netas | E7: % Merma | F7: Unidades | G7: Costo | H7: Total costo | J7: COSTO DEL PLATO | K7: =SUM(Tabla1103453454455456479[Total costo]) -> 6107.2178 | M7: 1. Llevar a fritura profunda (160 grados) los palmitos previamente apanados.
B8: BROTES DE RABANO 50 | C8: g | D8: 1 | E8: 0 | F8: 1 | G8: =+VLOOKUP(Tabla1103453454455456479[[#This Row],[Ingrediente]],Tabla34[#All],3,0) -> 307.5 | H8: =+Tabla1103453454455456479[[#This Row],[Costo]]*Tabla1103453454455456479[[#This Row],[Unidades]] -> 307.5 | J8: MARGEN DE ERROR DEL 5% | K8: =+K7*5% -> 305.36089 | M8: 2. Cortar cada palmito en forma diagonal.
B9: SUB. MELCOCHA | C9: g | D9: 40 | E9: 0 | F9: 40 | G9: =+VLOOKUP(Tabla1103453454455456479[[#This Row],[Ingrediente]],Tabla34[#All],3,0) -> 18.115947 | H9: =+Tabla1103453454455456479[[#This Row],[Costo]]*Tabla1103453454455456479[[#This Row],[Unidades]] -> 724.63787 | J9: COSTO + MARGEN ERROR | K9: =+K7+K8 -> 6412.5787
B10: SUB. PALMITOS | C10: uds | D10: 3 | E10: 0 | F10: 3 | G10: =+VLOOKUP(Tabla1103453454455456479[[#This Row],[Ingrediente]],Tabla34[#All],3,0) -> 612.85 | H10: =+Tabla1103453454455456479[[#This Row],[Costo]]*Tabla1103453454455456479[[#This Row],[Unidades]] -> 1838.55 | J10: VALOR DE VENTA SUGERIDO | K10: 31000 | M10: Emplatado
B11: SUB. SALSA DINAMITA | C11: g | D11: 80 | E11: 0 | F11: 80 | G11: =+VLOOKUP(Tabla1103453454455456479[[#This Row],[Ingrediente]],Tabla34[#All],3,0) -> 37.67 | H11: =+Tabla1103453454455456479[[#This Row],[Costo]]*Tabla1103453454455456479[[#This Row],[Unidades]] -> 3013.6 | J11: IPOCONSUMO | K11: =+K10/1.08*0.08 -> 2296.2963 | M11: 1. Realizar lagrimales en línea recta, dividiendo el plato en dos.
B12: SUB. TIERRA DE ARVERJA | C12: g | D12: 5 | E12: 0 | F12: 5 | G12: =+VLOOKUP(Tabla1103453454455456479[[#This Row],[Ingrediente]],Tabla34[#All],3,0) -> 44.585987 | H12: =+Tabla1103453454455456479[[#This Row],[Costo]]*Tabla1103453454455456479[[#This Row],[Unidades]] -> 222.92994 | J12: VALOR ANTES DE IPO | K12: =+K10-K11 -> 28703.704 | M12: 2. Hacer un espejo con la tierra de arveja en la mitad del plato.
H13: =SUBTOTAL(109,Tabla1103453454455456479[Total costo]) -> 6107.2178 | J13: MARGEN. | K13: =+K9/K12 -> 0.22340597 | M13: 3. Sobre el espejo de arveja ubicar los palmitos en forma de zigzag.
J14: GANANCIA | K14: =+K12-K9 -> 22291.125 | M14: 4. Coronamos con la salsa dinamita, decoramos con brotes y flores comestibles.
J15: MARGEN PORCENTUAL | K15: =+K14/K9 -> 3.4761562
B17: DEDOS DE QUESO COSTEÃ‘O | J17: ANALISIS RECETA | M17: Preparacion
B18: Ingrediente | C18: Und | D18: Unidades Netas | E18: % Merma | F18: Unidades | G18: Costo | H18: Total costo | J18: COSTO DEL PLATO | K18: =SUM(Tabla1103453454455456479364654[Total costo]) -> 5074.2176 | M18: 1. Cortar el queso costeño en bastones de 2,5 cm x 7,5 cm.
B19: SUB. MERMELADA DE AJI DULCE | C19: g | D19: 40 | E19: 0 | F19: 40 | G19: =+VLOOKUP(Tabla1103453454455456479364654[[#This Row],[Ingrediente]],Tabla34[#All],3,0) -> 9.5229411 | H19: =+Tabla1103453454455456479364654[[#This Row],[Costo]]*Tabla1103453454455456479364654[[#This Row],[Unidades]] -> 380.91764 | J19: MARGEN DE ERROR DEL 5% | K19: =+K18*5% -> 253.71088 | M19: 2. Llevar a fritura profunda (160 grados) hasta que doren.
B20: QUESO COSTEÃ‘O BLOQUE 2,5K | C20: g | D20: 120 | E20: 0 | F20: 120 | G20: =+VLOOKUP(Tabla1103453454455456479364654[[#This Row],[Ingrediente]],Tabla34[#All],3,0) -> 32.29 | H20: =+Tabla1103453454455456479364654[[#This Row],[Costo]]*Tabla1103453454455456479364654[[#This Row],[Unidades]] -> 3874.8 | J20: COSTO + MARGEN ERROR | K20: =+K18+K19 -> 5327.9285
B21: BROTES DE RABANO 50 | C21: g | D21: 1 | E21: 0 | F21: 1 | G21: =+VLOOKUP(Tabla1103453454455456479364654[[#This Row],[Ingrediente]],Tabla34[#All],3,0) -> 307.5 | H21: =+Tabla1103453454455456479364654[[#This Row],[Costo]]*Tabla1103453454455456479364654[[#This Row],[Unidades]] -> 307.5 | J21: VALOR DE VENTA | K21: 26000 | M21: Emplatado
B22: FLORES COMESTIBLES (PENSAMIENTOS) | C22: g | D22: 1 | E22: 0 | F22: 1 | G22: =+VLOOKUP(Tabla1103453454455456479364654[[#This Row],[Ingrediente]],Tabla34[#All],3,0) -> 511 | H22: =+Tabla1103453454455456479364654[[#This Row],[Costo]]*Tabla1103453454455456479364654[[#This Row],[Unidades]] -> 511 | J22: IPOCONSUMO | K22: =+K21/1.08*0.08 -> 1925.9259 | M22: 1. Formar una torre con los quesos.
H23: =SUBTOTAL(109,Tabla1103453454455456479364654[Total costo]) -> 5074.2176 | J23: VALOR ANTES DE IPO | K23: =+K21-K22 -> 24074.074 | M23: 2. Verter en una salsera la mermelada de ají
J24: MARGEN. | K24: =+K20/K23 -> 0.22131395 | M24: 3. Decoramos con brotes y flores.
J25: GANANCIA | K25: =+K23-K20 -> 18746.146
J26: MARGEN PORCENTUAL | K26: =+K25/K20 -> 3.5184679
B29: GRATINADO DE JAIBA | J29: ANALISIS RECETA | M29: Preparacion
B30: Ingrediente | C30: Und | D30: Unidades Netas | E30: % Merma | F30: Unidades | G30: Costo | H30: Total costo | J30: COSTO DEL PLATO | K30: =SUM(Tabla11034534544554564793637[Total costo]) -> 7112.3836 | M30: 1. Llevar a un wok la jaiba y agregar los ingredientes como la leche de coco, la pasta rocoto, pasta de ají amarillo, coco deshidratado, sal y fondo. Acentuar sabores y dejar espesar.
B31: COM PAN BAGUETTE CONGELADO X 400G PT MB | C31: uds | D31: 0.33 | E31: 0 | F31: 0.33 | G31: =+VLOOKUP(Tabla11034534544554564793637[[#This Row],[Ingrediente]],Tabla34[#All],3,0) -> 2800 | H31: =+Tabla11034534544554564793637[[#This Row],[Costo]]*Tabla11034534544554564793637[[#This Row],[Unidades]] -> 924 | J31: MARGEN DE ERROR DEL 5% | K31: =+K30*5% -> 355.61918 | M31: 2. Untar al pan la mantequilla y llevar al horno por un minuto.
B32: CARNE DE JAIBA CLAWN X KILO | C32: uds | D32: 1 | E32: 0 | F32: 1 | G32: =+VLOOKUP(Tabla11034534544554564793637[[#This Row],[Ingrediente]],Tabla34[#All],3,0) -> 57.12 | H32: =+Tabla11034534544554564793637[[#This Row],[Costo]]*Tabla11034534544554564793637[[#This Row],[Unidades]] -> 57.12 | J32: COSTO + MARGEN ERROR | K32: =+K30+K31 -> 7468.0028 | M32: 3. Verter la preparación del wok, a una cacerola y esparcir el perejil finamente picado, el queso mozarela y el queso parmesano ambos rayados.
B33: SUB. PASTA DE AJI AMARILLO | C33: g | D33: 30 | E33: 0 | F33: 30 | G33: =+VLOOKUP(Tabla11034534544554564793637[[#This Row],[Ingrediente]],Tabla34[#All],3,0) -> 27.651436 | H33: =+Tabla11034534544554564793637[[#This Row],[Costo]]*Tabla11034534544554564793637[[#This Row],[Unidades]] -> 829.54308 | J33: VALOR DE VENTA | K33: 41000 | M33: 4. Llevar la cacerola a gratinar en el horno por un periodo de 3 minutos.
B34: QUESO ALPINA PARMESANO RAYADO 2.5 L | C34: g | D34: 20 | E34: 0 | F34: 20 | G34: =+VLOOKUP(Tabla11034534544554564793637[[#This Row],[Ingrediente]],Tabla34[#All],3,0) -> 60.9875 | H34: =+Tabla11034534544554564793637[[#This Row],[Costo]]*Tabla11034534544554564793637[[#This Row],[Unidades]] -> 1219.75 | J34: IPOCONSUMO | K34: =+K33/1.08*0.08 -> 3037.037
B35: SUB. PASTA ROCOTO | C35: g | D35: 30 | E35: 0 | F35: 30 | G35: =+VLOOKUP(Tabla11034534544554564793637[[#This Row],[Ingrediente]],Tabla34[#All],3,0) -> 40.42512 | H35: =+Tabla11034534544554564793637[[#This Row],[Costo]]*Tabla11034534544554564793637[[#This Row],[Unidades]] -> 1212.7536 | J35: VALOR ANTES DE IPO | K35: =+K33-K34 -> 37962.963 | M35: Emplatado
B36: QUESO MOZZARELLA BLOQUE X 2,5K | C36: g | D36: 40 | E36: 0 | F36: 40 | G36: =+VLOOKUP(Tabla11034534544554564793637[[#This Row],[Ingrediente]],Tabla34[#All],3,0) -> 24.1152 | H36: =+Tabla11034534544554564793637[[#This Row],[Costo]]*Tabla11034534544554564793637[[#This Row],[Unidades]] -> 964.608 | J36: MARGEN. | K36: =+K32/K35 -> 0.19671812 | M36: 1. Ubicar la cacerola sobre un plato panda.
B37: MANTEQUILLA FRESCA BATIDA X KILO | C37: g | D37: 15 | E37: 0 | F37: 15 | G37: =+VLOOKUP(Tabla11034534544554564793637[[#This Row],[Ingrediente]],Tabla34[#All],3,0) -> 34.714286 | H37: =+Tabla11034534544554564793637[[#This Row],[Costo]]*Tabla11034534544554564793637[[#This Row],[Unidades]] -> 520.71429 | J37: GANANCIA | K37: =+K35-K32 -> 30494.96 | M37: 2. Ubicar los panes.
B38: COCO RALLADO NRO1 IPRODESA XK CD21 | C38: g | D38: 10 | E38: 0 | F38: 10 | G38: =+VLOOKUP(Tabla11034534544554564793637[[#This Row],[Ingrediente]],Tabla34[#All],3,0) -> 37.6305 | H38: =+Tabla11034534544554564793637[[#This Row],[Costo]]*Tabla11034534544554564793637[[#This Row],[Unidades]] -> 376.305 | J38: MARGEN PORCENTUAL | K38: =+K37/K32 -> 4.0834157 | M38: 3. Decorar con brotes.
B39: BROTES DE RABANO 50 | C39: g | D39: 1 | E39: 0 | F39: 1 | G39: =+VLOOKUP(Tabla11034534544554564793637[[#This Row],[Ingrediente]],Tabla34[#All],3,0) -> 307.5 | H39: =+Tabla11034534544554564793637[[#This Row],[Costo]]*Tabla11034534544554564793637[[#This Row],[Unidades]] -> 307.5
B40: SUB. LECHE DE COCO | C40: g | D40: 50 | E40: 0 | F40: 50 | G40: =+VLOOKUP(Tabla11034534544554564793637[[#This Row],[Ingrediente]],Tabla34[#All],3,0) -> 3.1357553 | H40: =+Tabla11034534544554564793637[[#This Row],[Costo]]*Tabla11034534544554564793637[[#This Row],[Unidades]] -> 156.78776
B41: SUB. PASTA DE PIMENTON | C41: g | D41: 15 | E41: 0 | F41: 15 | G41: =+VLOOKUP(Tabla11034534544554564793637[[#This Row],[Ingrediente]],Tabla34[#All],3,0) -> 14.714642 | H41: =+Tabla11034534544554564793637[[#This Row],[Costo]]*Tabla11034534544554564793637[[#This Row],[Unidades]] -> 220.71963
B42: ACEITE VEGETAL X 20LT | C42: g | D42: 5 | E42: 0 | F42: 5 | G42: =+VLOOKUP(Tabla11034534544554564793637[[#This Row],[Ingrediente]],Tabla34[#All],3,0) -> 7.68385 | H42: =+Tabla11034534544554564793637[[#This Row],[Costo]]*Tabla11034534544554564793637[[#This Row],[Unidades]] -> 38.41925
B43: PEREJIL CRESPO X KILO | C43: g | D43: 3 | E43: 40 | F43: 5 | G43: =+VLOOKUP(Tabla11034534544554564793637[[#This Row],[Ingrediente]],Tabla34[#All],3,0) -> 8 | H43: =+Tabla11034534544554564793637[[#This Row],[Costo]]*Tabla11034534544554564793637[[#This Row],[Unidades]] -> 40
B44: SAL REFISAL X 1000G | C44: g | D44: 3 | E44: 0 | F44: 3 | G44: =+VLOOKUP(Tabla11034534544554564793637[[#This Row],[Ingrediente]],Tabla34[#All],3,0) -> 2.401 | H44: =+Tabla11034534544554564793637[[#This Row],[Costo]]*Tabla11034534544554564793637[[#This Row],[Unidades]] -> 7.203
B45: SUB. FONDO DE PESCADO BISQUE | C45: g | D45: 100 | E45: 0 | F45: 100 | G45: =+VLOOKUP(Tabla11034534544554564793637[[#This Row],[Ingrediente]],Tabla34[#All],3,0) -> 2.3696 | H45: =+Tabla11034534544554564793637[[#This Row],[Costo]]*Tabla11034534544554564793637[[#This Row],[Unidades]] -> 236.96
H46: =SUBTOTAL(109,Tabla11034534544554564793637[Total costo]) -> 7112.3836
B49: GRATINADO DE SETAS | J49: ANALISIS RECETA | M49: Preparacion
B50: Ingrediente | C50: Und | D50: Unidades Netas | E50: % Merma | F50: Unidades | G50: Costo | H50: Total costo | J50: COSTO DEL PLATO | K50: =SUM(Tabla11034534544554564793638[Total costo]) -> 9230.1927 | M50: 1. Cortar en láminas las setas, es decir, el champiñón, la orellana y el portobello y reservar para el siguiente paso.
B51: CHAMPIÃ‘ON PORTOBELLO X KILO | C51: g | D51: 50.000001 | E51: 5 | F51: 52.63158 | G51: =+VLOOKUP(Tabla11034534544554564793638[[#This Row],[Ingrediente]],Tabla34[#All],3,0) -> 35 | H51: =+Tabla11034534544554564793638[[#This Row],[Costo]]*Tabla11034534544554564793638[[#This Row],[Unidades]] -> 1842.1053 | J51: MARGEN DE ERROR DEL 5% | K51: =+K50*5% -> 461.50964 | M51: 2. Llevar a un wok las setas ya laminadas (champiñón, orellana y portobello) y agregar la cebolla blanca picada en brunoise, crema de leche y la sal. Acentuar sabores y dejar espesar.
B52: CHAMPIÃ‘ON X KILO | C52: g | D52: 50.000001 | E52: 5 | F52: 52.63158 | G52: =+VLOOKUP(Tabla11034534544554564793638[[#This Row],[Ingrediente]],Tabla34[#All],3,0) -> 27 | H52: =+Tabla11034534544554564793638[[#This Row],[Costo]]*Tabla11034534544554564793638[[#This Row],[Unidades]] -> 1421.0527 | J52: COSTO + MARGEN ERROR | K52: =+K50+K51 -> 9691.7024 | M52: 3. Untar al pan la mantequilla y llevar al horno por un minuto.
B53: CHAMPIÃ‘ON ORELLANA X KILO | C53: g | D53: 50.000001 | E53: 5 | F53: 52.63158 | G53: =+VLOOKUP(Tabla11034534544554564793638[[#This Row],[Ingrediente]],Tabla34[#All],3,0) -> 28 | H53: =+Tabla11034534544554564793638[[#This Row],[Costo]]*Tabla11034534544554564793638[[#This Row],[Unidades]] -> 1473.6842 | J53: VALOR DE VENTA | K53: 39000 | M53: 4. Verter la preparación del wok, a una cacerola y esparcir el perejil finamente picado, el queso mozarela y el queso parmesano ambos rayados.
B54: QUESO ALPINA PARMESANO RAYADO 2.5 L | C54: g | D54: 20 | E54: 0 | F54: 20 | G54: =+VLOOKUP(Tabla11034534544554564793638[[#This Row],[Ingrediente]],Tabla34[#All],3,0) -> 60.9875 | H54: =+Tabla11034534544554564793638[[#This Row],[Costo]]*Tabla11034534544554564793638[[#This Row],[Unidades]] -> 1219.75 | J54: IPOCONSUMO | K54: =+K53/1.08*0.08 -> 2888.8889 | M54: 5. Llevar la cacerola a gratinar en el horno por un periodo de 3 minutos.
B55: COM PAN BAGUETTE CONGELADO X 400G PT MB | C55: uds | D55: 0.33 | E55: 0 | F55: 0.33 | G55: =+VLOOKUP(Tabla11034534544554564793638[[#This Row],[Ingrediente]],Tabla34[#All],3,0) -> 2800 | H55: =+Tabla11034534544554564793638[[#This Row],[Costo]]*Tabla11034534544554564793638[[#This Row],[Unidades]] -> 924 | J55: VALOR ANTES DE IPO | K55: =+K53-K54 -> 36111.111
B56: QUESO MOZZARELLA BLOQUE X 2,5K | C56: g | D56: 40 | E56: 0 | F56: 40 | G56: =+VLOOKUP(Tabla11034534544554564793638[[#This Row],[Ingrediente]],Tabla34[#All],3,0) -> 24.1152 | H56: =+Tabla11034534544554564793638[[#This Row],[Costo]]*Tabla11034534544554564793638[[#This Row],[Unidades]] -> 964.608 | J56: MARGEN. | K56: =+K52/K55 -> 0.2683856 | M56: Emplatado
B57: CREMA DE LECHE X 9700G | C57: g | D57: 30 | E57: 0 | F57: 30 | G57: =+VLOOKUP(Tabla11034534544554564793638[[#This Row],[Ingrediente]],Tabla34[#All],3,0) -> 19.804167 | H57: =+Tabla11034534544554564793638[[#This Row],[Costo]]*Tabla11034534544554564793638[[#This Row],[Unidades]] -> 594.125 | J57: GANANCIA | K57: =+K55-K52 -> 26419.409 | M57: 1. Ubicar la cacerola sobre un plato Pando
B58: MANTEQUILLA FRESCA BATIDA X KILO | C58: g | D58: 10 | E58: 0 | F58: 10 | G58: =+VLOOKUP(Tabla11034534544554564793638[[#This Row],[Ingrediente]],Tabla34[#All],3,0) -> 34.714286 | H58: =+Tabla11034534544554564793638[[#This Row],[Costo]]*Tabla11034534544554564793638[[#This Row],[Unidades]] -> 347.14286 | J58: MARGEN PORCENTUAL | K58: =+K57/K52 -> 2.7259823 | M58: 2. Ubicar los panes.
B59: BROTES DE RABANO 50 | C59: g | D59: 1 | E59: 0 | F59: 1 | G59: =+VLOOKUP(Tabla11034534544554564793638[[#This Row],[Ingrediente]],Tabla34[#All],3,0) -> 307.5 | H59: =+Tabla11034534544554564793638[[#This Row],[Costo]]*Tabla11034534544554564793638[[#This Row],[Unidades]] -> 307.5 | M59: 3. Decorar con brotes.
B60: CEBOLLA BLANCA LIMPIA X KILO | C60: g | D60: 15 | E60: 17 | F60: 18.072289 | G60: =+VLOOKUP(Tabla11034534544554564793638[[#This Row],[Ingrediente]],Tabla34[#All],3,0) -> 2.8 | H60: =+Tabla11034534544554564793638[[#This Row],[Costo]]*Tabla11034534544554564793638[[#This Row],[Unidades]] -> 50.602409
B61: ACEITE VEGETAL X 20LT | C61: g | D61: 5 | E61: 0 | F61: 5 | G61: =+VLOOKUP(Tabla11034534544554564793638[[#This Row],[Ingrediente]],Tabla34[#All],3,0) -> 7.68385 | H61: =+Tabla11034534544554564793638[[#This Row],[Costo]]*Tabla11034534544554564793638[[#This Row],[Unidades]] -> 38.41925
B62: PEREJIL CRESPO X KILO | C62: g | D62: 3 | E62: 40 | F62: 5 | G62: =+VLOOKUP(Tabla11034534544554564793638[[#This Row],[Ingrediente]],Tabla34[#All],3,0) -> 8 | H62: =+Tabla11034534544554564793638[[#This Row],[Costo]]*Tabla11034534544554564793638[[#This Row],[Unidades]] -> 40
B63: SAL REFISAL X 1000G | C63: g | D63: 3 | E63: 0 | F63: 3 | G63: =+VLOOKUP(Tabla11034534544554564793638[[#This Row],[Ingrediente]],Tabla34[#All],3,0) -> 2.401 | H63: =+Tabla11034534544554564793638[[#This Row],[Costo]]*Tabla11034534544554564793638[[#This Row],[Unidades]] -> 7.203
H64: =SUBTOTAL(109,Tabla11034534544554564793638[Total costo]) -> 9230.1927
B67: PICADA DE MAR | J67: ANALISIS RECETA | M67: Preparacion
B68: Ingrediente | C68: Und | D68: Unidades Netas | E68: % Merma | F68: Unidades | G68: Costo | H68: Total costo | J68: COSTO DEL PLATO | K68: =SUM(Tabla11034534544554564793639[Total costo]) -> 14121.395 | M68: 1. En un Bowl marinar todas las proteínas (Tilapia y Palmitos picados en Julianas; añadir los calamares y camarones) con soya, sal y pimienta. Realizar el proceso de apanado (Primero Harina de Trigo, luego huevo y finalizamos pasando por panco)
B69: CAMARON CRUDO 41-50 0% PORCIONX 7UND PAQUETE POR 10 PORCIONES | C69: uds | D69: 7 | E69: 0 | F69: 7 | G69: =+VLOOKUP(Tabla11034534544554564793639[[#This Row],[Ingrediente]],Tabla34[#All],3,0) -> 514.28 | H69: =+Tabla11034534544554564793639[[#This Row],[Costo]]*Tabla11034534544554564793639[[#This Row],[Unidades]] -> 3599.96 | J69: MARGEN DE ERROR DEL 5% | K69: =+K68*5% -> 706.06973 | M69: 2. Llevar a fritura profunda a 160 grados centígrados hasta que dore.
B70: SUERO ATOYABUEY BONGA DEL SINU 5000 | C70: g | D70: 30 | E70: 0 | F70: 30 | G70: =+VLOOKUP(Tabla11034534544554564793639[[#This Row],[Ingrediente]],Tabla34[#All],3,0) -> 24.7145 | H70: =+Tabla11034534544554564793639[[#This Row],[Costo]]*Tabla11034534544554564793639[[#This Row],[Unidades]] -> 741.435 | J70: COSTO + MARGEN ERROR | K70: =+K68+K69 -> 14827.464 | M70: 3. Cortar el limón en cascos. Reservar para el emplatado.
B71: FILETE DE TILAPIA FRESCA LO | C71: g | D71: 50.000001 | E71: 10 | F71: 55.555557 | G71: =+VLOOKUP(Tabla11034534544554564793639[[#This Row],[Ingrediente]],Tabla34[#All],3,0) -> 39 | H71: =+Tabla11034534544554564793639[[#This Row],[Costo]]*Tabla11034534544554564793639[[#This Row],[Unidades]] -> 2166.6667 | J71: VALOR DE VENTA | K71: 49000
B72: MIGA DE PAN PANKO BLANCO X 20 KILOS | C72: g | D72: 100 | E72: 0 | F72: 100 | G72: =+VLOOKUP(Tabla11034534544554564793639[[#This Row],[Ingrediente]],Tabla34[#All],3,0) -> 13.02 | H72: =+Tabla11034534544554564793639[[#This Row],[Costo]]*Tabla11034534544554564793639[[#This Row],[Unidades]] -> 1302 | J72: IPOCONSUMO | K72: =+K71/1.08*0.08 -> 3629.6296
B73: SUB. MELCOCHA | C73: g | D73: 40 | E73: 0 | F73: 40 | G73: =+VLOOKUP(Tabla11034534544554564793639[[#This Row],[Ingrediente]],Tabla34[#All],3,0) -> 18.115947 | H73: =+Tabla11034534544554564793639[[#This Row],[Costo]]*Tabla11034534544554564793639[[#This Row],[Unidades]] -> 724.63787 | J73: VALOR ANTES DE IPO | K73: =+K71-K72 -> 45370.37 | M73: Emplatado
B74: SUB. SALSA TARTARA | C74: g | D74: 40 | E74: 0 | F74: 40 | G74: =+VLOOKUP(Tabla11034534544554564793639[[#This Row],[Ingrediente]],Tabla34[#All],3,0) -> 22.061498 | H74: =+Tabla11034534544554564793639[[#This Row],[Costo]]*Tabla11034534544554564793639[[#This Row],[Unidades]] -> 882.45993 | J74: MARGEN. | K74: =+K70/K73 -> 0.32680942 | M74: 1. En un plato pando, realizar lagrimales con melcocha y suero. Entre las dos salsas 6 lagrimales.
B75: HUEVOS AAA | C75: uds | D75: 1 | E75: 0 | F75: 1 | G75: =+VLOOKUP(Tabla11034534544554564793639[[#This Row],[Ingrediente]],Tabla34[#All],3,0) -> 726.66667 | H75: =+Tabla11034534544554564793639[[#This Row],[Costo]]*Tabla11034534544554564793639[[#This Row],[Unidades]] -> 726.66667 | J75: GANANCIA | K75: =+K73-K70 -> 30542.906 | M75: 2. Sobre los lagrimales, ubicar las proteínas previamente preparadas en forma piramidal
B76: SUB. CEBOLLAS ENCURTIDAS | C76: g | D76: 30 | E76: 0 | F76: 30 | G76: =+VLOOKUP(Tabla11034534544554564793639[[#This Row],[Ingrediente]],Tabla34[#All],3,0) -> 6.3326452 | H76: =+Tabla11034534544554564793639[[#This Row],[Costo]]*Tabla11034534544554564793639[[#This Row],[Unidades]] -> 189.97935 | J76: MARGEN PORCENTUAL | K76: =+K75/K70 -> 2.0598873 | M76: 3. Coronamos con cebolla encurtida y chips de plátano.
B77: SUB. PALMITOS | C77: uds | D77: 1 | E77: 0 | F77: 1 | G77: =+VLOOKUP(Tabla11034534544554564793639[[#This Row],[Ingrediente]],Tabla34[#All],3,0) -> 612.85 | H77: =+Tabla11034534544554564793639[[#This Row],[Costo]]*Tabla11034534544554564793639[[#This Row],[Unidades]] -> 612.85 | M77: 4. Ubicar los cascos de Limón y la salsa tártara, en la salsera.
B78: LIMON TAHITI X KILO | C78: g | D78: 29.999999 | E78: 78 | F78: 136.36363 | G78: =+VLOOKUP(Tabla11034534544554564793639[[#This Row],[Ingrediente]],Tabla34[#All],3,0) -> 4.5 | H78: =+Tabla11034534544554564793639[[#This Row],[Costo]]*Tabla11034534544554564793639[[#This Row],[Unidades]] -> 613.63634 | M78: 5. Esparcir cilantro en plus en todo el plato.
B79: HARINA DE TRIGO HAZ DE OROS BOLSA X550g | C79: g | D79: 20 | E79: 0 | F79: 20 | G79: =+VLOOKUP(Tabla11034534544554564793639[[#This Row],[Ingrediente]],Tabla34[#All],3,0) -> 4.2672 | H79: =+Tabla11034534544554564793639[[#This Row],[Costo]]*Tabla11034534544554564793639[[#This Row],[Unidades]] -> 85.344
B80: PIMIENTA NEGRA MOLIDA BADIA 453GR | C80: g | D80: 1 | E80: 0 | F80: 1 | G80: =+VLOOKUP(Tabla11034534544554564793639[[#This Row],[Ingrediente]],Tabla34[#All],3,0) -> 57.218062 | H80: =+Tabla11034534544554564793639[[#This Row],[Costo]]*Tabla11034534544554564793639[[#This Row],[Unidades]] -> 57.218062
B81: CILANTRO LIMPIO X KILO | C81: g | D81: 3.9999999 | E81: 40 | F81: 6.6666665 | G81: =+VLOOKUP(Tabla11034534544554564793639[[#This Row],[Ingrediente]],Tabla34[#All],3,0) -> 12 | H81: =+Tabla11034534544554564793639[[#This Row],[Costo]]*Tabla11034534544554564793639[[#This Row],[Unidades]] -> 79.999998
B82: SUB. TUBOS DE CALAMAR X 80G | C82: uds | D82: 0.5 | E82: 0 | F82: 0.5 | G82: =+VLOOKUP(Tabla11034534544554564793639[[#This Row],[Ingrediente]],Tabla34[#All],3,0) -> 4196.75 | H82: =+Tabla11034534544554564793639[[#This Row],[Costo]]*Tabla11034534544554564793639[[#This Row],[Unidades]] -> 2098.375
B83: SAL REFISAL X 1000G | C83: g | D83: 2 | E83: 0 | F83: 2 | G83: =+VLOOKUP(Tabla11034534544554564793639[[#This Row],[Ingrediente]],Tabla34[#All],3,0) -> 2.401 | H83: =+Tabla11034534544554564793639[[#This Row],[Costo]]*Tabla11034534544554564793639[[#This Row],[Unidades]] -> 4.802
B84: SUB. CHIPS DE PLATANO | C84: g | D84: 15 | E84: 0 | F84: 15 | G84: =+VLOOKUP(Tabla11034534544554564793639[[#This Row],[Ingrediente]],Tabla34[#All],3,0) -> 15.690917 | H84: =+Tabla11034534544554564793639[[#This Row],[Costo]]*Tabla11034534544554564793639[[#This Row],[Unidades]] -> 235.36376
H85: =SUBTOTAL(109,Tabla11034534544554564793639[Total costo]) -> 14121.395
B88: PATACONES MAREA | M88: Preparacion
B89: Ingrediente | C89: Und | D89: Unidades Netas | E89: % Merma | F89: Unidades | G89: Costo | H89: Total costo | M89: 1. Llevar a fritura profunda los patacones (160 Grados)
B90: CAMARON CRUDO 41-50 0% PORCIONX 7UND PAQUETE POR 10 PORCIONES | C90: uds | D90: 8 | E90: 0 | F90: 8 | G90: =+VLOOKUP(Tabla11034534544554564793640[[#This Row],[Ingrediente]],Tabla34[#All],3,0) -> 514.28 | H90: =+Tabla11034534544554564793640[[#This Row],[Costo]]*Tabla11034534544554564793640[[#This Row],[Unidades]] -> 4114.24 | J90: ANALISIS RECETA | M90: 2. En un Bowl agregar los camarones, cilantro, mango, aguacate y vinagreta, mezclar
B91: SUERO ATOYABUEY BONGA DEL SINU 5000 | C91: g | D91: 15 | E91: 0 | F91: 15 | G91: =+VLOOKUP(Tabla11034534544554564793640[[#This Row],[Ingrediente]],Tabla34[#All],3,0) -> 24.7145 | H91: =+Tabla11034534544554564793640[[#This Row],[Costo]]*Tabla11034534544554564793640[[#This Row],[Unidades]] -> 370.7175 | J91: COSTO DEL PLATO | K91: =SUM(Tabla11034534544554564793640[Total costo]) -> 7522.9824
B92: PATACONES MEDIANOS VERDE X UND | C92: uds | D92: 2 | E92: 0 | F92: 2 | G92: =+VLOOKUP(Tabla11034534544554564793640[[#This Row],[Ingrediente]],Tabla34[#All],3,0) -> 500 | H92: =+Tabla11034534544554564793640[[#This Row],[Costo]]*Tabla11034534544554564793640[[#This Row],[Unidades]] -> 1000 | J92: MARGEN DE ERROR DEL 5% | K92: =+K91*5% -> 376.14912 | M92: Emplatado
B93: LIMON TAHITI X KILO | C93: g | D93: 59.999997 | E93: 78 | F93: 272.72726 | G93: =+VLOOKUP(Tabla11034534544554564793640[[#This Row],[Ingrediente]],Tabla34[#All],3,0) -> 4.5 | H93: =+Tabla11034534544554564793640[[#This Row],[Costo]]*Tabla11034534544554564793640[[#This Row],[Unidades]] -> 1227.2727 | J93: COSTO + MARGEN ERROR | K93: =+K91+K92 -> 7899.1315 | M93: 1. Realizar 4 lagrimales con suero costeño y entre estos ubicar los patacones
B94: SUB. VINAGRETA DE MANGO | C94: g | D94: 40 | E94: 0 | F94: 40 | G94: =+VLOOKUP(Tabla11034534544554564793640[[#This Row],[Ingrediente]],Tabla34[#All],3,0) -> 7.925333 | H94: =+Tabla11034534544554564793640[[#This Row],[Costo]]*Tabla11034534544554564793640[[#This Row],[Unidades]] -> 317.01332 | J94: VALOR DE VENTA | K94: 35000 | M94: 2. Sobre cada patacón agregar la mezcla del Bowl y esparcir paprika.
B95: AGUACATE CHOCKETTE X KILO | C95: g | D95: 20 | E95: 25 | F95: 26.666666 | G95: =+VLOOKUP(Tabla11034534544554564793640[[#This Row],[Ingrediente]],Tabla34[#All],3,0) -> 8.5 | H95: =+Tabla11034534544554564793640[[#This Row],[Costo]]*Tabla11034534544554564793640[[#This Row],[Unidades]] -> 226.66666 | J95: IPOCONSUMO | K95: =+K94/1.08*0.08 -> 2592.5926 | M95: 3. Decorar con brotes
B96: AJI DULCE X KILO | C96: g | D96: 9.9999999 | E96: 33 | F96: 14.925373 | G96: =+VLOOKUP(Tabla11034534544554564793640[[#This Row],[Ingrediente]],Tabla34[#All],3,0) -> 9.8 | H96: =+Tabla11034534544554564793640[[#This Row],[Costo]]*Tabla11034534544554564793640[[#This Row],[Unidades]] -> 146.26866 | J96: VALOR ANTES DE IPO | K96: =+K94-K95 -> 32407.407
B97: MANGO TOMMY X KILO | C97: g | D97: 20 | E97: 30 | F97: 28.571428 | G97: =+VLOOKUP(Tabla11034534544554564793640[[#This Row],[Ingrediente]],Tabla34[#All],3,0) -> 2.5 | H97: =+Tabla11034534544554564793640[[#This Row],[Costo]]*Tabla11034534544554564793640[[#This Row],[Unidades]] -> 71.42857 | J97: MARGEN. | K97: =+K93/K96 -> 0.24374463
B98: CEBOLLA MORADA LIMPIA | C98: g | D98: 5 | E98: 20 | F98: 6.25 | G98: =+VLOOKUP(Tabla11034534544554564793640[[#This Row],[Ingrediente]],Tabla34[#All],3,0) -> 4.7 | H98: =+Tabla11034534544554564793640[[#This Row],[Costo]]*Tabla11034534544554564793640[[#This Row],[Unidades]] -> 29.375 | J98: GANANCIA | K98: =+K96-K93 -> 24508.276
B99: CILANTRO LIMPIO X KILO | C99: g | D99: 0.99999996 | E99: 40 | F99: 1.6666666 | G99: =+VLOOKUP(Tabla11034534544554564793640[[#This Row],[Ingrediente]],Tabla34[#All],3,0) -> 12 | H99: =+Tabla11034534544554564793640[[#This Row],[Costo]]*Tabla11034534544554564793640[[#This Row],[Unidades]] -> 19.999999 | J99: MARGEN PORCENTUAL | K99: =+K98/K93 -> 3.1026545
H100: =SUBTOTAL(109,Tabla11034534544554564793640[Total costo]) -> 7522.9824
B103: CROQUETAS CREMOSA DE JAIBA | J103: ANALISIS RECETA | M103: Preparacion
B104: Ingrediente | C104: Und | D104: Unidades Netas | E104: % Merma | F104: Unidades | G104: Costo | H104: Total costo | J104: COSTO DEL PLATO | K104: =SUM(Tabla11034534544554564793643[Total costo]) -> 4354.4651 | M104: 1. Cortar el pescado en láminas de 2 Milímetros y agregar sobre todo el plato
B105: BROTES DE RABANO 50 | C105: g | D105: 3 | E105: 0 | F105: 3 | G105: =+VLOOKUP(Tabla11034534544554564793643[[#This Row],[Ingrediente]],Tabla34[#All],3,0) -> 307.5 | H105: =+Tabla11034534544554564793643[[#This Row],[Costo]]*Tabla11034534544554564793643[[#This Row],[Unidades]] -> 922.5 | J105: MARGEN DE ERROR DEL 5% | K105: =+K104*5% -> 217.72326 | M105: 2. En un bowl agregar Ajino moto, Limón y mayonesa de la casa, incorporamos y bañamos el pescado con esta salsa, despelucar tomates y montar aire
B106: MEZCLUM X 500G | C106: g | D106: 3 | E106: 0 | F106: 3 | G106: =+VLOOKUP(Tabla11034534544554564793643[[#This Row],[Ingrediente]],Tabla34[#All],3,0) -> 12 | H106: =+Tabla11034534544554564793643[[#This Row],[Costo]]*Tabla11034534544554564793643[[#This Row],[Unidades]] -> 36 | J106: COSTO + MARGEN ERROR | K106: =+K104+K105 -> 4572.1884 | M106: 3. Freír la tocineta y triturar
B107: FLORES COMESTIBLES (PENSAMIENTOS) | C107: g | D107: 1 | E107: 0 | F107: 1 | G107: =+VLOOKUP(Tabla11034534544554564793643[[#This Row],[Ingrediente]],Tabla34[#All],3,0) -> 511 | H107: =+Tabla11034534544554564793643[[#This Row],[Costo]]*Tabla11034534544554564793643[[#This Row],[Unidades]] -> 511 | J107: VALOR DE VENTA | K107: 35000
B108: SUB. MAYONESA DE MARACUYA | C108: g | D108: 20 | E108: 0 | F108: 20 | G108: =+VLOOKUP(Tabla11034534544554564793643[[#This Row],[Ingrediente]],Tabla34[#All],3,0) -> 30.254664 | H108: =+Tabla11034534544554564793643[[#This Row],[Costo]]*Tabla11034534544554564793643[[#This Row],[Unidades]] -> 605.09329 | J108: IPOCONSUMO | K108: =+K107/1.08*0.08 -> 2592.5926 | M108: Emplatado
B109: SUB. CROQUETAS DE JAIBA | C109: uds | D109: 5 | E109: 0 | F109: 5 | G109: =+VLOOKUP(Tabla11034534544554564793643[[#This Row],[Ingrediente]],Tabla34[#All],3,0) -> 455.97436 | H109: =+Tabla11034534544554564793643[[#This Row],[Costo]]*Tabla11034534544554564793643[[#This Row],[Unidades]] -> 2279.8718 | J109: VALOR ANTES DE IPO | K109: =+K107-K108 -> 32407.407 | M109: 1. Esparcir Parmesano y tocineta, ubicar el aire en tres partes del plato
H110: =SUBTOTAL(109,Tabla11034534544554564793643[Total costo]) -> 4354.4651 | J110: MARGEN. | K110: =+K106/K109 -> 0.14108467 | M110: 2. Decorar con brotes y flores comestibles
J111: GANANCIA | K111: =+K109-K106 -> 27835.219
J112: MARGEN PORCENTUAL | K112: =+K111/K106 -> 6.0879423
B115: TACO DE PESCADO | J115: ANALISIS RECETA | M115: Preparacion
B116: Ingrediente | C116: Und | D116: Unidades Netas | E116: % Merma | F116: Unidades | G116: Costo | H116: Total costo | J116: COSTO DEL PLATO | K116: =SUM(Tabla11034534544554564793644[Total costo]) -> 3257.7793 | M116: 1. Llevar a fritura profunda las croquetas de jaiba previamente apanadas ( 160 grados centígrados)
B117: FILETE DE TILAPIA FRESCA LO | C117: g | D117: 29.999999 | E117: 10 | F117: 33.333332 | G117: =+VLOOKUP(Tabla11034534544554564793644[[#This Row],[Ingrediente]],Tabla34[#All],3,0) -> 39 | H117: =+Tabla11034534544554564793644[[#This Row],[Costo]]*Tabla11034534544554564793644[[#This Row],[Unidades]] -> 1299.9999 | J117: MARGEN DE ERROR DEL 5% | K117: =+K116*5% -> 162.88896 | M117: 2. Verter la parrillera en una salsera.
B118: TORTILLA DE MAIZ X 20UND | C118: uds | D118: 1 | E118: 0 | F118: 1 | G118: =+VLOOKUP(Tabla11034534544554564793644[[#This Row],[Ingrediente]],Tabla34[#All],3,0) -> 750 | H118: =+Tabla11034534544554564793644[[#This Row],[Costo]]*Tabla11034534544554564793644[[#This Row],[Unidades]] -> 750 | J118: COSTO + MARGEN ERROR | K118: =+K116+K117 -> 3420.6682
...

Sheet CEVICHES
B6: COCTEL CARTAGENERO | J6: ANALISIS RECETA | M6: Preparacion
B7: Ingrediente | C7: Und | D7: Cant. | E7: Columna1 | F7: Columna2 | G7: Costo | H7: Total costo | J7: COSTO DEL PLATO | K7: =SUM(Tabla110345345445545647945[Total costo]) -> 13633.205 | M7: 1. Blanquear los camarones, fritas y patacones.
B8: AJINOMOTO X KILO | C8: g | D8: 1 | E8: 0 | F8: 1 | G8: =+VLOOKUP(Tabla110345345445545647945[[#This Row],[Ingrediente]],Tabla34[#All],3,0) -> 13.401291 | H8: =+Tabla110345345445545647945[[#This Row],[Costo]]*Tabla110345345445545647945[[#This Row],[Columna2]] -> 13.401291 | J8: MARGEN DE ERROR DEL 10% | K8: =+K7*5% -> 681.66023 | M8: 2. En un bowl incorporar la cebolla, cilantro en plus, camarones blanqueados, sriracha, salsa de tomate, limón, sal y mayonesa.
B9: AJO LIMPIO X KILO | C9: g | D9: 1 | E9: 13 | F9: 1.149 | G9: =+VLOOKUP(Tabla110345345445545647945[[#This Row],[Ingrediente]],Tabla34[#All],3,0) -> 19 | H9: =+Tabla110345345445545647945[[#This Row],[Costo]]*Tabla110345345445545647945[[#This Row],[Columna2]] -> 21.831 | J9: COSTO + MARGEN ERROR | K9: =+K7+K8 -> 14314.865 | M9: Cortar la piña en cubos.
B10: CAMARON CRUDO 41-50 0% PORCIONX 7UND PAQUETE POR 10 PORCIONES | C10: uds | D10: 16 | E10: 0 | F10: 16 | G10: =+VLOOKUP(Tabla110345345445545647945[[#This Row],[Ingrediente]],Tabla34[#All],3,0) -> 514.28 | H10: =+Tabla110345345445545647945[[#This Row],[Costo]]*Tabla110345345445545647945[[#This Row],[Columna2]] -> 8228.48 | J10: VALOR DE VENTA | K10: 48000
B11: CEBOLLA BLANCA LIMPIA X KILO | C11: g | D11: 15 | E11: 10 | F11: 16.667 | G11: =+VLOOKUP(Tabla110345345445545647945[[#This Row],[Ingrediente]],Tabla34[#All],3,0) -> 2.8 | H11: =+Tabla110345345445545647945[[#This Row],[Costo]]*Tabla110345345445545647945[[#This Row],[Columna2]] -> 46.6676 | J11: IPOCONSUMO | K11: =+K10/1.08*0.08 -> 3555.5556 | M11: Emplatado
B12: CEBOLLA MORADA LIMPIA | C12: g | D12: 15 | E12: 10 | F12: 16.667 | G12: =+VLOOKUP(Tabla110345345445545647945[[#This Row],[Ingrediente]],Tabla34[#All],3,0) -> 4.7 | H12: =+Tabla110345345445545647945[[#This Row],[Costo]]*Tabla110345345445545647945[[#This Row],[Columna2]] -> 78.3349 | J12: VALOR ANTES DE IPO | K12: =+K10-K11 -> 44444.444 | M12: 1. En una copa poner parte de la piña picada, en un palillo hacer un pincho con el resto de la piña.
B13: CILANTRO LIMPIO X KILO | C13: g | D13: 3 | E13: 40 | F13: 5 | G13: =+VLOOKUP(Tabla110345345445545647945[[#This Row],[Ingrediente]],Tabla34[#All],3,0) -> 12 | H13: =+Tabla110345345445545647945[[#This Row],[Costo]]*Tabla110345345445545647945[[#This Row],[Columna2]] -> 60 | J13: MARGEN. | K13: =+K9/K12 -> 0.32208446 | M13: 2. En la copa verter la mezcla obtenida en el bowl
B14: LECITINA DE SOYA X500G | C14: g | D14: 0.5 | E14: 0 | F14: 0.5 | G14: =+VLOOKUP(Tabla110345345445545647945[[#This Row],[Ingrediente]],Tabla34[#All],3,0) -> 148 | H14: =+Tabla110345345445545647945[[#This Row],[Costo]]*Tabla110345345445545647945[[#This Row],[Columna2]] -> 74 | J14: GANANCIA | K14: =+K12-K9 -> 30129.58 | M14: 3. Clavar el pincho de piña, decorar con mézclum, y masago.
B15: LIMON TAHITI X KILO | C15: g | D15: 3 | E15: 78 | F15: 13.636 | G15: =+VLOOKUP(Tabla110345345445545647945[[#This Row],[Ingrediente]],Tabla34[#All],3,0) -> 4.5 | H15: =+Tabla110345345445545647945[[#This Row],[Costo]]*Tabla110345345445545647945[[#This Row],[Columna2]] -> 61.362 | J15: MARGEN PORCENTUAL | K15: =+K14/K9 -> 2.1047757
B16: MAYONESA FRUCO GALON X3770G | C16: g | D16: 60 | E16: 0 | F16: 60 | G16: =+VLOOKUP(Tabla110345345445545647945[[#This Row],[Ingrediente]],Tabla34[#All],3,0) -> 26.272577 | H16: =+Tabla110345345445545647945[[#This Row],[Costo]]*Tabla110345345445545647945[[#This Row],[Columna2]] -> 1576.3546
B17: MEZCLUM X 500G | C17: g | D17: 3 | E17: 0 | F17: 3 | G17: =+VLOOKUP(Tabla110345345445545647945[[#This Row],[Ingrediente]],Tabla34[#All],3,0) -> 12 | H17: =+Tabla110345345445545647945[[#This Row],[Costo]]*Tabla110345345445545647945[[#This Row],[Columna2]] -> 36
B18: SAL REFISAL X 1000G | C18: g | D18: 1 | E18: 0 | F18: 1 | G18: =+VLOOKUP(Tabla110345345445545647945[[#This Row],[Ingrediente]],Tabla34[#All],3,0) -> 2.401 | H18: =+Tabla110345345445545647945[[#This Row],[Costo]]*Tabla110345345445545647945[[#This Row],[Columna2]] -> 2.401
B19: SALSA DE TOMATE FRUCO GX 4350G | C19: g | D19: 140 | E19: 0 | F19: 140 | G19: =+VLOOKUP(Tabla110345345445545647945[[#This Row],[Ingrediente]],Tabla34[#All],3,0) -> 18.828046 | H19: =+Tabla110345345445545647945[[#This Row],[Costo]]*Tabla110345345445545647945[[#This Row],[Columna2]] -> 2635.9264
B20: SRIRACHA HOT CHILLI SAUCE x 482ML | C20: g | D20: 3 | E20: 0 | F20: 3 | G20: =+VLOOKUP(Tabla110345345445545647945[[#This Row],[Ingrediente]],Tabla34[#All],3,0) -> 39.31131 | H20: =+Tabla110345345445545647945[[#This Row],[Costo]]*Tabla110345345445545647945[[#This Row],[Columna2]] -> 117.93393
B21: SUB. BASE LECHE DE TIGRE MALANGA | C21: g | D21: 20 | E21: 0 | F21: 20 | G21: =+VLOOKUP(Tabla110345345445545647945[[#This Row],[Ingrediente]],Tabla34[#All],3,0) -> 8.624517 | H21: =+Tabla110345345445545647945[[#This Row],[Costo]]*Tabla110345345445545647945[[#This Row],[Columna2]] -> 172.49034
B22: SUB. CHIPS DE PLATANO | C22: g | D22: 15 | E22: 0 | F22: 15 | G22: =+VLOOKUP(Tabla110345345445545647945[[#This Row],[Ingrediente]],Tabla34[#All],3,0) -> 15.690917 | H22: =+Tabla110345345445545647945[[#This Row],[Costo]]*Tabla110345345445545647945[[#This Row],[Columna2]] -> 235.36376
B23: SUB. PASTA DE CILANTRO | C23: g | D23: 5 | E23: 0 | F23: 5 | G23: =+VLOOKUP(Tabla110345345445545647945[[#This Row],[Ingrediente]],Tabla34[#All],3,0) -> 10.280677 | H23: =+Tabla110345345445545647945[[#This Row],[Costo]]*Tabla110345345445545647945[[#This Row],[Columna2]] -> 51.403385
B24: SUB. RON DE COCO | C24: g | D24: 5 | E24: 0 | F24: 5 | G24: =+VLOOKUP(Tabla110345345445545647945[[#This Row],[Ingrediente]],Tabla34[#All],3,0) -> 44.250857 | H24: =+Tabla110345345445545647945[[#This Row],[Costo]]*Tabla110345345445545647945[[#This Row],[Columna2]] -> 221.25429
H25: =SUBTOTAL(109,Tabla110345345445545647945[Total costo]) -> 13633.205
B27: CEVICHE DE CHICHARRON | J27: ANALISIS RECETA | M27: Preparacion
B28: Ingrediente | C28: Und | D28: Cant. | E28: Columna1 | F28: Columna2 | G28: Costo | H28: Total costo | J28: COSTO DEL PLATO | K28: =SUM(Tabla11034534544554564793646[Total costo]) -> 13508.45 | M28: 1. Fritar el tocino
B29: CILANTRO LIMPIO X KILO | C29: g | D29: 3 | E29: 40 | F29: 5 | G29: =+VLOOKUP(Tabla11034534544554564793646[[#This Row],[Ingrediente]],Tabla34[#All],3,0) -> 12 | H29: =+Tabla11034534544554564793646[[#This Row],[Costo]]*Tabla11034534544554564793646[[#This Row],[Columna2]] -> 60 | J29: MARGEN DE ERROR DEL 10% | K29: =+K28*5% -> 675.42252 | M29: 2. Despelucar los tomates
B30: MEZCLUM X 500G | C30: g | D30: 4 | E30: 0 | F30: 4 | G30: =+VLOOKUP(Tabla11034534544554564793646[[#This Row],[Ingrediente]],Tabla34[#All],3,0) -> 12 | H30: =+Tabla11034534544554564793646[[#This Row],[Costo]]*Tabla11034534544554564793646[[#This Row],[Columna2]] -> 48 | J30: COSTO + MARGEN ERROR | K30: =+K28+K29 -> 14183.873 | M30: 3. En un bol mezclamos cebolla, cilantro en plus, acevichada y el tocino ya previamente frito.
B31: SUB. ACEVICHADA | C31: g | D31: 100 | E31: 0 | F31: 100 | G31: =+VLOOKUP(Tabla11034534544554564793646[[#This Row],[Ingrediente]],Tabla34[#All],3,0) -> 26.416185 | H31: =+Tabla11034534544554564793646[[#This Row],[Costo]]*Tabla11034534544554564793646[[#This Row],[Columna2]] -> 2641.6185 | J31: VALOR DE VENTA | K31: 46000
B32: SUB. CHICHARRON | C32: uds | D32: 1 | E32: 0 | F32: 1 | G32: =+VLOOKUP(Tabla11034534544554564793646[[#This Row],[Ingrediente]],Tabla34[#All],3,0) -> 9017.9941 | H32: =+Tabla11034534544554564793646[[#This Row],[Costo]]*Tabla11034534544554564793646[[#This Row],[Columna2]] -> 9017.9941 | J32: IPOCONSUMO | K32: =+K31/1.08*0.08 -> 3407.4074 | M32: Emplatado
B33: SUB. CHIPS DE PLATANO | C33: g | D33: 15 | E33: 0 | F33: 15 | G33: =+VLOOKUP(Tabla11034534544554564793646[[#This Row],[Ingrediente]],Tabla34[#All],3,0) -> 15.690917 | H33: =+Tabla11034534544554564793646[[#This Row],[Costo]]*Tabla11034534544554564793646[[#This Row],[Columna2]] -> 235.36376 | J33: VALOR ANTES DE IPO | K33: =+K31-K32 -> 42592.593 | M33: 1. En una copa verter la mezcla obtenida en el bowl
B34: SUERO ATOYABUEY BONGA DEL SINU 5000 | C34: g | D34: 30 | E34: 0 | F34: 30 | G34: =+VLOOKUP(Tabla11034534544554564793646[[#This Row],[Ingrediente]],Tabla34[#All],3,0) -> 24.7145 | H34: =+Tabla11034534544554564793646[[#This Row],[Costo]]*Tabla11034534544554564793646[[#This Row],[Columna2]] -> 741.435 | J34: MARGEN. | K34: =+K30/K33 -> 0.33301267 | M34: 2. Decorar con tomates despelucados, mézclum y chips de plátano
B35: TOMATE CHERRY X KILO | C35: g | D35: 30 | E35: 5 | F35: 31.579 | G35: =+VLOOKUP(Tabla11034534544554564793646[[#This Row],[Ingrediente]],Tabla34[#All],3,0) -> 11 | H35: =+Tabla11034534544554564793646[[#This Row],[Costo]]*Tabla11034534544554564793646[[#This Row],[Columna2]] -> 347.369 | J35: GANANCIA | K35: =+K33-K30 -> 28408.72
B36: CEBOLLA BLANCA LIMPIA X KILO | C36: g | D36: 50 | E36: 10 | F36: 55.556 | G36: =+VLOOKUP(Tabla11034534544554564793646[[#This Row],[Ingrediente]],Tabla34[#All],3,0) -> 2.8 | H36: =+Tabla11034534544554564793646[[#This Row],[Costo]]*Tabla11034534544554564793646[[#This Row],[Columna2]] -> 155.5568 | J36: MARGEN PORCENTUAL | K36: =+K35/K30 -> 2.0028888
B37: CEBOLLA MORADA LIMPIA | C37: g | D37: 50 | E37: 10 | F37: 55.556 | G37: =+VLOOKUP(Tabla11034534544554564793646[[#This Row],[Ingrediente]],Tabla34[#All],3,0) -> 4.7 | H37: =+Tabla11034534544554564793646[[#This Row],[Costo]]*Tabla11034534544554564793646[[#This Row],[Columna2]] -> 261.1132
H38: =SUBTOTAL(109,Tabla11034534544554564793646[Total costo]) -> 13508.45
B41: CEVICHE MIRAFLORES | J41: ANALISIS RECETA | M41: Preparacion
B42: Ingrediente | C42: Und | D42: Cant. | E42: Columna1 | F42: Columna2 | G42: Costo | H42: Total costo | J42: COSTO DEL PLATO | K42: =SUM(Tabla1103453454455456479363747[Total costo]) -> 15171.746
B43: AGUACATE CHOCKETTE X KILO | C43: g | D43: 40 | E43: 25 | F43: 53.333 | G43: =+VLOOKUP(Tabla1103453454455456479363747[[#This Row],[Ingrediente]],Tabla34[#All],3,0) -> 8.5 | H43: =+Tabla1103453454455456479363747[[#This Row],[Costo]]*Tabla1103453454455456479363747[[#This Row],[Columna2]] -> 453.3305 | J43: MARGEN DE ERROR DEL 10% | K43: =+K42*10% -> 1517.1746
B44: SUB. TUBOS DE CALAMAR X 80G | C44: uds | D44: 1 | E44: 0 | F44: 1 | G44: =+VLOOKUP(Tabla1103453454455456479363747[[#This Row],[Ingrediente]],Tabla34[#All],3,0) -> 4196.75 | H44: =+Tabla1103453454455456479363747[[#This Row],[Costo]]*Tabla1103453454455456479363747[[#This Row],[Columna2]] -> 4196.75 | J44: COSTO + MARGEN ERROR | K44: =+K42+K43 -> 16688.921
B45: CILANTRO LIMPIO X KILO | C45: g | D45: 3 | E45: 40 | F45: 5 | G45: =+VLOOKUP(Tabla1103453454455456479363747[[#This Row],[Ingrediente]],Tabla34[#All],3,0) -> 12 | H45: =+Tabla1103453454455456479363747[[#This Row],[Costo]]*Tabla1103453454455456479363747[[#This Row],[Columna2]] -> 60 | J45: VALOR DE VENTA | K45: 48000
B46: FILETE DE TILAPIA FRESCA LO | C46: g | D46: 120 | E46: 10 | F46: 133.333 | G46: =+VLOOKUP(Tabla1103453454455456479363747[[#This Row],[Ingrediente]],Tabla34[#All],3,0) -> 39 | H46: =+Tabla1103453454455456479363747[[#This Row],[Costo]]*Tabla1103453454455456479363747[[#This Row],[Columna2]] -> 5199.987 | J46: IPOCONSUMO | K46: =+K45/1.08*0.08 -> 3555.5556 | M46: Emplatado
B47: LIMON TAHITI X KILO | C47: g | D47: 50 | E47: 78 | F47: 227.273 | G47: =+VLOOKUP(Tabla1103453454455456479363747[[#This Row],[Ingrediente]],Tabla34[#All],3,0) -> 4.5 | H47: =+Tabla1103453454455456479363747[[#This Row],[Costo]]*Tabla1103453454455456479363747[[#This Row],[Columna2]] -> 1022.7285 | J47: VALOR ANTES DE IPO | K47: =+K45-K46 -> 44444.444
B48: MEZCLUM X 500G | C48: g | D48: 5 | E48: 0 | F48: 5 | G48: =+VLOOKUP(Tabla1103453454455456479363747[[#This Row],[Ingrediente]],Tabla34[#All],3,0) -> 12 | H48: =+Tabla1103453454455456479363747[[#This Row],[Costo]]*Tabla1103453454455456479363747[[#This Row],[Columna2]] -> 60 | J48: MARGEN. | K48: =+K44/K47 -> 0.37550072
B49: NITRÃ“GENO LÃQUIDO | C49: g | D49: 30 | E49: 0 | F49: 30 | G49: =+VLOOKUP(Tabla1103453454455456479363747[[#This Row],[Ingrediente]],Tabla34[#All],3,0) -> 8.9 | H49: =+Tabla1103453454455456479363747[[#This Row],[Costo]]*Tabla1103453454455456479363747[[#This Row],[Columna2]] -> 267 | J49: GANANCIA | K49: =+K47-K44 -> 27755.524
B50: PAPA CRIOLLA BALIN O CHIRIYA | C50: g | D50: 120 | E50: 5 | F50: 126.316 | G50: =+VLOOKUP(Tabla1103453454455456479363747[[#This Row],[Ingrediente]],Tabla34[#All],3,0) -> 4.5 | H50: =+Tabla1103453454455456479363747[[#This Row],[Costo]]*Tabla1103453454455456479363747[[#This Row],[Columna2]] -> 568.422 | J50: MARGEN PORCENTUAL | K50: =+K49/K44 -> 1.6631108
B51: PIMIENTA NEGRA MOLIDA BADIA 453GR | C51: g | D51: 1 | E51: 0 | F51: 1 | G51: =+VLOOKUP(Tabla1103453454455456479363747[[#This Row],[Ingrediente]],Tabla34[#All],3,0) -> 57.218062 | H51: =+Tabla1103453454455456479363747[[#This Row],[Costo]]*Tabla1103453454455456479363747[[#This Row],[Columna2]] -> 57.218062
B52: SAL REFISAL X 1000G | C52: g | D52: 3 | E52: 0 | F52: 3 | G52: =+VLOOKUP(Tabla1103453454455456479363747[[#This Row],[Ingrediente]],Tabla34[#All],3,0) -> 2.401 | H52: =+Tabla1103453454455456479363747[[#This Row],[Costo]]*Tabla1103453454455456479363747[[#This Row],[Columna2]] -> 7.203
B53: SUB. BASE LECHE DE TIGRE MALANGA | C53: g | D53: 50 | E53: 0 | F53: 50 | G53: =+VLOOKUP(Tabla1103453454455456479363747[[#This Row],[Ingrediente]],Tabla34[#All],3,0) -> 8.624517 | H53: =+Tabla1103453454455456479363747[[#This Row],[Costo]]*Tabla1103453454455456479363747[[#This Row],[Columna2]] -> 431.22585
B54: SUB. PASTA DE AJI AMARILLO | C54: g | D54: 60 | E54: 0 | F54: 60 | G54: =+VLOOKUP(Tabla1103453454455456479363747[[#This Row],[Ingrediente]],Tabla34[#All],3,0) -> 27.651436 | H54: =+Tabla1103453454455456479363747[[#This Row],[Costo]]*Tabla1103453454455456479363747[[#This Row],[Columna2]] -> 1659.0862
B55: SUERO ATOYABUEY BONGA DEL SINU 5000 | C55: g | D55: 30 | E55: 0 | F55: 30 | G55: =+VLOOKUP(Tabla1103453454455456479363747[[#This Row],[Ingrediente]],Tabla34[#All],3,0) -> 24.7145 | H55: =+Tabla1103453454455456479363747[[#This Row],[Costo]]*Tabla1103453454455456479363747[[#This Row],[Columna2]] -> 741.435
B56: TOMATE PERLA X KILO | C56: g | D56: 5 | E56: 5 | F56: 5.263 | G56: =+VLOOKUP(Tabla1103453454455456479363747[[#This Row],[Ingrediente]],Tabla34[#All],3,0) -> 37.5 | H56: =+Tabla1103453454455456479363747[[#This Row],[Costo]]*Tabla1103453454455456479363747[[#This Row],[Columna2]] -> 197.3625
B57: CEBOLLA BLANCA LIMPIA X KILO | C57: g | D57: 30 | E57: 10 | F57: 33.333 | G57: =+VLOOKUP(Tabla1103453454455456479363747[[#This Row],[Ingrediente]],Tabla34[#All],3,0) -> 2.8 | H57: =+Tabla1103453454455456479363747[[#This Row],[Costo]]*Tabla1103453454455456479363747[[#This Row],[Columna2]] -> 93.3324
B58: CEBOLLA MORADA LIMPIA | C58: g | D58: 30 | E58: 10 | F58: 33.333 | G58: =+VLOOKUP(Tabla1103453454455456479363747[[#This Row],[Ingrediente]],Tabla34[#All],3,0) -> 4.7 | H58: =+Tabla1103453454455456479363747[[#This Row],[Costo]]*Tabla1103453454455456479363747[[#This Row],[Columna2]] -> 156.6651
H59: =SUBTOTAL(109,Tabla1103453454455456479363747[Total costo]) -> 15171.746
B61: CEVICHE TRUFADO | J61: ANALISIS RECETA | M61: Preparacion
B62: Ingrediente | C62: Und | D62: Cant. | E62: Columna1 | F62: Columna2 | G62: Costo | H62: Total costo | J62: COSTO DEL PLATO | K62: =SUM(Tabla1103453454455456479363848[Total costo]) -> 14774.118 | M62: 1. Apanar los camarones "harina, huevo, panko" fritar.
B63: AJONJOLI NEGRO X 500GR | C63: g | D63: 1 | E63: 0 | F63: 1 | G63: =+VLOOKUP(Tabla1103453454455456479363848[[#This Row],[Ingrediente]],Tabla34[#All],3,0) -> 73.78 | H63: =+Tabla1103453454455456479363848[[#This Row],[Costo]]*Tabla1103453454455456479363848[[#This Row],[Columna2]] -> 73.78 | J63: MARGEN DE ERROR DEL 10% | K63: =+K62*10% -> 1477.4118 | M63: 2. Cortar la tilapia en cubos, agregar a un bol y desdoblar con Limón, de golpe incorporamos la cebolla, cilantro, maicitos, pasta de trufa, sal, pimienta, mezclar todo.
B64: CAMARON CRUDO 41-50 0% PORCIONX 7UND PAQUETE POR 10 PORCIONES | C64: uds | D64: 6 | E64: 0 | F64: 6 | G64: =+VLOOKUP(Tabla1103453454455456479363848[[#This Row],[Ingrediente]],Tabla34[#All],3,0) -> 514.28 | H64: =+Tabla1103453454455456479363848[[#This Row],[Costo]]*Tabla1103453454455456479363848[[#This Row],[Columna2]] -> 3085.68 | J64: COSTO + MARGEN ERROR | K64: =+K62+K63 -> 16251.53
B65: CEBOLLA PUERRO X KILO | C65: g | D65: 20 | E65: 40 | F65: 33.333 | G65: =+VLOOKUP(Tabla1103453454455456479363848[[#This Row],[Ingrediente]],Tabla34[#All],3,0) -> 6 | H65: =+Tabla1103453454455456479363848[[#This Row],[Costo]]*Tabla1103453454455456479363848[[#This Row],[Columna2]] -> 199.998 | J65: VALOR DE VENTA | K65: 52000 | M65: Emplatado
B66: FILETE DE TILAPIA FRESCA LO | C66: g | D66: 120 | E66: 10 | F66: 133.333 | G66: =+VLOOKUP(Tabla1103453454455456479363848[[#This Row],[Ingrediente]],Tabla34[#All],3,0) -> 39 | H66: =+Tabla1103453454455456479363848[[#This Row],[Costo]]*Tabla1103453454455456479363848[[#This Row],[Columna2]] -> 5199.987 | J66: IPOCONSUMO | K66: =+K65/1.08*0.08 -> 3851.8519 | M66: 1. En un plato hondo montar el ceviche en forma de pirámide.
B67: HARINA DE TRIGO HAZ DE OROS BOLSA X550g | C67: g | D67: 10 | E67: 0 | F67: 10 | G67: =+VLOOKUP(Tabla1103453454455456479363848[[#This Row],[Ingrediente]],Tabla34[#All],3,0) -> 4.2672 | H67: =+Tabla1103453454455456479363848[[#This Row],[Costo]]*Tabla1103453454455456479363848[[#This Row],[Columna2]] -> 42.672 | J67: VALOR ANTES DE IPO | K67: =+K65-K66 -> 48148.148 | M67: 2. Ubicar los camarones rodeando el ceviche.
B68: LIMON TAHITI X KILO | C68: g | D68: 40 | E68: 78 | F68: 181.818 | G68: =+VLOOKUP(Tabla1103453454455456479363848[[#This Row],[Ingrediente]],Tabla34[#All],3,0) -> 4.5 | H68: =+Tabla1103453454455456479363848[[#This Row],[Costo]]*Tabla1103453454455456479363848[[#This Row],[Columna2]] -> 818.181 | J68: MARGEN. | K68: =+K64/K67 -> 0.33753177 | M68: 3. Esparcir ajonjolí y coronar con puerro crocante.
B69: MAIZ EN GRANO MCCAIN X 1KG | C69: g | D69: 30 | E69: 0 | F69: 30 | G69: =+VLOOKUP(Tabla1103453454455456479363848[[#This Row],[Ingrediente]],Tabla34[#All],3,0) -> 18.6985 | H69: =+Tabla1103453454455456479363848[[#This Row],[Costo]]*Tabla1103453454455456479363848[[#This Row],[Columna2]] -> 560.955 | J69: GANANCIA | K69: =+K67-K64 -> 31896.618
B70: MIGA DE PAN PANKO BLANCO X 20 KILOS | C70: g | D70: 30 | E70: 0 | F70: 30 | G70: =+VLOOKUP(Tabla1103453454455456479363848[[#This Row],[Ingrediente]],Tabla34[#All],3,0) -> 13.02 | H70: =+Tabla1103453454455456479363848[[#This Row],[Costo]]*Tabla1103453454455456479363848[[#This Row],[Columna2]] -> 390.6 | J70: MARGEN PORCENTUAL | K70: =+K69/K64 -> 1.9626841
B71: NITRÃ“GENO LÃQUIDO | C71: g | D71: 30 | E71: 0 | F71: 30 | G71: =+VLOOKUP(Tabla1103453454455456479363848[[#This Row],[Ingrediente]],Tabla34[#All],3,0) -> 8.9 | H71: =+Tabla1103453454455456479363848[[#This Row],[Costo]]*Tabla1103453454455456479363848[[#This Row],[Columna2]] -> 267
B72: PIMIENTA NEGRA MOLIDA BADIA 453GR | C72: g | D72: 1 | E72: 0 | F72: 1 | G72: =+VLOOKUP(Tabla1103453454455456479363848[[#This Row],[Ingrediente]],Tabla34[#All],3,0) -> 57.218062 | H72: =+Tabla1103453454455456479363848[[#This Row],[Costo]]*Tabla1103453454455456479363848[[#This Row],[Columna2]] -> 57.218062
B73: SAL REFISAL X 1000G | C73: g | D73: 2 | E73: 0 | F73: 2 | G73: =+VLOOKUP(Tabla1103453454455456479363848[[#This Row],[Ingrediente]],Tabla34[#All],3,0) -> 2.401 | H73: =+Tabla1103453454455456479363848[[#This Row],[Costo]]*Tabla1103453454455456479363848[[#This Row],[Columna2]] -> 4.802
B74: SUB. HUEVO BATIDO | C74: g | D74: 40 | E74: 0 | F74: 40 | G74: =+VLOOKUP(Tabla1103453454455456479363848[[#This Row],[Ingrediente]],Tabla34[#All],3,0) -> 18.782609 | H74: =+Tabla1103453454455456479363848[[#This Row],[Costo]]*Tabla1103453454455456479363848[[#This Row],[Columna2]] -> 751.30435
B75: CEBOLLA BLANCA LIMPIA X KILO | C75: g | D75: 30 | E75: 10 | F75: 33.333 | G75: =+VLOOKUP(Tabla1103453454455456479363848[[#This Row],[Ingrediente]],Tabla34[#All],3,0) -> 2.8 | H75: =+Tabla1103453454455456479363848[[#This Row],[Costo]]*Tabla1103453454455456479363848[[#This Row],[Columna2]] -> 93.3324
B76: CEBOLLA MORADA LIMPIA | C76: g | D76: 30 | E76: 10 | F76: 33.333 | G76: =+VLOOKUP(Tabla1103453454455456479363848[[#This Row],[Ingrediente]],Tabla34[#All],3,0) -> 4.7 | H76: =+Tabla1103453454455456479363848[[#This Row],[Costo]]*Tabla1103453454455456479363848[[#This Row],[Columna2]] -> 156.6651
B77: ARMONIA TARTUFATA X 500 | C77: g | D77: 10 | E77: 0 | F77: 10 | G77: =+VLOOKUP(Tabla1103453454455456479363848[[#This Row],[Ingrediente]],Tabla34[#All],3,0) -> 202.104 | H77: =+Tabla1103453454455456479363848[[#This Row],[Costo]]*Tabla1103453454455456479363848[[#This Row],[Columna2]] -> 2021.04
B78: MAYONESA FRUCO GALON X3770G | C78: g | D78: 40 | E78: 0 | F78: 40 | G78: =+VLOOKUP(Tabla1103453454455456479363848[[#This Row],[Ingrediente]],Tabla34[#All],3,0) -> 26.272577 | H78: =+Tabla1103453454455456479363848[[#This Row],[Costo]]*Tabla1103453454455456479363848[[#This Row],[Columna2]] -> 1050.9031
H79: =SUBTOTAL(109,Tabla1103453454455456479363848[Total costo]) -> 14774.118
B81: CEVICHE ARENA BLANCA | J81: ANALISIS RECETA | M81: Preparacion
B82: Ingrediente | C82: Und | D82: Cant. | E82: Columna1 | F82: Columna2 | G82: Costo | H82: Total costo | J82: COSTO DEL PLATO | K82: =SUM(Tabla1103453454455456479363949[Total costo]) -> 11832.023 | M82: 1. Blanquear camarón y anillos de calamar.
B83: AGUACATE CHOCKETTE X KILO | C83: g | D83: 40 | E83: 25 | F83: 53.333 | G83: =+VLOOKUP(Tabla1103453454455456479363949[[#This Row],[Ingrediente]],Tabla34[#All],3,0) -> 8.5 | H83: =+Tabla1103453454455456479363949[[#This Row],[Costo]]*Tabla1103453454455456479363949[[#This Row],[Columna2]] -> 453.3305 | J83: MARGEN DE ERROR DEL 10% | K83: =+K82*10% -> 1183.2023 | M83: 2. En un bol incorporar el camarón y calamar blanqueados, zanahoria, tomate, cilantro en plus, mayo peruana, Limón, mezclar todo.
B84: AJO LIMPIO X KILO | C84: g | D84: 2 | E84: 13 | F84: 2.299 | G84: =+VLOOKUP(Tabla1103453454455456479363949[[#This Row],[Ingrediente]],Tabla34[#All],3,0) -> 19 | H84: =+Tabla1103453454455456479363949[[#This Row],[Costo]]*Tabla1103453454455456479363949[[#This Row],[Columna2]] -> 43.681 | J84: COSTO + MARGEN ERROR | K84: =+K82+K83 -> 13015.226 | M84: 3. Fritar papas criollas.
B85: SUB. TUBOS DE CALAMAR X 80G | C85: uds | D85: 1 | E85: 0 | F85: 1 | G85: =+VLOOKUP(Tabla1103453454455456479363949[[#This Row],[Ingrediente]],Tabla34[#All],3,0) -> 4196.75 | H85: =+Tabla1103453454455456479363949[[#This Row],[Costo]]*Tabla1103453454455456479363949[[#This Row],[Columna2]] -> 4196.75 | J85: VALOR DE VENTA | K85: 44000 | M85: cortar aguacate en cubos.
B86: CAMARON CRUDO 41-50 0% PORCIONX 7UND PAQUETE POR 10 PORCIONES | C86: uds | D86: 7 | E86: 0 | F86: 7 | G86: =+VLOOKUP(Tabla1103453454455456479363949[[#This Row],[Ingrediente]],Tabla34[#All],3,0) -> 514.28 | H86: =+Tabla1103453454455456479363949[[#This Row],[Costo]]*Tabla1103453454455456479363949[[#This Row],[Columna2]] -> 3599.96 | J86: IPOCONSUMO | K86: =+K85/1.08*0.08 -> 3259.2593
B87: CILANTRO LIMPIO X KILO | C87: g | D87: 3 | E87: 40 | F87: 5 | G87: =+VLOOKUP(Tabla1103453454455456479363949[[#This Row],[Ingrediente]],Tabla34[#All],3,0) -> 12 | H87: =+Tabla1103453454455456479363949[[#This Row],[Costo]]*Tabla1103453454455456479363949[[#This Row],[Columna2]] -> 60 | J87: VALOR ANTES DE IPO | K87: =+K85-K86 -> 40740.741 | M87: Emplatado
B88: LIMON TAHITI X KILO | C88: g | D88: 50 | E88: 78 | F88: 227.273 | G88: =+VLOOKUP(Tabla1103453454455456479363949[[#This Row],[Ingrediente]],Tabla34[#All],3,0) -> 4.5 | H88: =+Tabla1103453454455456479363949[[#This Row],[Costo]]*Tabla1103453454455456479363949[[#This Row],[Columna2]] -> 1022.7285 | J88: MARGEN. | K88: =+K84/K87 -> 0.31946463 | M88: 1. En un plato hondo poner la mezcla obtenida en el bol haciendo nunca pirámide.
B89: NITRÃ“GENO LÃQUIDO | C89: g | D89: 30 | E89: 0 | F89: 30 | G89: =+VLOOKUP(Tabla1103453454455456479363949[[#This Row],[Ingrediente]],Tabla34[#All],3,0) -> 8.9 | H89: =+Tabla1103453454455456479363949[[#This Row],[Costo]]*Tabla1103453454455456479363949[[#This Row],[Columna2]] -> 267 | J89: GANANCIA | K89: =+K87-K84 -> 27725.515 | M89: 2. Esparcir queso parmesano, distribuir los cubos de aguacate.
B90: PAPA CRIOLLA BALIN O CHIRIYA | C90: g | D90: 120 | E90: 5 | F90: 126.316 | G90: =+VLOOKUP(Tabla1103453454455456479363949[[#This Row],[Ingrediente]],Tabla34[#All],3,0) -> 4.5 | H90: =+Tabla1103453454455456479363949[[#This Row],[Costo]]*Tabla1103453454455456479363949[[#This Row],[Columna2]] -> 568.422 | J90: MARGEN PORCENTUAL | K90: =+K89/K84 -> 2.130237 | M90: 3. Poner las criollas en el costado formando una pirámide pequeña.
B91: PIMIENTA NEGRA MOLIDA BADIA 453GR | C91: g | D91: 1 | E91: 0 | F91: 1 | G91: =+VLOOKUP(Tabla1103453454455456479363949[[#This Row],[Ingrediente]],Tabla34[#All],3,0) -> 57.218062 | H91: =+Tabla1103453454455456479363949[[#This Row],[Costo]]*Tabla1103453454455456479363949[[#This Row],[Columna2]] -> 57.218062 | M91: 4. Finalizamos con topphing de puerro crocante.
B92: QUESO ALPINA PARMESANO RAYADO 2.5 L | C92: g | D92: 5 | E92: 0 | F92: 5 | G92: =+VLOOKUP(Tabla1103453454455456479363949[[#This Row],[Ingrediente]],Tabla34[#All],3,0) -> 60.9875 | H92: =+Tabla1103453454455456479363949[[#This Row],[Costo]]*Tabla1103453454455456479363949[[#This Row],[Columna2]] -> 304.9375
B93: SAL REFISAL X 1000G | C93: g | D93: 2 | E93: 0 | F93: 2 | G93: =+VLOOKUP(Tabla1103453454455456479363949[[#This Row],[Ingrediente]],Tabla34[#All],3,0) -> 2.401 | H93: =+Tabla1103453454455456479363949[[#This Row],[Costo]]*Tabla1103453454455456479363949[[#This Row],[Columna2]] -> 4.802
B94: SUB. BASE LECHE DE TIGRE MALANGA | C94: g | D94: 70 | E94: 0 | F94: 70 | G94: =+VLOOKUP(Tabla1103453454455456479363949[[#This Row],[Ingrediente]],Tabla34[#All],3,0) -> 8.624517 | H94: =+Tabla1103453454455456479363949[[#This Row],[Costo]]*Tabla1103453454455456479363949[[#This Row],[Columna2]] -> 603.71619
B95: SUB. PUERRO CROCANTE | C95: g | D95: 20 | E95: 0 | F95: 20 | G95: =+VLOOKUP(Tabla1103453454455456479363949[[#This Row],[Ingrediente]],Tabla34[#All],3,0) -> 18.392951 | H95: =+Tabla1103453454455456479363949[[#This Row],[Costo]]*Tabla1103453454455456479363949[[#This Row],[Columna2]] -> 367.85903
B96: TOMATE CHONTO X KILO | C96: g | D96: 20 | E96: 15 | F96: 23.529 | G96: =+VLOOKUP(Tabla1103453454455456479363949[[#This Row],[Ingrediente]],Tabla34[#All],3,0) -> 4 | H96: =+Tabla1103453454455456479363949[[#This Row],[Costo]]*Tabla1103453454455456479363949[[#This Row],[Columna2]] -> 94.116
B97: ZANAHORIA TRONCO X KILO | C97: g | D97: 20 | E97: 20 | F97: 25 | G97: =+VLOOKUP(Tabla1103453454455456479363949[[#This Row],[Ingrediente]],Tabla34[#All],3,0) -> 2.5 | H97: =+Tabla1103453454455456479363949[[#This Row],[Costo]]*Tabla1103453454455456479363949[[#This Row],[Columna2]] -> 62.5
B98: CEBOLLA BLANCA LIMPIA X KILO | C98: g | D98: 15 | E98: 10 | F98: 16.667 | G98: =+VLOOKUP(Tabla1103453454455456479363949[[#This Row],[Ingrediente]],Tabla34[#All],3,0) -> 2.8 | H98: =+Tabla1103453454455456479363949[[#This Row],[Costo]]*Tabla1103453454455456479363949[[#This Row],[Columna2]] -> 46.6676
B99: CEBOLLA MORADA LIMPIA | C99: g | D99: 15 | E99: 10 | F99: 16.667 | G99: =+VLOOKUP(Tabla1103453454455456479363949[[#This Row],[Ingrediente]],Tabla34[#All],3,0) -> 4.7 | H99: =+Tabla1103453454455456479363949[[#This Row],[Costo]]*Tabla1103453454455456479363949[[#This Row],[Columna2]] -> 78.3349
H100: =SUBTOTAL(109,Tabla1103453454455456479363949[Total costo]) -> 11832.023

Sheet LOS ARREBATOS DEL CHEF
B5: PESCA MALANGA | J5: ANALISIS RECETA | M5: Preparacion
B6: ArtÃ­culo | C6: Unidad Medida | D6: Unidades Netas | E6: % Merma | F6: Unidades | G6: Costo | H6: Total costo | J6: COSTO DEL PLATO | K6: =SUM(Tabla110345345445545647945586877869510811712713622823724627233260269297315316348494493497502[Total costo]) -> 23982.653 | M6: 1.Apanar los langostinos pasandolos por harina, huevo, queso costeño rallado y llevar a fritura profunda.
B7: FILETE DE ROBALO*200G | C7: uds | D7: 1 | E7: 0 | F7: 1 | G7: =+VLOOKUP(Tabla110345345445545647945586877869510811712713622823724627233260269297315316348494493497502[[#This Row],[ArtÃ­culo]],Tabla34[#All],3,0) -> 12500 | H7: =+Tabla110345345445545647945586877869510811712713622823724627233260269297315316348494493497502[[#This Row],[Costo]]*Tabla110345345445545647945586877869510811712713622823724627233260269297315316348494493497502[[#This Row],[Unidades]] -> 12500 | J7: MARGEN DE ERROR DEL 5% | K7: =+K6*5% -> 1199.1327 | M7: 2.Hidratar el pure de platano y agregarle queso mozzarella
B8: CAMARON CRUDO 41-50 0% PORCIONX 7UND PAQUETE POR 10 PORCIONES | C8: uds | D8: 7 | E8: 0 | F8: 7 | G8: =+VLOOKUP(Tabla110345345445545647945586877869510811712713622823724627233260269297315316348494493497502[[#This Row],[ArtÃ­culo]],Tabla34[#All],3,0) -> 514.28 | H8: =+Tabla110345345445545647945586877869510811712713622823724627233260269297315316348494493497502[[#This Row],[Costo]]*Tabla110345345445545647945586877869510811712713622823724627233260269297315316348494493497502[[#This Row],[Unidades]] -> 3599.96 | J8: COSTO + MARGEN ERROR | K8: =+K6+K7 -> 25181.786 | M8: 3.Para la salsa llevar a un wok o sartén crema de leche, queso azul, pasta de ajo, parmesano, salsa soya y cocinar hasta llegar a punto de napa.
B9: SUB. PASTA ROCOTO | C9: g | D9: 50 | E9: 0 | F9: 50 | G9: =+VLOOKUP(Tabla110345345445545647945586877869510811712713622823724627233260269297315316348494493497502[[#This Row],[ArtÃ­culo]],Tabla34[#All],3,0) -> 40.42512 | H9: =+Tabla110345345445545647945586877869510811712713622823724627233260269297315316348494493497502[[#This Row],[Costo]]*Tabla110345345445545647945586877869510811712713622823724627233260269297315316348494493497502[[#This Row],[Unidades]] -> 2021.256 | J9: VALOR DE VENTA | K9: 63000
B10: CREMA DE COCO ROLAND X 960 GR | C10: g | D10: 30 | E10: 0 | F10: 30 | G10: =+VLOOKUP(Tabla110345345445545647945586877869510811712713622823724627233260269297315316348494493497502[[#This Row],[ArtÃ­culo]],Tabla34[#All],3,0) -> 39.071701 | H10: =+Tabla110345345445545647945586877869510811712713622823724627233260269297315316348494493497502[[#This Row],[Costo]]*Tabla110345345445545647945586877869510811712713622823724627233260269297315316348494493497502[[#This Row],[Unidades]] -> 1172.151 | J10: IPOCONSUMO | K10: =+K9/1.08*0.08 -> 4666.6667 | M10: Emplatado
B11: AGUACATE CHOCKETTE X KILO | C11: g | D11: 100 | E11: 25 | F11: 133.333 | G11: =+VLOOKUP(Tabla110345345445545647945586877869510811712713622823724627233260269297315316348494493497502[[#This Row],[ArtÃ­culo]],Tabla34[#All],3,0) -> 8.5 | H11: =+Tabla110345345445545647945586877869510811712713622823724627233260269297315316348494493497502[[#This Row],[Costo]]*Tabla110345345445545647945586877869510811712713622823724627233260269297315316348494493497502[[#This Row],[Unidades]] -> 1133.3305 | J11: VALOR ANTES DE IPO | K11: =+K9-K10 -> 58333.333
B12: CREMA DE LECHE X 9700G | C12: g | D12: 50 | E12: 0 | F12: 50 | G12: =+VLOOKUP(Tabla110345345445545647945586877869510811712713622823724627233260269297315316348494493497502[[#This Row],[ArtÃ­culo]],Tabla34[#All],3,0) -> 19.804167 | H12: =+Tabla110345345445545647945586877869510811712713622823724627233260269297315316348494493497502[[#This Row],[Costo]]*Tabla110345345445545647945586877869510811712713622823724627233260269297315316348494493497502[[#This Row],[Unidades]] -> 990.20833 | J12: MARGEN. | K12: =+K8/K11 -> 0.43168776
B13: SUB. ARROZ COCIDO | C13: g | D13: 150 | E13: 0 | F13: 150 | G13: =+VLOOKUP(Tabla110345345445545647945586877869510811712713622823724627233260269297315316348494493497502[[#This Row],[ArtÃ­culo]],Tabla34[#All],3,0) -> 5.8053972 | H13: =+Tabla110345345445545647945586877869510811712713622823724627233260269297315316348494493497502[[#This Row],[Costo]]*Tabla110345345445545647945586877869510811712713622823724627233260269297315316348494493497502[[#This Row],[Unidades]] -> 870.80957 | J13: GANANCIA | K13: =+K11-K8 -> 33151.547
B14: QUESO ALPINA PARMESANO RAYADO 2.5 L | C14: g | D14: 10 | E14: 0 | F14: 10 | G14: =+VLOOKUP(Tabla110345345445545647945586877869510811712713622823724627233260269297315316348494493497502[[#This Row],[ArtÃ­culo]],Tabla34[#All],3,0) -> 60.9875 | H14: =+Tabla110345345445545647945586877869510811712713622823724627233260269297315316348494493497502[[#This Row],[Costo]]*Tabla110345345445545647945586877869510811712713622823724627233260269297315316348494493497502[[#This Row],[Unidades]] -> 609.875 | J14: MARGEN PORCENTUAL | K14: =+K13/K8 -> 1.3164891
B15: BROTES DE RABANO 50 | C15: g | D15: 1 | E15: 0 | F15: 1 | G15: =+VLOOKUP(Tabla110345345445545647945586877869510811712713622823724627233260269297315316348494493497502[[#This Row],[ArtÃ­culo]],Tabla34[#All],3,0) -> 307.5 | H15: =+Tabla110345345445545647945586877869510811712713622823724627233260269297315316348494493497502[[#This Row],[Costo]]*Tabla110345345445545647945586877869510811712713622823724627233260269297315316348494493497502[[#This Row],[Unidades]] -> 307.5
B16: SUB. MAYONESA DE MARACUYA | C16: g | D16: 10 | E16: 0 | F16: 10 | G16: =+VLOOKUP(Tabla110345345445545647945586877869510811712713622823724627233260269297315316348494493497502[[#This Row],[ArtÃ­culo]],Tabla34[#All],3,0) -> 30.254664 | H16: =+Tabla110345345445545647945586877869510811712713622823724627233260269297315316348494493497502[[#This Row],[Costo]]*Tabla110345345445545647945586877869510811712713622823724627233260269297315316348494493497502[[#This Row],[Unidades]] -> 302.54664
B17: TOMATE CHERRY X KILO | C17: g | D17: 20 | E17: 0 | F17: 20 | G17: =+VLOOKUP(Tabla110345345445545647945586877869510811712713622823724627233260269297315316348494493497502[[#This Row],[ArtÃ­culo]],Tabla34[#All],3,0) -> 11 | H17: =+Tabla110345345445545647945586877869510811712713622823724627233260269297315316348494493497502[[#This Row],[Costo]]*Tabla110345345445545647945586877869510811712713622823724627233260269297315316348494493497502[[#This Row],[Unidades]] -> 220
B18: CEBOLLA MORADA LIMPIA | C18: g | D18: 15 | E18: 25 | F18: 20 | G18: =+VLOOKUP(Tabla110345345445545647945586877869510811712713622823724627233260269297315316348494493497502[[#This Row],[ArtÃ­culo]],Tabla34[#All],3,0) -> 4.7 | H18: =+Tabla110345345445545647945586877869510811712713622823724627233260269297315316348494493497502[[#This Row],[Costo]]*Tabla110345345445545647945586877869510811712713622823724627233260269297315316348494493497502[[#This Row],[Unidades]] -> 94
B19: PIMIENTA NEGRA MOLIDA BADIA 453GR | C19: g | D19: 1 | E19: 0 | F19: 1 | G19: =+VLOOKUP(Tabla110345345445545647945586877869510811712713622823724627233260269297315316348494493497502[[#This Row],[ArtÃ­culo]],Tabla34[#All],3,0) -> 57.218062 | H19: =+Tabla110345345445545647945586877869510811712713622823724627233260269297315316348494493497502[[#This Row],[Costo]]*Tabla110345345445545647945586877869510811712713622823724627233260269297315316348494493497502[[#This Row],[Unidades]] -> 57.218062
B20: SUB. PASTA DE AJO | C20: g | D20: 3 | E20: 0 | F20: 3 | G20: =+VLOOKUP(Tabla110345345445545647945586877869510811712713622823724627233260269297315316348494493497502[[#This Row],[ArtÃ­culo]],Tabla34[#All],3,0) -> 14.257835 | H20: =+Tabla110345345445545647945586877869510811712713622823724627233260269297315316348494493497502[[#This Row],[Costo]]*Tabla110345345445545647945586877869510811712713622823724627233260269297315316348494493497502[[#This Row],[Unidades]] -> 42.773506
